Workbook
Name ANZ_Breite: #REF!
Name ANZ_Elemente: #REF!
Name ANZ_Höhe: #REF!
Name ANZ_Tiefe: #REF!
Name Bericht: #REF!
Name Gewicht_Klappe: #REF!
Name Gewicht_Platte: #REF!
Name Gewicht_Profil: #REF!
Name Gewicht_Scharnier: #REF!
Name Gewicht_Schubkasten: #REF!
Name Konfektion: #REF!
Name PL_CHF_Faktor: Preisliste_Tische!$G$2
Name PL_Inflation: Preisliste_Tische!$C$2
Name PL_Jahre: Preisliste_Tische!$E$2
Name Preise_Profil46: Preisliste_Tische!$B$6:$H$18
Name Preise_Tischplatten: Preisliste_Tische!$B$22:$L$32
Name Rabatt: #REF!
Name Tiefe: #REF!
Name Tischnamen: Preisliste_Tische!$C$22:$C$32
Name Vertrieb: #REF!
Name Zusatzrabatt: #REF!

Sheet Statistik
A1: Preisvergleich nach Preisgruppe – Typ: Platte (EUR)
A2: Alle Preise in EUR exkl. MwSt. | PG1 = MDF | PG2 = Furnier | PG3 = Alu | PG4 = Glas
A4: Art.-Nr. | B4: Kategorie | C4: Bezeichnung | D4: Breite (mm) | E4: Tiefe (mm) | F4: PG1 MDF | G4: PG2 Furnier | H4: PG3 Alu | I4: PG4 Glas | J4: PG2/PG1 (Furnier vs. MDF) | K4: PG3/PG1 (Alu vs. MDF) | L4: PG4/PG1 (Glas vs. MDF) | M4: PG3/PG2 (Alu vs. Furnier) | N4: PG4/PG2 (Glas vs. Furnier) | O4: PG4/PG3 (Glas vs. Alu) | P4: Ø Preis EUR
A5: 3000 | B5: =IFERROR(_xlfn.XLOOKUP(A5,Aktiv!$A:$A,Aktiv!$C:$C,"–"),"") -> Boden | C5: =IFERROR(_xlfn.XLOOKUP(A5,Aktiv!$A:$A,Aktiv!$D:$D,"–"),"") -> Boden (360x360) | D5: =IFERROR(_xlfn.XLOOKUP(A5,Aktiv!$A:$A,Aktiv!$E:$E,"–"),"") -> 360 | E5: =IFERROR(_xlfn.XLOOKUP(A5,Aktiv!$A:$A,Aktiv!$F:$F,"–"),"") -> 360 | F5: =IFERROR(_xlfn.XLOOKUP(A5,Aktiv!$A:$A,Aktiv!$G:$G,"–"),"") -> 25 | G5: =IFERROR(_xlfn.XLOOKUP(A5,Aktiv!$A:$A,Aktiv!$H:$H,"–"),"") -> 103 | H5: =IFERROR(_xlfn.XLOOKUP(A5,Aktiv!$A:$A,Aktiv!$I:$I,"–"),"") -> 120 | I5: =IFERROR(_xlfn.XLOOKUP(A5,Aktiv!$A:$A,Aktiv!$J:$J,"–"),"") -> 145 | J5: =IFERROR(IF(OR(F5=0,G5=0,F5="",G5=""),"-",(G5-F5)/F5),"–") -> 3.12 | K5: =IFERROR(IF(OR(F5=0,H5=0,F5="",H5=""),"-",(H5-F5)/F5),"–") -> 3.8 | L5: =IFERROR(IF(OR(F5=0,I5=0,F5="",I5=""),"-",(I5-F5)/F5),"–") -> 4.8 | M5: =IFERROR(IF(OR(G5=0,H5=0,G5="",H5=""),"-",(H5-G5)/G5),"–") -> 0.16504854 | N5: =IFERROR(IF(OR(G5=0,I5=0,G5="",I5=""),"-",(I5-G5)/G5),"–") -> 0.40776699 | O5: =IFERROR(IF(OR(H5=0,I5=0,H5="",I5=""),"-",(I5-H5)/H5),"–") -> 0.20833333 | P5: =IFERROR(ROUND(AVERAGEIF(F5:I5,"<>0"),0),"–") -> 98
A6: 3001 | B6: =IFERROR(_xlfn.XLOOKUP(A6,Aktiv!$A:$A,Aktiv!$C:$C,"–"),"") -> Boden | C6: =IFERROR(_xlfn.XLOOKUP(A6,Aktiv!$A:$A,Aktiv!$D:$D,"–"),"") -> Boden (420x360) | D6: =IFERROR(_xlfn.XLOOKUP(A6,Aktiv!$A:$A,Aktiv!$E:$E,"–"),"") -> 420 | E6: =IFERROR(_xlfn.XLOOKUP(A6,Aktiv!$A:$A,Aktiv!$F:$F,"–"),"") -> 360 | F6: =IFERROR(_xlfn.XLOOKUP(A6,Aktiv!$A:$A,Aktiv!$G:$G,"–"),"") -> 27 | G6: =IFERROR(_xlfn.XLOOKUP(A6,Aktiv!$A:$A,Aktiv!$H:$H,"–"),"") -> 103 | H6: =IFERROR(_xlfn.XLOOKUP(A6,Aktiv!$A:$A,Aktiv!$I:$I,"–"),"") -> 120 | I6: =IFERROR(_xlfn.XLOOKUP(A6,Aktiv!$A:$A,Aktiv!$J:$J,"–"),"") -> 145 | J6: =IFERROR(IF(OR(F6=0,G6=0,F6="",G6=""),"-",(G6-F6)/F6),"–") -> 2.8148148 | K6: =IFERROR(IF(OR(F6=0,H6=0,F6="",H6=""),"-",(H6-F6)/F6),"–") -> 3.4444444 | L6: =IFERROR(IF(OR(F6=0,I6=0,F6="",I6=""),"-",(I6-F6)/F6),"–") -> 4.3703704 | M6: =IFERROR(IF(OR(G6=0,H6=0,G6="",H6=""),"-",(H6-G6)/G6),"–") -> 0.16504854 | N6: =IFERROR(IF(OR(G6=0,I6=0,G6="",I6=""),"-",(I6-G6)/G6),"–") -> 0.40776699 | O6: =IFERROR(IF(OR(H6=0,I6=0,H6="",I6=""),"-",(I6-H6)/H6),"–") -> 0.20833333 | P6: =IFERROR(ROUND(AVERAGEIF(F6:I6,"<>0"),0),"–") -> 99
A7: 3002 | B7: =IFERROR(_xlfn.XLOOKUP(A7,Aktiv!$A:$A,Aktiv!$C:$C,"–"),"") -> Boden | C7: =IFERROR(_xlfn.XLOOKUP(A7,Aktiv!$A:$A,Aktiv!$D:$D,"–"),"") -> Boden (580x360) | D7: =IFERROR(_xlfn.XLOOKUP(A7,Aktiv!$A:$A,Aktiv!$E:$E,"–"),"") -> 580 | E7: =IFERROR(_xlfn.XLOOKUP(A7,Aktiv!$A:$A,Aktiv!$F:$F,"–"),"") -> 360 | F7: =IFERROR(_xlfn.XLOOKUP(A7,Aktiv!$A:$A,Aktiv!$G:$G,"–"),"") -> 37 | G7: =IFERROR(_xlfn.XLOOKUP(A7,Aktiv!$A:$A,Aktiv!$H:$H,"–"),"") -> 126 | H7: =IFERROR(_xlfn.XLOOKUP(A7,Aktiv!$A:$A,Aktiv!$I:$I,"–"),"") -> 131 | I7: =IFERROR(_xlfn.XLOOKUP(A7,Aktiv!$A:$A,Aktiv!$J:$J,"–"),"") -> 146 | J7: =IFERROR(IF(OR(F7=0,G7=0,F7="",G7=""),"-",(G7-F7)/F7),"–") -> 2.4054054 | K7: =IFERROR(IF(OR(F7=0,H7=0,F7="",H7=""),"-",(H7-F7)/F7),"–") -> 2.5405405 | L7: =IFERROR(IF(OR(F7=0,I7=0,F7="",I7=""),"-",(I7-F7)/F7),"–") -> 2.9459459 | M7: =IFERROR(IF(OR(G7=0,H7=0,G7="",H7=""),"-",(H7-G7)/G7),"–") -> 0.03968254 | N7: =IFERROR(IF(OR(G7=0,I7=0,G7="",I7=""),"-",(I7-G7)/G7),"–") -> 0.15873016 | O7: =IFERROR(IF(OR(H7=0,I7=0,H7="",I7=""),"-",(I7-H7)/H7),"–") -> 0.11450382 | P7: =IFERROR(ROUND(AVERAGEIF(F7:I7,"<>0"),0),"–") -> 110
A8: 3003 | B8: =IFERROR(_xlfn.XLOOKUP(A8,Aktiv!$A:$A,Aktiv!$C:$C,"–"),"") -> Boden | C8: =IFERROR(_xlfn.XLOOKUP(A8,Aktiv!$A:$A,Aktiv!$D:$D,"–"),"") -> Boden (780x360) | D8: =IFERROR(_xlfn.XLOOKUP(A8,Aktiv!$A:$A,Aktiv!$E:$E,"–"),"") -> 780 | E8: =IFERROR(_xlfn.XLOOKUP(A8,Aktiv!$A:$A,Aktiv!$F:$F,"–"),"") -> 360 | F8: =IFERROR(_xlfn.XLOOKUP(A8,Aktiv!$A:$A,Aktiv!$G:$G,"–"),"") -> 49 | G8: =IFERROR(_xlfn.XLOOKUP(A8,Aktiv!$A:$A,Aktiv!$H:$H,"–"),"") -> 169 | H8: =IFERROR(_xlfn.XLOOKUP(A8,Aktiv!$A:$A,Aktiv!$I:$I,"–"),"") -> 177 | I8: =IFERROR(_xlfn.XLOOKUP(A8,Aktiv!$A:$A,Aktiv!$J:$J,"–"),"") -> 196 | J8: =IFERROR(IF(OR(F8=0,G8=0,F8="",G8=""),"-",(G8-F8)/F8),"–") -> 2.4489796 | K8: =IFERROR(IF(OR(F8=0,H8=0,F8="",H8=""),"-",(H8-F8)/F8),"–") -> 2.6122449 | L8: =IFERROR(IF(OR(F8=0,I8=0,F8="",I8=""),"-",(I8-F8)/F8),"–") -> 3 | M8: =IFERROR(IF(OR(G8=0,H8=0,G8="",H8=""),"-",(H8-G8)/G8),"–") -> 0.047337278 | N8: =IFERROR(IF(OR(G8=0,I8=0,G8="",I8=""),"-",(I8-G8)/G8),"–") -> 0.15976331 | O8: =IFERROR(IF(OR(H8=0,I8=0,H8="",I8=""),"-",(I8-H8)/H8),"–") -> 0.10734463 | P8: =IFERROR(ROUND(AVERAGEIF(F8:I8,"<>0"),0),"–") -> 148
A9: 3004 | B9: =IFERROR(_xlfn.XLOOKUP(A9,Aktiv!$A:$A,Aktiv!$C:$C,"–"),"") -> Boden | C9: =IFERROR(_xlfn.XLOOKUP(A9,Aktiv!$A:$A,Aktiv!$D:$D,"–"),"") -> Boden (980x360) | D9: =IFERROR(_xlfn.XLOOKUP(A9,Aktiv!$A:$A,Aktiv!$E:$E,"–"),"") -> 980 | E9: =IFERROR(_xlfn.XLOOKUP(A9,Aktiv!$A:$A,Aktiv!$F:$F,"–"),"") -> 360 | F9: =IFERROR(_xlfn.XLOOKUP(A9,Aktiv!$A:$A,Aktiv!$G:$G,"–"),"") -> 62 | G9: =IFERROR(_xlfn.XLOOKUP(A9,Aktiv!$A:$A,Aktiv!$H:$H,"–"),"") -> 213 | H9: =IFERROR(_xlfn.XLOOKUP(A9,Aktiv!$A:$A,Aktiv!$I:$I,"–"),"") -> 222 | I9: =IFERROR(_xlfn.XLOOKUP(A9,Aktiv!$A:$A,Aktiv!$J:$J,"–"),"") -> 247 | J9: =IFERROR(IF(OR(F9=0,G9=0,F9="",G9=""),"-",(G9-F9)/F9),"–") -> 2.4354839 | K9: =IFERROR(IF(OR(F9=0,H9=0,F9="",H9=""),"-",(H9-F9)/F9),"–") -> 2.5806452 | L9: =IFERROR(IF(OR(F9=0,I9=0,F9="",I9=""),"-",(I9-F9)/F9),"–") -> 2.983871 | M9: =IFERROR(IF(OR(G9=0,H9=0,G9="",H9=""),"-",(H9-G9)/G9),"–") -> 0.042253521 | N9: =IFERROR(IF(OR(G9=0,I9=0,G9="",I9=""),"-",(I9-G9)/G9),"–") -> 0.15962441 | O9: =IFERROR(IF(OR(H9=0,I9=0,H9="",I9=""),"-",(I9-H9)/H9),"–") -> 0.11261261 | P9: =IFERROR(ROUND(AVERAGEIF(F9:I9,"<>0"),0),"–") -> 186
A10: 3005 | B10: =IFERROR(_xlfn.XLOOKUP(A10,Aktiv!$A:$A,Aktiv!$C:$C,"–"),"") -> Boden | C10: =IFERROR(_xlfn.XLOOKUP(A10,Aktiv!$A:$A,Aktiv!$D:$D,"–"),"") -> Boden (360x580) | D10: =IFERROR(_xlfn.XLOOKUP(A10,Aktiv!$A:$A,Aktiv!$E:$E,"–"),"") -> 360 | E10: =IFERROR(_xlfn.XLOOKUP(A10,Aktiv!$A:$A,Aktiv!$F:$F,"–"),"") -> 580 | F10: =IFERROR(_xlfn.XLOOKUP(A10,Aktiv!$A:$A,Aktiv!$G:$G,"–"),"") -> 37 | G10: =IFERROR(_xlfn.XLOOKUP(A10,Aktiv!$A:$A,Aktiv!$H:$H,"–"),"") -> 126 | H10: =IFERROR(_xlfn.XLOOKUP(A10,Aktiv!$A:$A,Aktiv!$I:$I,"–"),"") -> 131 | I10: =IFERROR(_xlfn.XLOOKUP(A10,Aktiv!$A:$A,Aktiv!$J:$J,"–"),"") -> 146 | J10: =IFERROR(IF(OR(F10=0,G10=0,F10="",G10=""),"-",(G10-F10)/F10),"–") -> 2.4054054 | K10: =IFERROR(IF(OR(F10=0,H10=0,F10="",H10=""),"-",(H10-F10)/F10),"–") -> 2.5405405 | L10: =IFERROR(IF(OR(F10=0,I10=0,F10="",I10=""),"-",(I10-F10)/F10),"–") -> 2.9459459 | M10: =IFERROR(IF(OR(G10=0,H10=0,G10="",H10=""),"-",(H10-G10)/G10),"–") -> 0.03968254 | N10: =IFERROR(IF(OR(G10=0,I10=0,G10="",I10=""),"-",(I10-G10)/G10),"–") -> 0.15873016 | O10: =IFERROR(IF(OR(H10=0,I10=0,H10="",I10=""),"-",(I10-H10)/H10),"–") -> 0.11450382 | P10: =IFERROR(ROUND(AVERAGEIF(F10:I10,"<>0"),0),"–") -> 110
A11: 3006 | B11: =IFERROR(_xlfn.XLOOKUP(A11,Aktiv!$A:$A,Aktiv!$C:$C,"–"),"") -> Boden | C11: =IFERROR(_xlfn.XLOOKUP(A11,Aktiv!$A:$A,Aktiv!$D:$D,"–"),"") -> Boden (420x580) | D11: =IFERROR(_xlfn.XLOOKUP(A11,Aktiv!$A:$A,Aktiv!$E:$E,"–"),"") -> 420 | E11: =IFERROR(_xlfn.XLOOKUP(A11,Aktiv!$A:$A,Aktiv!$F:$F,"–"),"") -> 580 | F11: =IFERROR(_xlfn.XLOOKUP(A11,Aktiv!$A:$A,Aktiv!$G:$G,"–"),"") -> 43 | G11: =IFERROR(_xlfn.XLOOKUP(A11,Aktiv!$A:$A,Aktiv!$H:$H,"–"),"") -> 147 | H11: =IFERROR(_xlfn.XLOOKUP(A11,Aktiv!$A:$A,Aktiv!$I:$I,"–"),"") -> 153 | I11: =IFERROR(_xlfn.XLOOKUP(A11,Aktiv!$A:$A,Aktiv!$J:$J,"–"),"") -> 170 | J11: =IFERROR(IF(OR(F11=0,G11=0,F11="",G11=""),"-",(G11-F11)/F11),"–") -> 2.4186047 | K11: =IFERROR(IF(OR(F11=0,H11=0,F11="",H11=""),"-",(H11-F11)/F11),"–") -> 2.5581395 | L11: =IFERROR(IF(OR(F11=0,I11=0,F11="",I11=""),"-",(I11-F11)/F11),"–") -> 2.9534884 | M11: =IFERROR(IF(OR(G11=0,H11=0,G11="",H11=""),"-",(H11-G11)/G11),"–") -> 0.040816327 | N11: =IFERROR(IF(OR(G11=0,I11=0,G11="",I11=""),"-",(I11-G11)/G11),"–") -> 0.15646259 | O11: =IFERROR(IF(OR(H11=0,I11=0,H11="",I11=""),"-",(I11-H11)/H11),"–") -> 0.11111111 | P11: =IFERROR(ROUND(AVERAGEIF(F11:I11,"<>0"),0),"–") -> 128
A12: 3007 | B12: =IFERROR(_xlfn.XLOOKUP(A12,Aktiv!$A:$A,Aktiv!$C:$C,"–"),"") -> Boden | C12: =IFERROR(_xlfn.XLOOKUP(A12,Aktiv!$A:$A,Aktiv!$D:$D,"–"),"") -> Boden (580x580) | D12: =IFERROR(_xlfn.XLOOKUP(A12,Aktiv!$A:$A,Aktiv!$E:$E,"–"),"") -> 580 | E12: =IFERROR(_xlfn.XLOOKUP(A12,Aktiv!$A:$A,Aktiv!$F:$F,"–"),"") -> 580 | F12: =IFERROR(_xlfn.XLOOKUP(A12,Aktiv!$A:$A,Aktiv!$G:$G,"–"),"") -> 59 | G12: =IFERROR(_xlfn.XLOOKUP(A12,Aktiv!$A:$A,Aktiv!$H:$H,"–"),"") -> 203 | H12: =IFERROR(_xlfn.XLOOKUP(A12,Aktiv!$A:$A,Aktiv!$I:$I,"–"),"") -> 211 | I12: =IFERROR(_xlfn.XLOOKUP(A12,Aktiv!$A:$A,Aktiv!$J:$J,"–"),"") -> 235 | J12: =IFERROR(IF(OR(F12=0,G12=0,F12="",G12=""),"-",(G12-F12)/F12),"–") -> 2.440678 | K12: =IFERROR(IF(OR(F12=0,H12=0,F12="",H12=""),"-",(H12-F12)/F12),"–") -> 2.5762712 | L12: =IFERROR(IF(OR(F12=0,I12=0,F12="",I12=""),"-",(I12-F12)/F12),"–") -> 2.9830508 | M12: =IFERROR(IF(OR(G12=0,H12=0,G12="",H12=""),"-",(H12-G12)/G12),"–") -> 0.039408867 | N12: =IFERROR(IF(OR(G12=0,I12=0,G12="",I12=""),"-",(I12-G12)/G12),"–") -> 0.15763547 | O12: =IFERROR(IF(OR(H12=0,I12=0,H12="",I12=""),"-",(I12-H12)/H12),"–") -> 0.11374408 | P12: =IFERROR(ROUND(AVERAGEIF(F12:I12,"<>0"),0),"–") -> 177
A13: 3008 | B13: =IFERROR(_xlfn.XLOOKUP(A13,Aktiv!$A:$A,Aktiv!$C:$C,"–"),"") -> Boden | C13: =IFERROR(_xlfn.XLOOKUP(A13,Aktiv!$A:$A,Aktiv!$D:$D,"–"),"") -> Boden (780x580) | D13: =IFERROR(_xlfn.XLOOKUP(A13,Aktiv!$A:$A,Aktiv!$E:$E,"–"),"") -> 780 | E13: =IFERROR(_xlfn.XLOOKUP(A13,Aktiv!$A:$A,Aktiv!$F:$F,"–"),"") -> 580 | F13: =IFERROR(_xlfn.XLOOKUP(A13,Aktiv!$A:$A,Aktiv!$G:$G,"–"),"") -> 80 | G13: =IFERROR(_xlfn.XLOOKUP(A13,Aktiv!$A:$A,Aktiv!$H:$H,"–"),"") -> 273 | H13: =IFERROR(_xlfn.XLOOKUP(A13,Aktiv!$A:$A,Aktiv!$I:$I,"–"),"") -> 284 | I13: =IFERROR(_xlfn.XLOOKUP(A13,Aktiv!$A:$A,Aktiv!$J:$J,"–"),"") -> 316 | J13: =IFERROR(IF(OR(F13=0,G13=0,F13="",G13=""),"-",(G13-F13)/F13),"–") -> 2.4125 | K13: =IFERROR(IF(OR(F13=0,H13=0,F13="",H13=""),"-",(H13-F13)/F13),"–") -> 2.55 | L13: =IFERROR(IF(OR(F13=0,I13=0,F13="",I13=""),"-",(I13-F13)/F13),"–") -> 2.95 | M13: =IFERROR(IF(OR(G13=0,H13=0,G13="",H13=""),"-",(H13-G13)/G13),"–") -> 0.04029304 | N13: =IFERROR(IF(OR(G13=0,I13=0,G13="",I13=""),"-",(I13-G13)/G13),"–") -> 0.15750916 | O13: =IFERROR(IF(OR(H13=0,I13=0,H13="",I13=""),"-",(I13-H13)/H13),"–") -> 0.11267606 | P13: =IFERROR(ROUND(AVERAGEIF(F13:I13,"<>0"),0),"–") -> 238
A14: 3009 | B14: =IFERROR(_xlfn.XLOOKUP(A14,Aktiv!$A:$A,Aktiv!$C:$C,"–"),"") -> Boden | C14: =IFERROR(_xlfn.XLOOKUP(A14,Aktiv!$A:$A,Aktiv!$D:$D,"–"),"") -> Boden (980x580) | D14: =IFERROR(_xlfn.XLOOKUP(A14,Aktiv!$A:$A,Aktiv!$E:$E,"–"),"") -> 980 | E14: =IFERROR(_xlfn.XLOOKUP(A14,Aktiv!$A:$A,Aktiv!$F:$F,"–"),"") -> 580 | F14: =IFERROR(_xlfn.XLOOKUP(A14,Aktiv!$A:$A,Aktiv!$G:$G,"–"),"") -> 100 | G14: =IFERROR(_xlfn.XLOOKUP(A14,Aktiv!$A:$A,Aktiv!$H:$H,"–"),"") -> 343 | H14: =IFERROR(_xlfn.XLOOKUP(A14,Aktiv!$A:$A,Aktiv!$I:$I,"–"),"") -> 357 | I14: =IFERROR(_xlfn.XLOOKUP(A14,Aktiv!$A:$A,Aktiv!$J:$J,"–"),"") -> 398 | J14: =IFERROR(IF(OR(F14=0,G14=0,F14="",G14=""),"-",(G14-F14)/F14),"–") -> 2.43 | K14: =IFERROR(IF(OR(F14=0,H14=0,F14="",H14=""),"-",(H14-F14)/F14),"–") -> 2.57 | L14: =IFERROR(IF(OR(F14=0,I14=0,F14="",I14=""),"-",(I14-F14)/F14),"–") -> 2.98 | M14: =IFERROR(IF(OR(G14=0,H14=0,G14="",H14=""),"-",(H14-G14)/G14),"–") -> 0.040816327 | N14: =IFERROR(IF(OR(G14=0,I14=0,G14="",I14=""),"-",(I14-G14)/G14),"–") -> 0.16034985 | O14: =IFERROR(IF(OR(H14=0,I14=0,H14="",I14=""),"-",(I14-H14)/H14),"–") -> 0.11484594 | P14: =IFERROR(ROUND(AVERAGEIF(F14:I14,"<>0"),0),"–") -> 300
A15: 3010 | B15: =IFERROR(_xlfn.XLOOKUP(A15,Aktiv!$A:$A,Aktiv!$C:$C,"–"),"") -> Boden | C15: =IFERROR(_xlfn.XLOOKUP(A15,Aktiv!$A:$A,Aktiv!$D:$D,"–"),"") -> Boden (780x780) | D15: =IFERROR(_xlfn.XLOOKUP(A15,Aktiv!$A:$A,Aktiv!$E:$E,"–"),"") -> 780 | E15: =IFERROR(_xlfn.XLOOKUP(A15,Aktiv!$A:$A,Aktiv!$F:$F,"–"),"") -> 780 | F15: =IFERROR(_xlfn.XLOOKUP(A15,Aktiv!$A:$A,Aktiv!$G:$G,"–"),"") -> 107 | G15: =IFERROR(_xlfn.XLOOKUP(A15,Aktiv!$A:$A,Aktiv!$H:$H,"–"),"") -> 367 | H15: =IFERROR(_xlfn.XLOOKUP(A15,Aktiv!$A:$A,Aktiv!$I:$I,"–"),"") -> 382 | I15: =IFERROR(_xlfn.XLOOKUP(A15,Aktiv!$A:$A,Aktiv!$J:$J,"–"),"") -> 426 | J15: =IFERROR(IF(OR(F15=0,G15=0,F15="",G15=""),"-",(G15-F15)/F15),"–") -> 2.4299065 | K15: =IFERROR(IF(OR(F15=0,H15=0,F15="",H15=""),"-",(H15-F15)/F15),"–") -> 2.5700935 | L15: =IFERROR(IF(OR(F15=0,I15=0,F15="",I15=""),"-",(I15-F15)/F15),"–") -> 2.9813084 | M15: =IFERROR(IF(OR(G15=0,H15=0,G15="",H15=""),"-",(H15-G15)/G15),"–") -> 0.040871935 | N15: =IFERROR(IF(OR(G15=0,I15=0,G15="",I15=""),"-",(I15-G15)/G15),"–") -> 0.16076294 | O15: =IFERROR(IF(OR(H15=0,I15=0,H15="",I15=""),"-",(I15-H15)/H15),"–") -> 0.11518325 | P15: =IFERROR(ROUND(AVERAGEIF(F15:I15,"<>0"),0),"–") -> 321
A16: 3011 | B16: =IFERROR(_xlfn.XLOOKUP(A16,Aktiv!$A:$A,Aktiv!$C:$C,"–"),"") -> Boden | C16: =IFERROR(_xlfn.XLOOKUP(A16,Aktiv!$A:$A,Aktiv!$D:$D,"–"),"") -> Boden (980x780) | D16: =IFERROR(_xlfn.XLOOKUP(A16,Aktiv!$A:$A,Aktiv!$E:$E,"–"),"") -> 980 | E16: =IFERROR(_xlfn.XLOOKUP(A16,Aktiv!$A:$A,Aktiv!$F:$F,"–"),"") -> 780 | F16: =IFERROR(_xlfn.XLOOKUP(A16,Aktiv!$A:$A,Aktiv!$G:$G,"–"),"") -> 135 | G16: =IFERROR(_xlfn.XLOOKUP(A16,Aktiv!$A:$A,Aktiv!$H:$H,"–"),"") -> 461 | H16: =IFERROR(_xlfn.XLOOKUP(A16,Aktiv!$A:$A,Aktiv!$I:$I,"–"),"") -> 480 | I16: =IFERROR(_xlfn.XLOOKUP(A16,Aktiv!$A:$A,Aktiv!$J:$J,"–"),"") -> 535 | J16: =IFERROR(IF(OR(F16=0,G16=0,F16="",G16=""),"-",(G16-F16)/F16),"–") -> 2.4148148 | K16: =IFERROR(IF(OR(F16=0,H16=0,F16="",H16=""),"-",(H16-F16)/F16),"–") -> 2.5555556 | L16: =IFERROR(IF(OR(F16=0,I16=0,F16="",I16=""),"-",(I16-F16)/F16),"–") -> 2.962963 | M16: =IFERROR(IF(OR(G16=0,H16=0,G16="",H16=""),"-",(H16-G16)/G16),"–") -> 0.041214751 | N16: =IFERROR(IF(OR(G16=0,I16=0,G16="",I16=""),"-",(I16-G16)/G16),"–") -> 0.16052061 | O16: =IFERROR(IF(OR(H16=0,I16=0,H16="",I16=""),"-",(I16-H16)/H16),"–") -> 0.11458333 | P16: =IFERROR(ROUND(AVERAGEIF(F16:I16,"<>0"),0),"–") -> 403
... A19: 3014 | B19: =IFERROR(_xlfn.XLOOKUP(A19,Aktiv!$A:$A,Aktiv!$C:$C,"–"),"") -> Boden | C19: =IFERROR(_xlfn.XLOOKUP(A19,Aktiv!$A:$A,Aktiv!$D:$D,"–"),"") -> Boden (420x980) | D19: =IFERROR(_xlfn.XLOOKUP(A19,Aktiv!$A:$A,Aktiv!$E:$E,"–"),"") -> 420 | E19: =IFERROR(_xlfn.XLOOKUP(A19,Aktiv!$A:$A,Aktiv!$F:$F,"–"),"") -> 980 | F19: =IFERROR(_xlfn.XLOOKUP(A19,Aktiv!$A:$A,Aktiv!$G:$G,"–"),"") -> 72 | G19: =IFERROR(_xlfn.XLOOKUP(A19,Aktiv!$A:$A,Aktiv!$H:$H,"–"),"") -> 248 | H19: =IFERROR(_xlfn.XLOOKUP(A19,Aktiv!$A:$A,Aktiv!$I:$I,"–"),"") -> 259 | I19: =IFERROR(_xlfn.XLOOKUP(A19,Aktiv!$A:$A,Aktiv!$J:$J,"–"),"") -> 288 | J19: =IFERROR(IF(OR(F19=0,G19=0,F19="",G19=""),"-",(G19-F19)/F19),"–") -> 2.4444444 | K19: =IFERROR(IF(OR(F19=0,H19=0,F19="",H19=""),"-",(H19-F19)/F19),"–") -> 2.5972222 | L19: =IFERROR(IF(OR(F19=0,I19=0,F19="",I19=""),"-",(I19-F19)/F19),"–") -> 3 | M19: =IFERROR(IF(OR(G19=0,H19=0,G19="",H19=""),"-",(H19-G19)/G19),"–") -> 0.044354839 | N19: =IFERROR(IF(OR(G19=0,I19=0,G19="",I19=""),"-",(I19-G19)/G19),"–") -> 0.16129032 | O19: =IFERROR(IF(OR(H19=0,I19=0,H19="",I19=""),"-",(I19-H19)/H19),"–") -> 0.11196911 | P19: =IFERROR(ROUND(AVERAGEIF(F19:I19,"<>0"),0),"–") -> 217
A20: S_0003 | B20: =IFERROR(_xlfn.XLOOKUP(A20,Aktiv!$A:$A,Aktiv!$C:$C,"–"),"") -> Boden | C20: =IFERROR(_xlfn.XLOOKUP(A20,Aktiv!$A:$A,Aktiv!$D:$D,"–"),"") -> Boden (420x420) | D20: =IFERROR(_xlfn.XLOOKUP(A20,Aktiv!$A:$A,Aktiv!$E:$E,"–"),"") -> 420 | E20: =IFERROR(_xlfn.XLOOKUP(A20,Aktiv!$A:$A,Aktiv!$F:$F,"–"),"") -> 420 | F20: =IFERROR(_xlfn.XLOOKUP(A20,Aktiv!$A:$A,Aktiv!$G:$G,"–"),"") -> 31 | G20: =IFERROR(_xlfn.XLOOKUP(A20,Aktiv!$A:$A,Aktiv!$H:$H,"–"),"") -> 106 | H20: =IFERROR(_xlfn.XLOOKUP(A20,Aktiv!$A:$A,Aktiv!$I:$I,"–"),"") -> 120 | I20: =IFERROR(_xlfn.XLOOKUP(A20,Aktiv!$A:$A,Aktiv!$J:$J,"–"),"") -> 145 | J20: =IFERROR(IF(OR(F20=0,G20=0,F20="",G20=""),"-",(G20-F20)/F20),"–") -> 2.4193548 | K20: =IFERROR(IF(OR(F20=0,H20=0,F20="",H20=""),"-",(H20-F20)/F20),"–") -> 2.8709677 | L20: =IFERROR(IF(OR(F20=0,I20=0,F20="",I20=""),"-",(I20-F20)/F20),"–") -> 3.6774194 | M20: =IFERROR(IF(OR(G20=0,H20=0,G20="",H20=""),"-",(H20-G20)/G20),"–") -> 0.13207547 | N20: =IFERROR(IF(OR(G20=0,I20=0,G20="",I20=""),"-",(I20-G20)/G20),"–") -> 0.36792453 | O20: =IFERROR(IF(OR(H20=0,I20=0,H20="",I20=""),"-",(I20-H20)/H20),"–") -> 0.20833333 | P20: =IFERROR(ROUND(AVERAGEIF(F20:I20,"<>0"),0),"–") -> 101
A21: 5200 | B21: =IFERROR(_xlfn.XLOOKUP(A21,Aktiv!$A:$A,Aktiv!$C:$C,"–"),"") -> Doppeltür | C21: =IFERROR(_xlfn.XLOOKUP(A21,Aktiv!$A:$A,Aktiv!$D:$D,"–"),"") -> Doppeltür (780x360) | D21: =IFERROR(_xlfn.XLOOKUP(A21,Aktiv!$A:$A,Aktiv!$E:$E,"–"),"") -> 780 | E21: =IFERROR(_xlfn.XLOOKUP(A21,Aktiv!$A:$A,Aktiv!$F:$F,"–"),"") -> 360 | F21: =IFERROR(_xlfn.XLOOKUP(A21,Aktiv!$A:$A,Aktiv!$G:$G,"–"),"") -> 212 | G21: =IFERROR(_xlfn.XLOOKUP(A21,Aktiv!$A:$A,Aktiv!$H:$H,"–"),"") -> 300 | H21: =IFERROR(_xlfn.XLOOKUP(A21,Aktiv!$A:$A,Aktiv!$I:$I,"–"),"") -> 316 | I21: =IFERROR(_xlfn.XLOOKUP(A21,Aktiv!$A:$A,Aktiv!$J:$J,"–"),"") -> 697 | J21: =IFERROR(IF(OR(F21=0,G21=0,F21="",G21=""),"-",(G21-F21)/F21),"–") -> 0.41509434 | K21: =IFERROR(IF(OR(F21=0,H21=0,F21="",H21=""),"-",(H21-F21)/F21),"–") -> 0.49056604 | L21: =IFERROR(IF(OR(F21=0,I21=0,F21="",I21=""),"-",(I21-F21)/F21),"–") -> 2.2877358 | M21: =IFERROR(IF(OR(G21=0,H21=0,G21="",H21=""),"-",(H21-G21)/G21),"–") -> 0.053333333 | N21: =IFERROR(IF(OR(G21=0,I21=0,G21="",I21=""),"-",(I21-G21)/G21),"–") -> 1.3233333 | O21: =IFERROR(IF(OR(H21=0,I21=0,H21="",I21=""),"-",(I21-H21)/H21),"–") -> 1.2056962 | P21: =IFERROR(ROUND(AVERAGEIF(F21:I21,"<>0"),0),"–") -> 381
A22: 5201 | B22: =IFERROR(_xlfn.XLOOKUP(A22,Aktiv!$A:$A,Aktiv!$C:$C,"–"),"") -> Doppeltür | C22: =IFERROR(_xlfn.XLOOKUP(A22,Aktiv!$A:$A,Aktiv!$D:$D,"–"),"") -> Doppeltür (780x720) | D22: =IFERROR(_xlfn.XLOOKUP(A22,Aktiv!$A:$A,Aktiv!$E:$E,"–"),"") -> 780 | E22: =IFERROR(_xlfn.XLOOKUP(A22,Aktiv!$A:$A,Aktiv!$F:$F,"–"),"") -> 720 | F22: =IFERROR(_xlfn.XLOOKUP(A22,Aktiv!$A:$A,Aktiv!$G:$G,"–"),"") -> 344 | G22: =IFERROR(_xlfn.XLOOKUP(A22,Aktiv!$A:$A,Aktiv!$H:$H,"–"),"") -> 487 | H22: =IFERROR(_xlfn.XLOOKUP(A22,Aktiv!$A:$A,Aktiv!$I:$I,"–"),"") -> 514 | I22: =IFERROR(_xlfn.XLOOKUP(A22,Aktiv!$A:$A,Aktiv!$J:$J,"–"),"") -> 1132 | J22: =IFERROR(IF(OR(F22=0,G22=0,F22="",G22=""),"-",(G22-F22)/F22),"–") -> 0.41569767 | K22: =IFERROR(IF(OR(F22=0,H22=0,F22="",H22=""),"-",(H22-F22)/F22),"–") -> 0.49418605 | L22: =IFERROR(IF(OR(F22=0,I22=0,F22="",I22=""),"-",(I22-F22)/F22),"–") -> 2.2906977 | M22: =IFERROR(IF(OR(G22=0,H22=0,G22="",H22=""),"-",(H22-G22)/G22),"–") -> 0.055441478 | N22: =IFERROR(IF(OR(G22=0,I22=0,G22="",I22=""),"-",(I22-G22)/G22),"–") -> 1.3244353 | O22: =IFERROR(IF(OR(H22=0,I22=0,H22="",I22=""),"-",(I22-H22)/H22),"–") -> 1.2023346 | P22: =IFERROR(ROUND(AVERAGEIF(F22:I22,"<>0"),0),"–") -> 619
A23: 5202 | B23: =IFERROR(_xlfn.XLOOKUP(A23,Aktiv!$A:$A,Aktiv!$C:$C,"–"),"") -> Doppeltür | C23: =IFERROR(_xlfn.XLOOKUP(A23,Aktiv!$A:$A,Aktiv!$D:$D,"–"),"") -> Doppeltür (780x1080) | D23: =IFERROR(_xlfn.XLOOKUP(A23,Aktiv!$A:$A,Aktiv!$E:$E,"–"),"") -> 780 | E23: =IFERROR(_xlfn.XLOOKUP(A23,Aktiv!$A:$A,Aktiv!$F:$F,"–"),"") -> 1080 | F23: =IFERROR(_xlfn.XLOOKUP(A23,Aktiv!$A:$A,Aktiv!$G:$G,"–"),"") -> 456 | G23: =IFERROR(_xlfn.XLOOKUP(A23,Aktiv!$A:$A,Aktiv!$H:$H,"–"),"") -> 646 | H23: =IFERROR(_xlfn.XLOOKUP(A23,Aktiv!$A:$A,Aktiv!$I:$I,"–"),"") -> 682 | I23: =IFERROR(_xlfn.XLOOKUP(A23,Aktiv!$A:$A,Aktiv!$J:$J,"–"),"") -> 1504 | J23: =IFERROR(IF(OR(F23=0,G23=0,F23="",G23=""),"-",(G23-F23)/F23),"–") -> 0.41666667 | K23: =IFERROR(IF(OR(F23=0,H23=0,F23="",H23=""),"-",(H23-F23)/F23),"–") -> 0.49561404 | L23: =IFERROR(IF(OR(F23=0,I23=0,F23="",I23=""),"-",(I23-F23)/F23),"–") -> 2.2982456 | M23: =IFERROR(IF(OR(G23=0,H23=0,G23="",H23=""),"-",(H23-G23)/G23),"–") -> 0.055727554 | N23: =IFERROR(IF(OR(G23=0,I23=0,G23="",I23=""),"-",(I23-G23)/G23),"–") -> 1.3281734 | O23: =IFERROR(IF(OR(H23=0,I23=0,H23="",I23=""),"-",(I23-H23)/H23),"–") -> 1.2052786 | P23: =IFERROR(ROUND(AVERAGEIF(F23:I23,"<>0"),0),"–") -> 822
A24: 5203 | B24: =IFERROR(_xlfn.XLOOKUP(A24,Aktiv!$A:$A,Aktiv!$C:$C,"–"),"") -> Doppeltür | C24: =IFERROR(_xlfn.XLOOKUP(A24,Aktiv!$A:$A,Aktiv!$D:$D,"–"),"") -> Doppeltür (780x1440) | D24: =IFERROR(_xlfn.XLOOKUP(A24,Aktiv!$A:$A,Aktiv!$E:$E,"–"),"") -> 780 | E24: =IFERROR(_xlfn.XLOOKUP(A24,Aktiv!$A:$A,Aktiv!$F:$F,"–"),"") -> 1440 | F24: =IFERROR(_xlfn.XLOOKUP(A24,Aktiv!$A:$A,Aktiv!$G:$G,"–"),"") -> 558 | G24: =IFERROR(_xlfn.XLOOKUP(A24,Aktiv!$A:$A,Aktiv!$H:$H,"–"),"") -> 790 | H24: =IFERROR(_xlfn.XLOOKUP(A24,Aktiv!$A:$A,Aktiv!$I:$I,"–"),"") -> 834 | I24: =IFERROR(_xlfn.XLOOKUP(A24,Aktiv!$A:$A,Aktiv!$J:$J,"–"),"") -> 1839 | J24: =IFERROR(IF(OR(F24=0,G24=0,F24="",G24=""),"-",(G24-F24)/F24),"–") -> 0.41577061 | K24: =IFERROR(IF(OR(F24=0,H24=0,F24="",H24=""),"-",(H24-F24)/F24),"–") -> 0.49462366 | L24: =IFERROR(IF(OR(F24=0,I24=0,F24="",I24=""),"-",(I24-F24)/F24),"–") -> 2.2956989 | M24: =IFERROR(IF(OR(G24=0,H24=0,G24="",H24=""),"-",(H24-G24)/G24),"–") -> 0.055696203 | N24: =IFERROR(IF(OR(G24=0,I24=0,G24="",I24=""),"-",(I24-G24)/G24),"–") -> 1.3278481 | O24: =IFERROR(IF(OR(H24=0,I24=0,H24="",I24=""),"-",(I24-H24)/H24),"–") -> 1.205036 | P24: =IFERROR(ROUND(AVERAGEIF(F24:I24,"<>0"),0),"–") -> 1005
A25: 5204 | B25: =IFERROR(_xlfn.XLOOKUP(A25,Aktiv!$A:$A,Aktiv!$C:$C,"–"),"") -> Doppeltür | C25: =IFERROR(_xlfn.XLOOKUP(A25,Aktiv!$A:$A,Aktiv!$D:$D,"–"),"") -> Doppeltür (780x1800) | D25: =IFERROR(_xlfn.XLOOKUP(A25,Aktiv!$A:$A,Aktiv!$E:$E,"–"),"") -> 780 | E25: =IFERROR(_xlfn.XLOOKUP(A25,Aktiv!$A:$A,Aktiv!$F:$F,"–"),"") -> 1800 | F25: =IFERROR(_xlfn.XLOOKUP(A25,Aktiv!$A:$A,Aktiv!$G:$G,"–"),"") -> 653 | G25: =IFERROR(_xlfn.XLOOKUP(A25,Aktiv!$A:$A,Aktiv!$H:$H,"–"),"") -> 924 | H25: =IFERROR(_xlfn.XLOOKUP(A25,Aktiv!$A:$A,Aktiv!$I:$I,"–"),"") -> 975 | I25: =IFERROR(_xlfn.XLOOKUP(A25,Aktiv!$A:$A,Aktiv!$J:$J,"–"),"") -> 2150 | J25: =IFERROR(IF(OR(F25=0,G25=0,F25="",G25=""),"-",(G25-F25)/F25),"–") -> 0.41500766 | K25: =IFERROR(IF(OR(F25=0,H25=0,F25="",H25=""),"-",(H25-F25)/F25),"–") -> 0.49310873 | L25: =IFERROR(IF(OR(F25=0,I25=0,F25="",I25=""),"-",(I25-F25)/F25),"–") -> 2.2924962 | M25: =IFERROR(IF(OR(G25=0,H25=0,G25="",H25=""),"-",(H25-G25)/G25),"–") -> 0.055194805 | N25: =IFERROR(IF(OR(G25=0,I25=0,G25="",I25=""),"-",(I25-G25)/G25),"–") -> 1.3268398 | O25: =IFERROR(IF(OR(H25=0,I25=0,H25="",I25=""),"-",(I25-H25)/H25),"–") -> 1.2051282 | P25: =IFERROR(ROUND(AVERAGEIF(F25:I25,"<>0"),0),"–") -> 1176
A26: 5205 | B26: =IFERROR(_xlfn.XLOOKUP(A26,Aktiv!$A:$A,Aktiv!$C:$C,"–"),"") -> Doppeltür | C26: =IFERROR(_xlfn.XLOOKUP(A26,Aktiv!$A:$A,Aktiv!$D:$D,"–"),"") -> Doppeltür (980x360) | D26: =IFERROR(_xlfn.XLOOKUP(A26,Aktiv!$A:$A,Aktiv!$E:$E,"–"),"") -> 980 | E26: =IFERROR(_xlfn.XLOOKUP(A26,Aktiv!$A:$A,Aktiv!$F:$F,"–"),"") -> 360 | F26: =IFERROR(_xlfn.XLOOKUP(A26,Aktiv!$A:$A,Aktiv!$G:$G,"–"),"") -> 248 | G26: =IFERROR(_xlfn.XLOOKUP(A26,Aktiv!$A:$A,Aktiv!$H:$H,"–"),"") -> 351 | H26: =IFERROR(_xlfn.XLOOKUP(A26,Aktiv!$A:$A,Aktiv!$I:$I,"–"),"") -> 371 | I26: =IFERROR(_xlfn.XLOOKUP(A26,Aktiv!$A:$A,Aktiv!$J:$J,"–"),"") -> 818 | J26: =IFERROR(IF(OR(F26=0,G26=0,F26="",G26=""),"-",(G26-F26)/F26),"–") -> 0.41532258 | K26: =IFERROR(IF(OR(F26=0,H26=0,F26="",H26=""),"-",(H26-F26)/F26),"–") -> 0.49596774 | L26: =IFERROR(IF(OR(F26=0,I26=0,F26="",I26=""),"-",(I26-F26)/F26),"–") -> 2.2983871 | M26: =IFERROR(IF(OR(G26=0,H26=0,G26="",H26=""),"-",(H26-G26)/G26),"–") -> 0.056980057 | N26: =IFERROR(IF(OR(G26=0,I26=0,G26="",I26=""),"-",(I26-G26)/G26),"–") -> 1.3304843 | O26: =IFERROR(IF(OR(H26=0,I26=0,H26="",I26=""),"-",(I26-H26)/H26),"–") -> 1.2048518 | P26: =IFERROR(ROUND(AVERAGEIF(F26:I26,"<>0"),0),"–") -> 447
A27: 5206 | B27: =IFERROR(_xlfn.XLOOKUP(A27,Aktiv!$A:$A,Aktiv!$C:$C,"–"),"") -> Doppeltür | C27: =IFERROR(_xlfn.XLOOKUP(A27,Aktiv!$A:$A,Aktiv!$D:$D,"–"),"") -> Doppeltür (980x720) | D27: =IFERROR(_xlfn.XLOOKUP(A27,Aktiv!$A:$A,Aktiv!$E:$E,"–"),"") -> 980 | E27: =IFERROR(_xlfn.XLOOKUP(A27,Aktiv!$A:$A,Aktiv!$F:$F,"–"),"") -> 720 | F27: =IFERROR(_xlfn.XLOOKUP(A27,Aktiv!$A:$A,Aktiv!$G:$G,"–"),"") -> 403 | G27: =IFERROR(_xlfn.XLOOKUP(A27,Aktiv!$A:$A,Aktiv!$H:$H,"–"),"") -> 571 | H27: =IFERROR(_xlfn.XLOOKUP(A27,Aktiv!$A:$A,Aktiv!$I:$I,"–"),"") -> 602 | I27: =IFERROR(_xlfn.XLOOKUP(A27,Aktiv!$A:$A,Aktiv!$J:$J,"–"),"") -> 1328 | J27: =IFERROR(IF(OR(F27=0,G27=0,F27="",G27=""),"-",(G27-F27)/F27),"–") -> 0.41687345 | K27: =IFERROR(IF(OR(F27=0,H27=0,F27="",H27=""),"-",(H27-F27)/F27),"–") -> 0.49379653 | L27: =IFERROR(IF(OR(F27=0,I27=0,F27="",I27=""),"-",(I27-F27)/F27),"–") -> 2.2952854 | M27: =IFERROR(IF(OR(G27=0,H27=0,G27="",H27=""),"-",(H27-G27)/G27),"–") -> 0.054290718 | N27: =IFERROR(IF(OR(G27=0,I27=0,G27="",I27=""),"-",(I27-G27)/G27),"–") -> 1.3257443 | O27: =IFERROR(IF(OR(H27=0,I27=0,H27="",I27=""),"-",(I27-H27)/H27),"–") -> 1.2059801 | P27: =IFERROR(ROUND(AVERAGEIF(F27:I27,"<>0"),0),"–") -> 726
A28: 5207 | B28: =IFERROR(_xlfn.XLOOKUP(A28,Aktiv!$A:$A,Aktiv!$C:$C,"–"),"") -> Doppeltür | C28: =IFERROR(_xlfn.XLOOKUP(A28,Aktiv!$A:$A,Aktiv!$D:$D,"–"),"") -> Doppeltür (980x1080) | D28: =IFERROR(_xlfn.XLOOKUP(A28,Aktiv!$A:$A,Aktiv!$E:$E,"–"),"") -> 980 | E28: =IFERROR(_xlfn.XLOOKUP(A28,Aktiv!$A:$A,Aktiv!$F:$F,"–"),"") -> 1080 | F28: =IFERROR(_xlfn.XLOOKUP(A28,Aktiv!$A:$A,Aktiv!$G:$G,"–"),"") -> 536 | G28: =IFERROR(_xlfn.XLOOKUP(A28,Aktiv!$A:$A,Aktiv!$H:$H,"–"),"") -> 758 | H28: =IFERROR(_xlfn.XLOOKUP(A28,Aktiv!$A:$A,Aktiv!$I:$I,"–"),"") -> 800 | I28: =IFERROR(_xlfn.XLOOKUP(A28,Aktiv!$A:$A,Aktiv!$J:$J,"–"),"") -> 1764 | J28: =IFERROR(IF(OR(F28=0,G28=0,F28="",G28=""),"-",(G28-F28)/F28),"–") -> 0.4141791 | K28: =IFERROR(IF(OR(F28=0,H28=0,F28="",H28=""),"-",(H28-F28)/F28),"–") -> 0.49253731 | L28: =IFERROR(IF(OR(F28=0,I28=0,F28="",I28=""),"-",(I28-F28)/F28),"–") -> 2.2910448 | M28: =IFERROR(IF(OR(G28=0,H28=0,G28="",H28=""),"-",(H28-G28)/G28),"–") -> 0.055408971 | N28: =IFERROR(IF(OR(G28=0,I28=0,G28="",I28=""),"-",(I28-G28)/G28),"–") -> 1.3271768 | O28: =IFERROR(IF(OR(H28=0,I28=0,H28="",I28=""),"-",(I28-H28)/H28),"–") -> 1.205 | P28: =IFERROR(ROUND(AVERAGEIF(F28:I28,"<>0"),0),"–") -> 965
A29: 5208 | B29: =IFERROR(_xlfn.XLOOKUP(A29,Aktiv!$A:$A,Aktiv!$C:$C,"–"),"") -> Doppeltür | C29: =IFERROR(_xlfn.XLOOKUP(A29,Aktiv!$A:$A,Aktiv!$D:$D,"–"),"") -> Doppeltür (980x1440) | D29: =IFERROR(_xlfn.XLOOKUP(A29,Aktiv!$A:$A,Aktiv!$E:$E,"–"),"") -> 980 | E29: =IFERROR(_xlfn.XLOOKUP(A29,Aktiv!$A:$A,Aktiv!$F:$F,"–"),"") -> 1440 | F29: =IFERROR(_xlfn.XLOOKUP(A29,Aktiv!$A:$A,Aktiv!$G:$G,"–"),"") -> - | G29: =IFERROR(_xlfn.XLOOKUP(A29,Aktiv!$A:$A,Aktiv!$H:$H,"–"),"") -> - | H29: =IFERROR(_xlfn.XLOOKUP(A29,Aktiv!$A:$A,Aktiv!$I:$I,"–"),"") -> - | I29: =IFERROR(_xlfn.XLOOKUP(A29,Aktiv!$A:$A,Aktiv!$J:$J,"–"),"") -> - | J29: =IFERROR(IF(OR(F29=0,G29=0,F29="",G29=""),"-",(G29-F29)/F29),"–") -> – | K29: =IFERROR(IF(OR(F29=0,H29=0,F29="",H29=""),"-",(H29-F29)/F29),"–") -> – | L29: =IFERROR(IF(OR(F29=0,I29=0,F29="",I29=""),"-",(I29-F29)/F29),"–") -> – | M29: =IFERROR(IF(OR(G29=0,H29=0,G29="",H29=""),"-",(H29-G29)/G29),"–") -> – | N29: =IFERROR(IF(OR(G29=0,I29=0,G29="",I29=""),"-",(I29-G29)/G29),"–") -> – | O29: =IFERROR(IF(OR(H29=0,I29=0,H29="",I29=""),"-",(I29-H29)/H29),"–") -> – | P29: =IFERROR(ROUND(AVERAGEIF(F29:I29,"<>0"),0),"–") -> –
A30: 5209 | B30: =IFERROR(_xlfn.XLOOKUP(A30,Aktiv!$A:$A,Aktiv!$C:$C,"–"),"") -> Doppeltür | C30: =IFERROR(_xlfn.XLOOKUP(A30,Aktiv!$A:$A,Aktiv!$D:$D,"–"),"") -> Doppeltür (980x1800) | D30: =IFERROR(_xlfn.XLOOKUP(A30,Aktiv!$A:$A,Aktiv!$E:$E,"–"),"") -> 980 | E30: =IFERROR(_xlfn.XLOOKUP(A30,Aktiv!$A:$A,Aktiv!$F:$F,"–"),"") -> 1800 | F30: =IFERROR(_xlfn.XLOOKUP(A30,Aktiv!$A:$A,Aktiv!$G:$G,"–"),"") -> - | G30: =IFERROR(_xlfn.XLOOKUP(A30,Aktiv!$A:$A,Aktiv!$H:$H,"–"),"") -> - | H30: =IFERROR(_xlfn.XLOOKUP(A30,Aktiv!$A:$A,Aktiv!$I:$I,"–"),"") -> - | I30: =IFERROR(_xlfn.XLOOKUP(A30,Aktiv!$A:$A,Aktiv!$J:$J,"–"),"") -> - | J30: =IFERROR(IF(OR(F30=0,G30=0,F30="",G30=""),"-",(G30-F30)/F30),"–") -> – | K30: =IFERROR(IF(OR(F30=0,H30=0,F30="",H30=""),"-",(H30-F30)/F30),"–") -> – | L30: =IFERROR(IF(OR(F30=0,I30=0,F30="",I30=""),"-",(I30-F30)/F30),"–") -> – | M30: =IFERROR(IF(OR(G30=0,H30=0,G30="",H30=""),"-",(H30-G30)/G30),"–") -> – | N30: =IFERROR(IF(OR(G30=0,I30=0,G30="",I30=""),"-",(I30-G30)/G30),"–") -> – | O30: =IFERROR(IF(OR(H30=0,I30=0,H30="",I30=""),"-",(I30-H30)/H30),"–") -> – | P30: =IFERROR(ROUND(AVERAGEIF(F30:I30,"<>0"),0),"–") -> –
A31: 5210 | B31: =IFERROR(_xlfn.XLOOKUP(A31,Aktiv!$A:$A,Aktiv!$C:$C,"–"),"") -> Doppeltür | C31: =IFERROR(_xlfn.XLOOKUP(A31,Aktiv!$A:$A,Aktiv!$D:$D,"–"),"") -> Doppeltür (780x660) | D31: =IFERROR(_xlfn.XLOOKUP(A31,Aktiv!$A:$A,Aktiv!$E:$E,"–"),"") -> 780 | E31: =IFERROR(_xlfn.XLOOKUP(A31,Aktiv!$A:$A,Aktiv!$F:$F,"–"),"") -> 660 | F31: =IFERROR(_xlfn.XLOOKUP(A31,Aktiv!$A:$A,Aktiv!$G:$G,"–"),"") -> 323 | G31: =IFERROR(_xlfn.XLOOKUP(A31,Aktiv!$A:$A,Aktiv!$H:$H,"–"),"") -> 458 | H31: =IFERROR(_xlfn.XLOOKUP(A31,Aktiv!$A:$A,Aktiv!$I:$I,"–"),"") -> 483 | I31: =IFERROR(_xlfn.XLOOKUP(A31,Aktiv!$A:$A,Aktiv!$J:$J,"–"),"") -> 1065 | J31: =IFERROR(IF(OR(F31=0,G31=0,F31="",G31=""),"-",(G31-F31)/F31),"–") -> 0.41795666 | K31: =IFERROR(IF(OR(F31=0,H31=0,F31="",H31=""),"-",(H31-F31)/F31),"–") -> 0.49535604 | L31: =IFERROR(IF(OR(F31=0,I31=0,F31="",I31=""),"-",(I31-F31)/F31),"–") -> 2.2972136 | M31: =IFERROR(IF(OR(G31=0,H31=0,G31="",H31=""),"-",(H31-G31)/G31),"–") -> 0.054585153 | N31: =IFERROR(IF(OR(G31=0,I31=0,G31="",I31=""),"-",(I31-G31)/G31),"–") -> 1.3253275 | O31: =IFERROR(IF(OR(H31=0,I31=0,H31="",I31=""),"-",(I31-H31)/H31),"–") -> 1.2049689 | P31: =IFERROR(ROUND(AVERAGEIF(F31:I31,"<>0"),0),"–") -> 582
A32: 3750 | B32: =IFERROR(_xlfn.XLOOKUP(A32,Aktiv!$A:$A,Aktiv!$C:$C,"–"),"") -> Fachboden groß | C32: =IFERROR(_xlfn.XLOOKUP(A32,Aktiv!$A:$A,Aktiv!$D:$D,"–"),"") -> Fachboden groß (360x360) | D32: =IFERROR(_xlfn.XLOOKUP(A32,Aktiv!$A:$A,Aktiv!$E:$E,"–"),"") -> 360 | E32: =IFERROR(_xlfn.XLOOKUP(A32,Aktiv!$A:$A,Aktiv!$F:$F,"–"),"") -> 360 | F32: =IFERROR(_xlfn.XLOOKUP(A32,Aktiv!$A:$A,Aktiv!$G:$G,"–"),"") -> 25 | G32: =IFERROR(_xlfn.XLOOKUP(A32,Aktiv!$A:$A,Aktiv!$H:$H,"–"),"") -> 103 | H32: =IFERROR(_xlfn.XLOOKUP(A32,Aktiv!$A:$A,Aktiv!$I:$I,"–"),"") -> 120 | I32: =IFERROR(_xlfn.XLOOKUP(A32,Aktiv!$A:$A,Aktiv!$J:$J,"–"),"") -> 145 | J32: =IFERROR(IF(OR(F32=0,G32=0,F32="",G32=""),"-",(G32-F32)/F32),"–") -> 3.12 | K32: =IFERROR(IF(OR(F32=0,H32=0,F32="",H32=""),"-",(H32-F32)/F32),"–") -> 3.8 | L32: =IFERROR(IF(OR(F32=0,I32=0,F32="",I32=""),"-",(I32-F32)/F32),"–") -> 4.8 | M32: =IFERROR(IF(OR(G32=0,H32=0,G32="",H32=""),"-",(H32-G32)/G32),"–") -> 0.16504854 | N32: =IFERROR(IF(OR(G32=0,I32=0,G32="",I32=""),"-",(I32-G32)/G32),"–") -> 0.40776699 | O32: =IFERROR(IF(OR(H32=0,I32=0,H32="",I32=""),"-",(I32-H32)/H32),"–") -> 0.20833333 | P32: =IFERROR(ROUND(AVERAGEIF(F32:I32,"<>0"),0),"–") -> 98
... A67: 5009 | B67: =IFERROR(_xlfn.XLOOKUP(A67,Aktiv!$A:$A,Aktiv!$C:$C,"–"),"") -> Klappe | C67: =IFERROR(_xlfn.XLOOKUP(A67,Aktiv!$A:$A,Aktiv!$D:$D,"–"),"") -> Klappe (360x180) | D67: =IFERROR(_xlfn.XLOOKUP(A67,Aktiv!$A:$A,Aktiv!$E:$E,"–"),"") -> 360 | E67: =IFERROR(_xlfn.XLOOKUP(A67,Aktiv!$A:$A,Aktiv!$F:$F,"–"),"") -> 180 | F67: =IFERROR(_xlfn.XLOOKUP(A67,Aktiv!$A:$A,Aktiv!$G:$G,"–"),"") -> - | G67: =IFERROR(_xlfn.XLOOKUP(A67,Aktiv!$A:$A,Aktiv!$H:$H,"–"),"") -> - | H67: =IFERROR(_xlfn.XLOOKUP(A67,Aktiv!$A:$A,Aktiv!$I:$I,"–"),"") -> - | I67: =IFERROR(_xlfn.XLOOKUP(A67,Aktiv!$A:$A,Aktiv!$J:$J,"–"),"") -> - | J67: =IFERROR(IF(OR(F67=0,G67=0,F67="",G67=""),"-",(G67-F67)/F67),"–") -> – | K67: =IFERROR(IF(OR(F67=0,H67=0,F67="",H67=""),"-",(H67-F67)/F67),"–") -> – | L67: =IFERROR(IF(OR(F67=0,I67=0,F67="",I67=""),"-",(I67-F67)/F67),"–") -> – | M67: =IFERROR(IF(OR(G67=0,H67=0,G67="",H67=""),"-",(H67-G67)/G67),"–") -> – | N67: =IFERROR(IF(OR(G67=0,I67=0,G67="",I67=""),"-",(I67-G67)/G67),"–") -> – | O67: =IFERROR(IF(OR(H67=0,I67=0,H67="",I67=""),"-",(I67-H67)/H67),"–") -> – | P67: =IFERROR(ROUND(AVERAGEIF(F67:I67,"<>0"),0),"–") -> –
A68: S_0046 | B68: =IFERROR(_xlfn.XLOOKUP(A68,Aktiv!$A:$A,Aktiv!$C:$C,"–"),"") -> Klappe | C68: =IFERROR(_xlfn.XLOOKUP(A68,Aktiv!$A:$A,Aktiv!$D:$D,"–"),"") -> Klappe (980x420) | D68: =IFERROR(_xlfn.XLOOKUP(A68,Aktiv!$A:$A,Aktiv!$E:$E,"–"),"") -> 980 | E68: =IFERROR(_xlfn.XLOOKUP(A68,Aktiv!$A:$A,Aktiv!$F:$F,"–"),"") -> 420 | F68: =IFERROR(_xlfn.XLOOKUP(A68,Aktiv!$A:$A,Aktiv!$G:$G,"–"),"") -> - | G68: =IFERROR(_xlfn.XLOOKUP(A68,Aktiv!$A:$A,Aktiv!$H:$H,"–"),"") -> - | H68: =IFERROR(_xlfn.XLOOKUP(A68,Aktiv!$A:$A,Aktiv!$I:$I,"–"),"") -> - | I68: =IFERROR(_xlfn.XLOOKUP(A68,Aktiv!$A:$A,Aktiv!$J:$J,"–"),"") -> - | J68: =IFERROR(IF(OR(F68=0,G68=0,F68="",G68=""),"-",(G68-F68)/F68),"–") -> – | K68: =IFERROR(IF(OR(F68=0,H68=0,F68="",H68=""),"-",(H68-F68)/F68),"–") -> – | L68: =IFERROR(IF(OR(F68=0,I68=0,F68="",I68=""),"-",(I68-F68)/F68),"–") -> – | M68: =IFERROR(IF(OR(G68=0,H68=0,G68="",H68=""),"-",(H68-G68)/G68),"–") -> – | N68: =IFERROR(IF(OR(G68=0,I68=0,G68="",I68=""),"-",(I68-G68)/G68),"–") -> – | O68: =IFERROR(IF(OR(H68=0,I68=0,H68="",I68=""),"-",(I68-H68)/H68),"–") -> – | P68: =IFERROR(ROUND(AVERAGEIF(F68:I68,"<>0"),0),"–") -> –
A69: 3800 | B69: =IFERROR(_xlfn.XLOOKUP(A69,Aktiv!$A:$A,Aktiv!$C:$C,"–"),"") -> Klappenboden | C69: =IFERROR(_xlfn.XLOOKUP(A69,Aktiv!$A:$A,Aktiv!$D:$D,"–"),"") -> Klappenboden (360x360) | D69: =IFERROR(_xlfn.XLOOKUP(A69,Aktiv!$A:$A,Aktiv!$E:$E,"–"),"") -> 360 | E69: =IFERROR(_xlfn.XLOOKUP(A69,Aktiv!$A:$A,Aktiv!$F:$F,"–"),"") -> 360 | F69: =IFERROR(_xlfn.XLOOKUP(A69,Aktiv!$A:$A,Aktiv!$G:$G,"–"),"") -> 25 | G69: =IFERROR(_xlfn.XLOOKUP(A69,Aktiv!$A:$A,Aktiv!$H:$H,"–"),"") -> 103 | H69: =IFERROR(_xlfn.XLOOKUP(A69,Aktiv!$A:$A,Aktiv!$I:$I,"–"),"") -> 120 | I69: =IFERROR(_xlfn.XLOOKUP(A69,Aktiv!$A:$A,Aktiv!$J:$J,"–"),"") -> 145 | J69: =IFERROR(IF(OR(F69=0,G69=0,F69="",G69=""),"-",(G69-F69)/F69),"–") -> 3.12 | K69: =IFERROR(IF(OR(F69=0,H69=0,F69="",H69=""),"-",(H69-F69)/F69),"–") -> 3.8 | L69: =IFERROR(IF(OR(F69=0,I69=0,F69="",I69=""),"-",(I69-F69)/F69),"–") -> 4.8 | M69: =IFERROR(IF(OR(G69=0,H69=0,G69="",H69=""),"-",(H69-G69)/G69),"–") -> 0.16504854 | N69: =IFERROR(IF(OR(G69=0,I69=0,G69="",I69=""),"-",(I69-G69)/G69),"–") -> 0.40776699 | O69: =IFERROR(IF(OR(H69=0,I69=0,H69="",I69=""),"-",(I69-H69)/H69),"–") -> 0.20833333 | P69: =IFERROR(ROUND(AVERAGEIF(F69:I69,"<>0"),0),"–") -> 98
A70: 3801 | B70: =IFERROR(_xlfn.XLOOKUP(A70,Aktiv!$A:$A,Aktiv!$C:$C,"–"),"") -> Klappenboden | C70: =IFERROR(_xlfn.XLOOKUP(A70,Aktiv!$A:$A,Aktiv!$D:$D,"–"),"") -> Klappenboden (420x360) | D70: =IFERROR(_xlfn.XLOOKUP(A70,Aktiv!$A:$A,Aktiv!$E:$E,"–"),"") -> 420 | E70: =IFERROR(_xlfn.XLOOKUP(A70,Aktiv!$A:$A,Aktiv!$F:$F,"–"),"") -> 360 | F70: =IFERROR(_xlfn.XLOOKUP(A70,Aktiv!$A:$A,Aktiv!$G:$G,"–"),"") -> 27 | G70: =IFERROR(_xlfn.XLOOKUP(A70,Aktiv!$A:$A,Aktiv!$H:$H,"–"),"") -> 103 | H70: =IFERROR(_xlfn.XLOOKUP(A70,Aktiv!$A:$A,Aktiv!$I:$I,"–"),"") -> 120 | I70: =IFERROR(_xlfn.XLOOKUP(A70,Aktiv!$A:$A,Aktiv!$J:$J,"–"),"") -> 145 | J70: =IFERROR(IF(OR(F70=0,G70=0,F70="",G70=""),"-",(G70-F70)/F70),"–") -> 2.8148148 | K70: =IFERROR(IF(OR(F70=0,H70=0,F70="",H70=""),"-",(H70-F70)/F70),"–") -> 3.4444444 | L70: =IFERROR(IF(OR(F70=0,I70=0,F70="",I70=""),"-",(I70-F70)/F70),"–") -> 4.3703704 | M70: =IFERROR(IF(OR(G70=0,H70=0,G70="",H70=""),"-",(H70-G70)/G70),"–") -> 0.16504854 | N70: =IFERROR(IF(OR(G70=0,I70=0,G70="",I70=""),"-",(I70-G70)/G70),"–") -> 0.40776699 | O70: =IFERROR(IF(OR(H70=0,I70=0,H70="",I70=""),"-",(I70-H70)/H70),"–") -> 0.20833333 | P70: =IFERROR(ROUND(AVERAGEIF(F70:I70,"<>0"),0),"–") -> 99
A71: 3802 | B71: =IFERROR(_xlfn.XLOOKUP(A71,Aktiv!$A:$A,Aktiv!$C:$C,"–"),"") -> Klappenboden | C71: =IFERROR(_xlfn.XLOOKUP(A71,Aktiv!$A:$A,Aktiv!$D:$D,"–"),"") -> Klappenboden (580x360) | D71: =IFERROR(_xlfn.XLOOKUP(A71,Aktiv!$A:$A,Aktiv!$E:$E,"–"),"") -> 580 | E71: =IFERROR(_xlfn.XLOOKUP(A71,Aktiv!$A:$A,Aktiv!$F:$F,"–"),"") -> 360 | F71: =IFERROR(_xlfn.XLOOKUP(A71,Aktiv!$A:$A,Aktiv!$G:$G,"–"),"") -> 37 | G71: =IFERROR(_xlfn.XLOOKUP(A71,Aktiv!$A:$A,Aktiv!$H:$H,"–"),"") -> 126 | H71: =IFERROR(_xlfn.XLOOKUP(A71,Aktiv!$A:$A,Aktiv!$I:$I,"–"),"") -> 131 | I71: =IFERROR(_xlfn.XLOOKUP(A71,Aktiv!$A:$A,Aktiv!$J:$J,"–"),"") -> 146 | J71: =IFERROR(IF(OR(F71=0,G71=0,F71="",G71=""),"-",(G71-F71)/F71),"–") -> 2.4054054 | K71: =IFERROR(IF(OR(F71=0,H71=0,F71="",H71=""),"-",(H71-F71)/F71),"–") -> 2.5405405 | L71: =IFERROR(IF(OR(F71=0,I71=0,F71="",I71=""),"-",(I71-F71)/F71),"–") -> 2.9459459 | M71: =IFERROR(IF(OR(G71=0,H71=0,G71="",H71=""),"-",(H71-G71)/G71),"–") -> 0.03968254 | N71: =IFERROR(IF(OR(G71=0,I71=0,G71="",I71=""),"-",(I71-G71)/G71),"–") -> 0.15873016 | O71: =IFERROR(IF(OR(H71=0,I71=0,H71="",I71=""),"-",(I71-H71)/H71),"–") -> 0.11450382 | P71: =IFERROR(ROUND(AVERAGEIF(F71:I71,"<>0"),0),"–") -> 110
A72: 3803 | B72: =IFERROR(_xlfn.XLOOKUP(A72,Aktiv!$A:$A,Aktiv!$C:$C,"–"),"") -> Klappenboden | C72: =IFERROR(_xlfn.XLOOKUP(A72,Aktiv!$A:$A,Aktiv!$D:$D,"–"),"") -> Klappenboden (780x360) | D72: =IFERROR(_xlfn.XLOOKUP(A72,Aktiv!$A:$A,Aktiv!$E:$E,"–"),"") -> 780 | E72: =IFERROR(_xlfn.XLOOKUP(A72,Aktiv!$A:$A,Aktiv!$F:$F,"–"),"") -> 360 | F72: =IFERROR(_xlfn.XLOOKUP(A72,Aktiv!$A:$A,Aktiv!$G:$G,"–"),"") -> 49 | G72: =IFERROR(_xlfn.XLOOKUP(A72,Aktiv!$A:$A,Aktiv!$H:$H,"–"),"") -> 169 | H72: =IFERROR(_xlfn.XLOOKUP(A72,Aktiv!$A:$A,Aktiv!$I:$I,"–"),"") -> 177 | I72: =IFERROR(_xlfn.XLOOKUP(A72,Aktiv!$A:$A,Aktiv!$J:$J,"–"),"") -> 196 | J72: =IFERROR(IF(OR(F72=0,G72=0,F72="",G72=""),"-",(G72-F72)/F72),"–") -> 2.4489796 | K72: =IFERROR(IF(OR(F72=0,H72=0,F72="",H72=""),"-",(H72-F72)/F72),"–") -> 2.6122449 | L72: =IFERROR(IF(OR(F72=0,I72=0,F72="",I72=""),"-",(I72-F72)/F72),"–") -> 3 | M72: =IFERROR(IF(OR(G72=0,H72=0,G72="",H72=""),"-",(H72-G72)/G72),"–") -> 0.047337278 | N72: =IFERROR(IF(OR(G72=0,I72=0,G72="",I72=""),"-",(I72-G72)/G72),"–") -> 0.15976331 | O72: =IFERROR(IF(OR(H72=0,I72=0,H72="",I72=""),"-",(I72-H72)/H72),"–") -> 0.10734463 | P72: =IFERROR(ROUND(AVERAGEIF(F72:I72,"<>0"),0),"–") -> 148
A73: 3804 | B73: =IFERROR(_xlfn.XLOOKUP(A73,Aktiv!$A:$A,Aktiv!$C:$C,"–"),"") -> Klappenboden | C73: =IFERROR(_xlfn.XLOOKUP(A73,Aktiv!$A:$A,Aktiv!$D:$D,"–"),"") -> Klappenboden (980x360) | D73: =IFERROR(_xlfn.XLOOKUP(A73,Aktiv!$A:$A,Aktiv!$E:$E,"–"),"") -> 980 | E73: =IFERROR(_xlfn.XLOOKUP(A73,Aktiv!$A:$A,Aktiv!$F:$F,"–"),"") -> 360 | F73: =IFERROR(_xlfn.XLOOKUP(A73,Aktiv!$A:$A,Aktiv!$G:$G,"–"),"") -> 62 | G73: =IFERROR(_xlfn.XLOOKUP(A73,Aktiv!$A:$A,Aktiv!$H:$H,"–"),"") -> 213 | H73: =IFERROR(_xlfn.XLOOKUP(A73,Aktiv!$A:$A,Aktiv!$I:$I,"–"),"") -> 222 | I73: =IFERROR(_xlfn.XLOOKUP(A73,Aktiv!$A:$A,Aktiv!$J:$J,"–"),"") -> 247 | J73: =IFERROR(IF(OR(F73=0,G73=0,F73="",G73=""),"-",(G73-F73)/F73),"–") -> 2.4354839 | K73: =IFERROR(IF(OR(F73=0,H73=0,F73="",H73=""),"-",(H73-F73)/F73),"–") -> 2.5806452 | L73: =IFERROR(IF(OR(F73=0,I73=0,F73="",I73=""),"-",(I73-F73)/F73),"–") -> 2.983871 | M73: =IFERROR(IF(OR(G73=0,H73=0,G73="",H73=""),"-",(H73-G73)/G73),"–") -> 0.042253521 | N73: =IFERROR(IF(OR(G73=0,I73=0,G73="",I73=""),"-",(I73-G73)/G73),"–") -> 0.15962441 | O73: =IFERROR(IF(OR(H73=0,I73=0,H73="",I73=""),"-",(I73-H73)/H73),"–") -> 0.11261261 | P73: =IFERROR(ROUND(AVERAGEIF(F73:I73,"<>0"),0),"–") -> 186
A74: 3805 | B74: =IFERROR(_xlfn.XLOOKUP(A74,Aktiv!$A:$A,Aktiv!$C:$C,"–"),"") -> Klappenboden | C74: =IFERROR(_xlfn.XLOOKUP(A74,Aktiv!$A:$A,Aktiv!$D:$D,"–"),"") -> Klappenboden (360x580) | D74: =IFERROR(_xlfn.XLOOKUP(A74,Aktiv!$A:$A,Aktiv!$E:$E,"–"),"") -> 360 | E74: =IFERROR(_xlfn.XLOOKUP(A74,Aktiv!$A:$A,Aktiv!$F:$F,"–"),"") -> 580 | F74: =IFERROR(_xlfn.XLOOKUP(A74,Aktiv!$A:$A,Aktiv!$G:$G,"–"),"") -> 37 | G74: =IFERROR(_xlfn.XLOOKUP(A74,Aktiv!$A:$A,Aktiv!$H:$H,"–"),"") -> 126 | H74: =IFERROR(_xlfn.XLOOKUP(A74,Aktiv!$A:$A,Aktiv!$I:$I,"–"),"") -> 131 | I74: =IFERROR(_xlfn.XLOOKUP(A74,Aktiv!$A:$A,Aktiv!$J:$J,"–"),"") -> 146 | J74: =IFERROR(IF(OR(F74=0,G74=0,F74="",G74=""),"-",(G74-F74)/F74),"–") -> 2.4054054 | K74: =IFERROR(IF(OR(F74=0,H74=0,F74="",H74=""),"-",(H74-F74)/F74),"–") -> 2.5405405 | L74: =IFERROR(IF(OR(F74=0,I74=0,F74="",I74=""),"-",(I74-F74)/F74),"–") -> 2.9459459 | M74: =IFERROR(IF(OR(G74=0,H74=0,G74="",H74=""),"-",(H74-G74)/G74),"–") -> 0.03968254 | N74: =IFERROR(IF(OR(G74=0,I74=0,G74="",I74=""),"-",(I74-G74)/G74),"–") -> 0.15873016 | O74: =IFERROR(IF(OR(H74=0,I74=0,H74="",I74=""),"-",(I74-H74)/H74),"–") -> 0.11450382 | P74: =IFERROR(ROUND(AVERAGEIF(F74:I74,"<>0"),0),"–") -> 110
A75: 3806 | B75: =IFERROR(_xlfn.XLOOKUP(A75,Aktiv!$A:$A,Aktiv!$C:$C,"–"),"") -> Klappenboden | C75: =IFERROR(_xlfn.XLOOKUP(A75,Aktiv!$A:$A,Aktiv!$D:$D,"–"),"") -> Klappenboden (420x580) | D75: =IFERROR(_xlfn.XLOOKUP(A75,Aktiv!$A:$A,Aktiv!$E:$E,"–"),"") -> 420 | E75: =IFERROR(_xlfn.XLOOKUP(A75,Aktiv!$A:$A,Aktiv!$F:$F,"–"),"") -> 580 | F75: =IFERROR(_xlfn.XLOOKUP(A75,Aktiv!$A:$A,Aktiv!$G:$G,"–"),"") -> 43 | G75: =IFERROR(_xlfn.XLOOKUP(A75,Aktiv!$A:$A,Aktiv!$H:$H,"–"),"") -> 147 | H75: =IFERROR(_xlfn.XLOOKUP(A75,Aktiv!$A:$A,Aktiv!$I:$I,"–"),"") -> 153 | I75: =IFERROR(_xlfn.XLOOKUP(A75,Aktiv!$A:$A,Aktiv!$J:$J,"–"),"") -> 170 | J75: =IFERROR(IF(OR(F75=0,G75=0,F75="",G75=""),"-",(G75-F75)/F75),"–") -> 2.4186047 | K75: =IFERROR(IF(OR(F75=0,H75=0,F75="",H75=""),"-",(H75-F75)/F75),"–") -> 2.5581395 | L75: =IFERROR(IF(OR(F75=0,I75=0,F75="",I75=""),"-",(I75-F75)/F75),"–") -> 2.9534884 | M75: =IFERROR(IF(OR(G75=0,H75=0,G75="",H75=""),"-",(H75-G75)/G75),"–") -> 0.040816327 | N75: =IFERROR(IF(OR(G75=0,I75=0,G75="",I75=""),"-",(I75-G75)/G75),"–") -> 0.15646259 | O75: =IFERROR(IF(OR(H75=0,I75=0,H75="",I75=""),"-",(I75-H75)/H75),"–") -> 0.11111111 | P75: =IFERROR(ROUND(AVERAGEIF(F75:I75,"<>0"),0),"–") -> 128
A76: 3807 | B76: =IFERROR(_xlfn.XLOOKUP(A76,Aktiv!$A:$A,Aktiv!$C:$C,"–"),"") -> Klappenboden | C76: =IFERROR(_xlfn.XLOOKUP(A76,Aktiv!$A:$A,Aktiv!$D:$D,"–"),"") -> Klappenboden (580x580) | D76: =IFERROR(_xlfn.XLOOKUP(A76,Aktiv!$A:$A,Aktiv!$E:$E,"–"),"") -> 580 | E76: =IFERROR(_xlfn.XLOOKUP(A76,Aktiv!$A:$A,Aktiv!$F:$F,"–"),"") -> 580 | F76: =IFERROR(_xlfn.XLOOKUP(A76,Aktiv!$A:$A,Aktiv!$G:$G,"–"),"") -> 59 | G76: =IFERROR(_xlfn.XLOOKUP(A76,Aktiv!$A:$A,Aktiv!$H:$H,"–"),"") -> 203 | H76: =IFERROR(_xlfn.XLOOKUP(A76,Aktiv!$A:$A,Aktiv!$I:$I,"–"),"") -> 211 | I76: =IFERROR(_xlfn.XLOOKUP(A76,Aktiv!$A:$A,Aktiv!$J:$J,"–"),"") -> 235 | J76: =IFERROR(IF(OR(F76=0,G76=0,F76="",G76=""),"-",(G76-F76)/F76),"–") -> 2.440678 | K76: =IFERROR(IF(OR(F76=0,H76=0,F76="",H76=""),"-",(H76-F76)/F76),"–") -> 2.5762712 | L76: =IFERROR(IF(OR(F76=0,I76=0,F76="",I76=""),"-",(I76-F76)/F76),"–") -> 2.9830508 | M76: =IFERROR(IF(OR(G76=0,H76=0,G76="",H76=""),"-",(H76-G76)/G76),"–") -> 0.039408867 | N76: =IFERROR(IF(OR(G76=0,I76=0,G76="",I76=""),"-",(I76-G76)/G76),"–") -> 0.15763547 | O76: =IFERROR(IF(OR(H76=0,I76=0,H76="",I76=""),"-",(I76-H76)/H76),"–") -> 0.11374408 | P76: =IFERROR(ROUND(AVERAGEIF(F76:I76,"<>0"),0),"–") -> 177
A77: 3808 | B77: =IFERROR(_xlfn.XLOOKUP(A77,Aktiv!$A:$A,Aktiv!$C:$C,"–"),"") -> Klappenboden | C77: =IFERROR(_xlfn.XLOOKUP(A77,Aktiv!$A:$A,Aktiv!$D:$D,"–"),"") -> Klappenboden (780x580) | D77: =IFERROR(_xlfn.XLOOKUP(A77,Aktiv!$A:$A,Aktiv!$E:$E,"–"),"") -> 780 | E77: =IFERROR(_xlfn.XLOOKUP(A77,Aktiv!$A:$A,Aktiv!$F:$F,"–"),"") -> 580 | F77: =IFERROR(_xlfn.XLOOKUP(A77,Aktiv!$A:$A,Aktiv!$G:$G,"–"),"") -> 80 | G77: =IFERROR(_xlfn.XLOOKUP(A77,Aktiv!$A:$A,Aktiv!$H:$H,"–"),"") -> 273 | H77: =IFERROR(_xlfn.XLOOKUP(A77,Aktiv!$A:$A,Aktiv!$I:$I,"–"),"") -> 284 | I77: =IFERROR(_xlfn.XLOOKUP(A77,Aktiv!$A:$A,Aktiv!$J:$J,"–"),"") -> 316 | J77: =IFERROR(IF(OR(F77=0,G77=0,F77="",G77=""),"-",(G77-F77)/F77),"–") -> 2.4125 | K77: =IFERROR(IF(OR(F77=0,H77=0,F77="",H77=""),"-",(H77-F77)/F77),"–") -> 2.55 | L77: =IFERROR(IF(OR(F77=0,I77=0,F77="",I77=""),"-",(I77-F77)/F77),"–") -> 2.95 | M77: =IFERROR(IF(OR(G77=0,H77=0,G77="",H77=""),"-",(H77-G77)/G77),"–") -> 0.04029304 | N77: =IFERROR(IF(OR(G77=0,I77=0,G77="",I77=""),"-",(I77-G77)/G77),"–") -> 0.15750916 | O77: =IFERROR(IF(OR(H77=0,I77=0,H77="",I77=""),"-",(I77-H77)/H77),"–") -> 0.11267606 | P77: =IFERROR(ROUND(AVERAGEIF(F77:I77,"<>0"),0),"–") -> 238
A78: 3809 | B78: =IFERROR(_xlfn.XLOOKUP(A78,Aktiv!$A:$A,Aktiv!$C:$C,"–"),"") -> Klappenboden | C78: =IFERROR(_xlfn.XLOOKUP(A78,Aktiv!$A:$A,Aktiv!$D:$D,"–"),"") -> Klappenboden (980x580) | D78: =IFERROR(_xlfn.XLOOKUP(A78,Aktiv!$A:$A,Aktiv!$E:$E,"–"),"") -> 980 | E78: =IFERROR(_xlfn.XLOOKUP(A78,Aktiv!$A:$A,Aktiv!$F:$F,"–"),"") -> 580 | F78: =IFERROR(_xlfn.XLOOKUP(A78,Aktiv!$A:$A,Aktiv!$G:$G,"–"),"") -> 100 | G78: =IFERROR(_xlfn.XLOOKUP(A78,Aktiv!$A:$A,Aktiv!$H:$H,"–"),"") -> 343 | H78: =IFERROR(_xlfn.XLOOKUP(A78,Aktiv!$A:$A,Aktiv!$I:$I,"–"),"") -> 357 | I78: =IFERROR(_xlfn.XLOOKUP(A78,Aktiv!$A:$A,Aktiv!$J:$J,"–"),"") -> 398 | J78: =IFERROR(IF(OR(F78=0,G78=0,F78="",G78=""),"-",(G78-F78)/F78),"–") -> 2.43 | K78: =IFERROR(IF(OR(F78=0,H78=0,F78="",H78=""),"-",(H78-F78)/F78),"–") -> 2.57 | L78: =IFERROR(IF(OR(F78=0,I78=0,F78="",I78=""),"-",(I78-F78)/F78),"–") -> 2.98 | M78: =IFERROR(IF(OR(G78=0,H78=0,G78="",H78=""),"-",(H78-G78)/G78),"–") -> 0.040816327 | N78: =IFERROR(IF(OR(G78=0,I78=0,G78="",I78=""),"-",(I78-G78)/G78),"–") -> 0.16034985 | O78: =IFERROR(IF(OR(H78=0,I78=0,H78="",I78=""),"-",(I78-H78)/H78),"–") -> 0.11484594 | P78: =IFERROR(ROUND(AVERAGEIF(F78:I78,"<>0"),0),"–") -> 300
A79: 3810 | B79: =IFERROR(_xlfn.XLOOKUP(A79,Aktiv!$A:$A,Aktiv!$C:$C,"–"),"") -> Klappenboden | C79: =IFERROR(_xlfn.XLOOKUP(A79,Aktiv!$A:$A,Aktiv!$D:$D,"–"),"") -> Klappenboden (420x780) | D79: =IFERROR(_xlfn.XLOOKUP(A79,Aktiv!$A:$A,Aktiv!$E:$E,"–"),"") -> 420 | E79: =IFERROR(_xlfn.XLOOKUP(A79,Aktiv!$A:$A,Aktiv!$F:$F,"–"),"") -> 780 | F79: =IFERROR(_xlfn.XLOOKUP(A79,Aktiv!$A:$A,Aktiv!$G:$G,"–"),"") -> - | G79: =IFERROR(_xlfn.XLOOKUP(A79,Aktiv!$A:$A,Aktiv!$H:$H,"–"),"") -> - | H79: =IFERROR(_xlfn.XLOOKUP(A79,Aktiv!$A:$A,Aktiv!$I:$I,"–"),"") -> - | I79: =IFERROR(_xlfn.XLOOKUP(A79,Aktiv!$A:$A,Aktiv!$J:$J,"–"),"") -> - | J79: =IFERROR(IF(OR(F79=0,G79=0,F79="",G79=""),"-",(G79-F79)/F79),"–") -> – | K79: =IFERROR(IF(OR(F79=0,H79=0,F79="",H79=""),"-",(H79-F79)/F79),"–") -> – | L79: =IFERROR(IF(OR(F79=0,I79=0,F79="",I79=""),"-",(I79-F79)/F79),"–") -> – | M79: =IFERROR(IF(OR(G79=0,H79=0,G79="",H79=""),"-",(H79-G79)/G79),"–") -> – | N79: =IFERROR(IF(OR(G79=0,I79=0,G79="",I79=""),"-",(I79-G79)/G79),"–") -> – | O79: =IFERROR(IF(OR(H79=0,I79=0,H79="",I79=""),"-",(I79-H79)/H79),"–") -> – | P79: =IFERROR(ROUND(AVERAGEIF(F79:I79,"<>0"),0),"–") -> –
A80: 3811 | B80: =IFERROR(_xlfn.XLOOKUP(A80,Aktiv!$A:$A,Aktiv!$C:$C,"–"),"") -> Klappenboden | C80: =IFERROR(_xlfn.XLOOKUP(A80,Aktiv!$A:$A,Aktiv!$D:$D,"–"),"") -> Klappenboden (420x980) | D80: =IFERROR(_xlfn.XLOOKUP(A80,Aktiv!$A:$A,Aktiv!$E:$E,"–"),"") -> 420 | E80: =IFERROR(_xlfn.XLOOKUP(A80,Aktiv!$A:$A,Aktiv!$F:$F,"–"),"") -> 980 | F80: =IFERROR(_xlfn.XLOOKUP(A80,Aktiv!$A:$A,Aktiv!$G:$G,"–"),"") -> - | G80: =IFERROR(_xlfn.XLOOKUP(A80,Aktiv!$A:$A,Aktiv!$H:$H,"–"),"") -> - | H80: =IFERROR(_xlfn.XLOOKUP(A80,Aktiv!$A:$A,Aktiv!$I:$I,"–"),"") -> - | I80: =IFERROR(_xlfn.XLOOKUP(A80,Aktiv!$A:$A,Aktiv!$J:$J,"–"),"") -> - | J80: =IFERROR(IF(OR(F80=0,G80=0,F80="",G80=""),"-",(G80-F80)/F80),"–") -> – | K80: =IFERROR(IF(OR(F80=0,H80=0,F80="",H80=""),"-",(H80-F80)/F80),"–") -> – | L80: =IFERROR(IF(OR(F80=0,I80=0,F80="",I80=""),"-",(I80-F80)/F80),"–") -> – | M80: =IFERROR(IF(OR(G80=0,H80=0,G80="",H80=""),"-",(H80-G80)/G80),"–") -> – | N80: =IFERROR(IF(OR(G80=0,I80=0,G80="",I80=""),"-",(I80-G80)/G80),"–") -> – | O80: =IFERROR(IF(OR(H80=0,I80=0,H80="",I80=""),"-",(I80-H80)/H80),"–") -> – | P80: =IFERROR(ROUND(AVERAGEIF(F80:I80,"<>0"),0),"–") -> –
... A122: 5307 | B122: =IFERROR(_xlfn.XLOOKUP(A122,Aktiv!$A:$A,Aktiv!$C:$C,"–"),"") -> Schublade | C122: =IFERROR(_xlfn.XLOOKUP(A122,Aktiv!$A:$A,Aktiv!$D:$D,"–"),"") -> Schublade (980x360) | D122: =IFERROR(_xlfn.XLOOKUP(A122,Aktiv!$A:$A,Aktiv!$E:$E,"–"),"") -> 980 | E122: =IFERROR(_xlfn.XLOOKUP(A122,Aktiv!$A:$A,Aktiv!$F:$F,"–"),"") -> 360 | F122: =IFERROR(_xlfn.XLOOKUP(A122,Aktiv!$A:$A,Aktiv!$G:$G,"–"),"") -> 349 | G122: =IFERROR(_xlfn.XLOOKUP(A122,Aktiv!$A:$A,Aktiv!$H:$H,"–"),"") -> 414 | H122: =IFERROR(_xlfn.XLOOKUP(A122,Aktiv!$A:$A,Aktiv!$I:$I,"–"),"") -> 451 | I122: =IFERROR(_xlfn.XLOOKUP(A122,Aktiv!$A:$A,Aktiv!$J:$J,"–"),"") -> - | J122: =IFERROR(IF(OR(F122=0,G122=0,F122="",G122=""),"-",(G122-F122)/F122),"–") -> 0.18624642 | K122: =IFERROR(IF(OR(F122=0,H122=0,F122="",H122=""),"-",(H122-F122)/F122),"–") -> 0.29226361 | L122: =IFERROR(IF(OR(F122=0,I122=0,F122="",I122=""),"-",(I122-F122)/F122),"–") -> – | M122: =IFERROR(IF(OR(G122=0,H122=0,G122="",H122=""),"-",(H122-G122)/G122),"–") -> 0.089371981 | N122: =IFERROR(IF(OR(G122=0,I122=0,G122="",I122=""),"-",(I122-G122)/G122),"–") -> – | O122: =IFERROR(IF(OR(H122=0,I122=0,H122="",I122=""),"-",(I122-H122)/H122),"–") -> – | P122: =IFERROR(ROUND(AVERAGEIF(F122:I122,"<>0"),0),"–") -> 405
A123: S_0001 | B123: =IFERROR(_xlfn.XLOOKUP(A123,Aktiv!$A:$A,Aktiv!$C:$C,"–"),"") -> Schublade | C123: =IFERROR(_xlfn.XLOOKUP(A123,Aktiv!$A:$A,Aktiv!$D:$D,"–"),"") -> Schublade (420x134) | D123: =IFERROR(_xlfn.XLOOKUP(A123,Aktiv!$A:$A,Aktiv!$E:$E,"–"),"") -> 420 | E123: =IFERROR(_xlfn.XLOOKUP(A123,Aktiv!$A:$A,Aktiv!$F:$F,"–"),"") -> 134 | F123: =IFERROR(_xlfn.XLOOKUP(A123,Aktiv!$A:$A,Aktiv!$G:$G,"–"),"") -> - | G123: =IFERROR(_xlfn.XLOOKUP(A123,Aktiv!$A:$A,Aktiv!$H:$H,"–"),"") -> - | H123: =IFERROR(_xlfn.XLOOKUP(A123,Aktiv!$A:$A,Aktiv!$I:$I,"–"),"") -> - | I123: =IFERROR(_xlfn.XLOOKUP(A123,Aktiv!$A:$A,Aktiv!$J:$J,"–"),"") -> - | J123: =IFERROR(IF(OR(F123=0,G123=0,F123="",G123=""),"-",(G123-F123)/F123),"–") -> – | K123: =IFERROR(IF(OR(F123=0,H123=0,F123="",H123=""),"-",(H123-F123)/F123),"–") -> – | L123: =IFERROR(IF(OR(F123=0,I123=0,F123="",I123=""),"-",(I123-F123)/F123),"–") -> – | M123: =IFERROR(IF(OR(G123=0,H123=0,G123="",H123=""),"-",(H123-G123)/G123),"–") -> – | N123: =IFERROR(IF(OR(G123=0,I123=0,G123="",I123=""),"-",(I123-G123)/G123),"–") -> – | O123: =IFERROR(IF(OR(H123=0,I123=0,H123="",I123=""),"-",(I123-H123)/H123),"–") -> – | P123: =IFERROR(ROUND(AVERAGEIF(F123:I123,"<>0"),0),"–") -> –
A124: S_0002 | B124: =IFERROR(_xlfn.XLOOKUP(A124,Aktiv!$A:$A,Aktiv!$C:$C,"–"),"") -> Schublade | C124: =IFERROR(_xlfn.XLOOKUP(A124,Aktiv!$A:$A,Aktiv!$D:$D,"–"),"") -> Schublade (420x220) | D124: =IFERROR(_xlfn.XLOOKUP(A124,Aktiv!$A:$A,Aktiv!$E:$E,"–"),"") -> 420 | E124: =IFERROR(_xlfn.XLOOKUP(A124,Aktiv!$A:$A,Aktiv!$F:$F,"–"),"") -> 220 | F124: =IFERROR(_xlfn.XLOOKUP(A124,Aktiv!$A:$A,Aktiv!$G:$G,"–"),"") -> - | G124: =IFERROR(_xlfn.XLOOKUP(A124,Aktiv!$A:$A,Aktiv!$H:$H,"–"),"") -> - | H124: =IFERROR(_xlfn.XLOOKUP(A124,Aktiv!$A:$A,Aktiv!$I:$I,"–"),"") -> - | I124: =IFERROR(_xlfn.XLOOKUP(A124,Aktiv!$A:$A,Aktiv!$J:$J,"–"),"") -> - | J124: =IFERROR(IF(OR(F124=0,G124=0,F124="",G124=""),"-",(G124-F124)/F124),"–") -> – | K124: =IFERROR(IF(OR(F124=0,H124=0,F124="",H124=""),"-",(H124-F124)/F124),"–") -> – | L124: =IFERROR(IF(OR(F124=0,I124=0,F124="",I124=""),"-",(I124-F124)/F124),"–") -> – | M124: =IFERROR(IF(OR(G124=0,H124=0,G124="",H124=""),"-",(H124-G124)/G124),"–") -> – | N124: =IFERROR(IF(OR(G124=0,I124=0,G124="",I124=""),"-",(I124-G124)/G124),"–") -> – | O124: =IFERROR(IF(OR(H124=0,I124=0,H124="",I124=""),"-",(I124-H124)/H124),"–") -> – | P124: =IFERROR(ROUND(AVERAGEIF(F124:I124,"<>0"),0),"–") -> –
A125: S_0009 | B125: =IFERROR(_xlfn.XLOOKUP(A125,Aktiv!$A:$A,Aktiv!$C:$C,"–"),"") -> Schublade | C125: =IFERROR(_xlfn.XLOOKUP(A125,Aktiv!$A:$A,Aktiv!$D:$D,"–"),"") -> Schublade (412x121) | D125: =IFERROR(_xlfn.XLOOKUP(A125,Aktiv!$A:$A,Aktiv!$E:$E,"–"),"") -> 412 | E125: =IFERROR(_xlfn.XLOOKUP(A125,Aktiv!$A:$A,Aktiv!$F:$F,"–"),"") -> 121 | F125: =IFERROR(_xlfn.XLOOKUP(A125,Aktiv!$A:$A,Aktiv!$G:$G,"–"),"") -> - | G125: =IFERROR(_xlfn.XLOOKUP(A125,Aktiv!$A:$A,Aktiv!$H:$H,"–"),"") -> - | H125: =IFERROR(_xlfn.XLOOKUP(A125,Aktiv!$A:$A,Aktiv!$I:$I,"–"),"") -> - | I125: =IFERROR(_xlfn.XLOOKUP(A125,Aktiv!$A:$A,Aktiv!$J:$J,"–"),"") -> - | J125: =IFERROR(IF(OR(F125=0,G125=0,F125="",G125=""),"-",(G125-F125)/F125),"–") -> – | K125: =IFERROR(IF(OR(F125=0,H125=0,F125="",H125=""),"-",(H125-F125)/F125),"–") -> – | L125: =IFERROR(IF(OR(F125=0,I125=0,F125="",I125=""),"-",(I125-F125)/F125),"–") -> – | M125: =IFERROR(IF(OR(G125=0,H125=0,G125="",H125=""),"-",(H125-G125)/G125),"–") -> – | N125: =IFERROR(IF(OR(G125=0,I125=0,G125="",I125=""),"-",(I125-G125)/G125),"–") -> – | O125: =IFERROR(IF(OR(H125=0,I125=0,H125="",I125=""),"-",(I125-H125)/H125),"–") -> – | P125: =IFERROR(ROUND(AVERAGEIF(F125:I125,"<>0"),0),"–") -> –
A126: S_0010 | B126: =IFERROR(_xlfn.XLOOKUP(A126,Aktiv!$A:$A,Aktiv!$C:$C,"–"),"") -> Schublade | C126: =IFERROR(_xlfn.XLOOKUP(A126,Aktiv!$A:$A,Aktiv!$D:$D,"–"),"") -> Schublade (412x400) | D126: =IFERROR(_xlfn.XLOOKUP(A126,Aktiv!$A:$A,Aktiv!$E:$E,"–"),"") -> 412 | E126: =IFERROR(_xlfn.XLOOKUP(A126,Aktiv!$A:$A,Aktiv!$F:$F,"–"),"") -> 400 | F126: =IFERROR(_xlfn.XLOOKUP(A126,Aktiv!$A:$A,Aktiv!$G:$G,"–"),"") -> - | G126: =IFERROR(_xlfn.XLOOKUP(A126,Aktiv!$A:$A,Aktiv!$H:$H,"–"),"") -> - | H126: =IFERROR(_xlfn.XLOOKUP(A126,Aktiv!$A:$A,Aktiv!$I:$I,"–"),"") -> - | I126: =IFERROR(_xlfn.XLOOKUP(A126,Aktiv!$A:$A,Aktiv!$J:$J,"–"),"") -> - | J126: =IFERROR(IF(OR(F126=0,G126=0,F126="",G126=""),"-",(G126-F126)/F126),"–") -> – | K126: =IFERROR(IF(OR(F126=0,H126=0,F126="",H126=""),"-",(H126-F126)/F126),"–") -> – | L126: =IFERROR(IF(OR(F126=0,I126=0,F126="",I126=""),"-",(I126-F126)/F126),"–") -> – | M126: =IFERROR(IF(OR(G126=0,H126=0,G126="",H126=""),"-",(H126-G126)/G126),"–") -> – | N126: =IFERROR(IF(OR(G126=0,I126=0,G126="",I126=""),"-",(I126-G126)/G126),"–") -> – | O126: =IFERROR(IF(OR(H126=0,I126=0,H126="",I126=""),"-",(I126-H126)/H126),"–") -> – | P126: =IFERROR(ROUND(AVERAGEIF(F126:I126,"<>0"),0),"–") -> –
A127: S_0017 | B127: =IFERROR(_xlfn.XLOOKUP(A127,Aktiv!$A:$A,Aktiv!$C:$C,"–"),"") -> Schublade | C127: =IFERROR(_xlfn.XLOOKUP(A127,Aktiv!$A:$A,Aktiv!$D:$D,"–"),"") -> Schublade (420x145) | D127: =IFERROR(_xlfn.XLOOKUP(A127,Aktiv!$A:$A,Aktiv!$E:$E,"–"),"") -> 420 | E127: =IFERROR(_xlfn.XLOOKUP(A127,Aktiv!$A:$A,Aktiv!$F:$F,"–"),"") -> 145 | F127: =IFERROR(_xlfn.XLOOKUP(A127,Aktiv!$A:$A,Aktiv!$G:$G,"–"),"") -> - | G127: =IFERROR(_xlfn.XLOOKUP(A127,Aktiv!$A:$A,Aktiv!$H:$H,"–"),"") -> - | H127: =IFERROR(_xlfn.XLOOKUP(A127,Aktiv!$A:$A,Aktiv!$I:$I,"–"),"") -> - | I127: =IFERROR(_xlfn.XLOOKUP(A127,Aktiv!$A:$A,Aktiv!$J:$J,"–"),"") -> - | J127: =IFERROR(IF(OR(F127=0,G127=0,F127="",G127=""),"-",(G127-F127)/F127),"–") -> – | K127: =IFERROR(IF(OR(F127=0,H127=0,F127="",H127=""),"-",(H127-F127)/F127),"–") -> – | L127: =IFERROR(IF(OR(F127=0,I127=0,F127="",I127=""),"-",(I127-F127)/F127),"–") -> – | M127: =IFERROR(IF(OR(G127=0,H127=0,G127="",H127=""),"-",(H127-G127)/G127),"–") -> – | N127: =IFERROR(IF(OR(G127=0,I127=0,G127="",I127=""),"-",(I127-G127)/G127),"–") -> – | O127: =IFERROR(IF(OR(H127=0,I127=0,H127="",I127=""),"-",(I127-H127)/H127),"–") -> – | P127: =IFERROR(ROUND(AVERAGEIF(F127:I127,"<>0"),0),"–") -> –
A128: S_0018 | B128: =IFERROR(_xlfn.XLOOKUP(A128,Aktiv!$A:$A,Aktiv!$C:$C,"–"),"") -> Schublade | C128: =IFERROR(_xlfn.XLOOKUP(A128,Aktiv!$A:$A,Aktiv!$D:$D,"–"),"") -> Schublade (420x293) | D128: =IFERROR(_xlfn.XLOOKUP(A128,Aktiv!$A:$A,Aktiv!$E:$E,"–"),"") -> 420 | E128: =IFERROR(_xlfn.XLOOKUP(A128,Aktiv!$A:$A,Aktiv!$F:$F,"–"),"") -> 293 | F128: =IFERROR(_xlfn.XLOOKUP(A128,Aktiv!$A:$A,Aktiv!$G:$G,"–"),"") -> - | G128: =IFERROR(_xlfn.XLOOKUP(A128,Aktiv!$A:$A,Aktiv!$H:$H,"–"),"") -> - | H128: =IFERROR(_xlfn.XLOOKUP(A128,Aktiv!$A:$A,Aktiv!$I:$I,"–"),"") -> - | I128: =IFERROR(_xlfn.XLOOKUP(A128,Aktiv!$A:$A,Aktiv!$J:$J,"–"),"") -> - | J128: =IFERROR(IF(OR(F128=0,G128=0,F128="",G128=""),"-",(G128-F128)/F128),"–") -> – | K128: =IFERROR(IF(OR(F128=0,H128=0,F128="",H128=""),"-",(H128-F128)/F128),"–") -> – | L128: =IFERROR(IF(OR(F128=0,I128=0,F128="",I128=""),"-",(I128-F128)/F128),"–") -> – | M128: =IFERROR(IF(OR(G128=0,H128=0,G128="",H128=""),"-",(H128-G128)/G128),"–") -> – | N128: =IFERROR(IF(OR(G128=0,I128=0,G128="",I128=""),"-",(I128-G128)/G128),"–") -> – | O128: =IFERROR(IF(OR(H128=0,I128=0,H128="",I128=""),"-",(I128-H128)/H128),"–") -> – | P128: =IFERROR(ROUND(AVERAGEIF(F128:I128,"<>0"),0),"–") -> –
A129: S_0029 | B129: =IFERROR(_xlfn.XLOOKUP(A129,Aktiv!$A:$A,Aktiv!$C:$C,"–"),"") -> Schublade | C129: =IFERROR(_xlfn.XLOOKUP(A129,Aktiv!$A:$A,Aktiv!$D:$D,"–"),"") -> Schublade (420x67) | D129: =IFERROR(_xlfn.XLOOKUP(A129,Aktiv!$A:$A,Aktiv!$E:$E,"–"),"") -> 420 | E129: =IFERROR(_xlfn.XLOOKUP(A129,Aktiv!$A:$A,Aktiv!$F:$F,"–"),"") -> 67 | F129: =IFERROR(_xlfn.XLOOKUP(A129,Aktiv!$A:$A,Aktiv!$G:$G,"–"),"") -> - | G129: =IFERROR(_xlfn.XLOOKUP(A129,Aktiv!$A:$A,Aktiv!$H:$H,"–"),"") -> - | H129: =IFERROR(_xlfn.XLOOKUP(A129,Aktiv!$A:$A,Aktiv!$I:$I,"–"),"") -> - | I129: =IFERROR(_xlfn.XLOOKUP(A129,Aktiv!$A:$A,Aktiv!$J:$J,"–"),"") -> - | J129: =IFERROR(IF(OR(F129=0,G129=0,F129="",G129=""),"-",(G129-F129)/F129),"–") -> – | K129: =IFERROR(IF(OR(F129=0,H129=0,F129="",H129=""),"-",(H129-F129)/F129),"–") -> – | L129: =IFERROR(IF(OR(F129=0,I129=0,F129="",I129=""),"-",(I129-F129)/F129),"–") -> – | M129: =IFERROR(IF(OR(G129=0,H129=0,G129="",H129=""),"-",(H129-G129)/G129),"–") -> – | N129: =IFERROR(IF(OR(G129=0,I129=0,G129="",I129=""),"-",(I129-G129)/G129),"–") -> – | O129: =IFERROR(IF(OR(H129=0,I129=0,H129="",I129=""),"-",(I129-H129)/H129),"–") -> – | P129: =IFERROR(ROUND(AVERAGEIF(F129:I129,"<>0"),0),"–") -> –
A130: S_0033 | B130: =IFERROR(_xlfn.XLOOKUP(A130,Aktiv!$A:$A,Aktiv!$C:$C,"–"),"") -> Schublade | C130: =IFERROR(_xlfn.XLOOKUP(A130,Aktiv!$A:$A,Aktiv!$D:$D,"–"),"") -> Schublade (420x142) | D130: =IFERROR(_xlfn.XLOOKUP(A130,Aktiv!$A:$A,Aktiv!$E:$E,"–"),"") -> 420 | E130: =IFERROR(_xlfn.XLOOKUP(A130,Aktiv!$A:$A,Aktiv!$F:$F,"–"),"") -> 142 | F130: =IFERROR(_xlfn.XLOOKUP(A130,Aktiv!$A:$A,Aktiv!$G:$G,"–"),"") -> - | G130: =IFERROR(_xlfn.XLOOKUP(A130,Aktiv!$A:$A,Aktiv!$H:$H,"–"),"") -> - | H130: =IFERROR(_xlfn.XLOOKUP(A130,Aktiv!$A:$A,Aktiv!$I:$I,"–"),"") -> - | I130: =IFERROR(_xlfn.XLOOKUP(A130,Aktiv!$A:$A,Aktiv!$J:$J,"–"),"") -> - | J130: =IFERROR(IF(OR(F130=0,G130=0,F130="",G130=""),"-",(G130-F130)/F130),"–") -> – | K130: =IFERROR(IF(OR(F130=0,H130=0,F130="",H130=""),"-",(H130-F130)/F130),"–") -> – | L130: =IFERROR(IF(OR(F130=0,I130=0,F130="",I130=""),"-",(I130-F130)/F130),"–") -> – | M130: =IFERROR(IF(OR(G130=0,H130=0,G130="",H130=""),"-",(H130-G130)/G130),"–") -> – | N130: =IFERROR(IF(OR(G130=0,I130=0,G130="",I130=""),"-",(I130-G130)/G130),"–") -> – | O130: =IFERROR(IF(OR(H130=0,I130=0,H130="",I130=""),"-",(I130-H130)/H130),"–") -> – | P130: =IFERROR(ROUND(AVERAGEIF(F130:I130,"<>0"),0),"–") -> –
A131: S_0034 | B131: =IFERROR(_xlfn.XLOOKUP(A131,Aktiv!$A:$A,Aktiv!$C:$C,"–"),"") -> Schublade | C131: =IFERROR(_xlfn.XLOOKUP(A131,Aktiv!$A:$A,Aktiv!$D:$D,"–"),"") -> Schublade (420x280) | D131: =IFERROR(_xlfn.XLOOKUP(A131,Aktiv!$A:$A,Aktiv!$E:$E,"–"),"") -> 420 | E131: =IFERROR(_xlfn.XLOOKUP(A131,Aktiv!$A:$A,Aktiv!$F:$F,"–"),"") -> 280 | F131: =IFERROR(_xlfn.XLOOKUP(A131,Aktiv!$A:$A,Aktiv!$G:$G,"–"),"") -> - | G131: =IFERROR(_xlfn.XLOOKUP(A131,Aktiv!$A:$A,Aktiv!$H:$H,"–"),"") -> - | H131: =IFERROR(_xlfn.XLOOKUP(A131,Aktiv!$A:$A,Aktiv!$I:$I,"–"),"") -> - | I131: =IFERROR(_xlfn.XLOOKUP(A131,Aktiv!$A:$A,Aktiv!$J:$J,"–"),"") -> - | J131: =IFERROR(IF(OR(F131=0,G131=0,F131="",G131=""),"-",(G131-F131)/F131),"–") -> – | K131: =IFERROR(IF(OR(F131=0,H131=0,F131="",H131=""),"-",(H131-F131)/F131),"–") -> – | L131: =IFERROR(IF(OR(F131=0,I131=0,F131="",I131=""),"-",(I131-F131)/F131),"–") -> – | M131: =IFERROR(IF(OR(G131=0,H131=0,G131="",H131=""),"-",(H131-G131)/G131),"–") -> – | N131: =IFERROR(IF(OR(G131=0,I131=0,G131="",I131=""),"-",(I131-G131)/G131),"–") -> – | O131: =IFERROR(IF(OR(H131=0,I131=0,H131="",I131=""),"-",(I131-H131)/H131),"–") -> – | P131: =IFERROR(ROUND(AVERAGEIF(F131:I131,"<>0"),0),"–") -> –
A132: S_0037 | B132: =IFERROR(_xlfn.XLOOKUP(A132,Aktiv!$A:$A,Aktiv!$C:$C,"–"),"") -> Schublade | C132: =IFERROR(_xlfn.XLOOKUP(A132,Aktiv!$A:$A,Aktiv!$D:$D,"–"),"") -> Schublade (420x141) | D132: =IFERROR(_xlfn.XLOOKUP(A132,Aktiv!$A:$A,Aktiv!$E:$E,"–"),"") -> 420 | E132: =IFERROR(_xlfn.XLOOKUP(A132,Aktiv!$A:$A,Aktiv!$F:$F,"–"),"") -> 141 | F132: =IFERROR(_xlfn.XLOOKUP(A132,Aktiv!$A:$A,Aktiv!$G:$G,"–"),"") -> - | G132: =IFERROR(_xlfn.XLOOKUP(A132,Aktiv!$A:$A,Aktiv!$H:$H,"–"),"") -> - | H132: =IFERROR(_xlfn.XLOOKUP(A132,Aktiv!$A:$A,Aktiv!$I:$I,"–"),"") -> - | I132: =IFERROR(_xlfn.XLOOKUP(A132,Aktiv!$A:$A,Aktiv!$J:$J,"–"),"") -> - | J132: =IFERROR(IF(OR(F132=0,G132=0,F132="",G132=""),"-",(G132-F132)/F132),"–") -> – | K132: =IFERROR(IF(OR(F132=0,H132=0,F132="",H132=""),"-",(H132-F132)/F132),"–") -> – | L132: =IFERROR(IF(OR(F132=0,I132=0,F132="",I132=""),"-",(I132-F132)/F132),"–") -> – | M132: =IFERROR(IF(OR(G132=0,H132=0,G132="",H132=""),"-",(H132-G132)/G132),"–") -> – | N132: =IFERROR(IF(OR(G132=0,I132=0,G132="",I132=""),"-",(I132-G132)/G132),"–") -> – | O132: =IFERROR(IF(OR(H132=0,I132=0,H132="",I132=""),"-",(I132-H132)/H132),"–") -> – | P132: =IFERROR(ROUND(AVERAGEIF(F132:I132,"<>0"),0),"–") -> –
A133: S_0044 | B133: =IFERROR(_xlfn.XLOOKUP(A133,Aktiv!$A:$A,Aktiv!$C:$C,"–"),"") -> Schublade | C133: =IFERROR(_xlfn.XLOOKUP(A133,Aktiv!$A:$A,Aktiv!$D:$D,"–"),"") -> Schublade (780x180) | D133: =IFERROR(_xlfn.XLOOKUP(A133,Aktiv!$A:$A,Aktiv!$E:$E,"–"),"") -> 780 | E133: =IFERROR(_xlfn.XLOOKUP(A133,Aktiv!$A:$A,Aktiv!$F:$F,"–"),"") -> 180 | F133: =IFERROR(_xlfn.XLOOKUP(A133,Aktiv!$A:$A,Aktiv!$G:$G,"–"),"") -> 318 | G133: =IFERROR(_xlfn.XLOOKUP(A133,Aktiv!$A:$A,Aktiv!$H:$H,"–"),"") -> 378 | H133: =IFERROR(_xlfn.XLOOKUP(A133,Aktiv!$A:$A,Aktiv!$I:$I,"–"),"") -> 411 | I133: =IFERROR(_xlfn.XLOOKUP(A133,Aktiv!$A:$A,Aktiv!$J:$J,"–"),"") -> - | J133: =IFERROR(IF(OR(F133=0,G133=0,F133="",G133=""),"-",(G133-F133)/F133),"–") -> 0.18867925 | K133: =IFERROR(IF(OR(F133=0,H133=0,F133="",H133=""),"-",(H133-F133)/F133),"–") -> 0.29245283 | L133: =IFERROR(IF(OR(F133=0,I133=0,F133="",I133=""),"-",(I133-F133)/F133),"–") -> – | M133: =IFERROR(IF(OR(G133=0,H133=0,G133="",H133=""),"-",(H133-G133)/G133),"–") -> 0.087301587 | N133: =IFERROR(IF(OR(G133=0,I133=0,G133="",I133=""),"-",(I133-G133)/G133),"–") -> – | O133: =IFERROR(IF(OR(H133=0,I133=0,H133="",I133=""),"-",(I133-H133)/H133),"–") -> – | P133: =IFERROR(ROUND(AVERAGEIF(F133:I133,"<>0"),0),"–") -> 369
A134: 5400 | B134: =IFERROR(_xlfn.XLOOKUP(A134,Aktiv!$A:$A,Aktiv!$C:$C,"–"),"") -> Schublade LB 1 | C134: =IFERROR(_xlfn.XLOOKUP(A134,Aktiv!$A:$A,Aktiv!$D:$D,"–"),"") -> Schublade LB 1 (420x180) | D134: =IFERROR(_xlfn.XLOOKUP(A134,Aktiv!$A:$A,Aktiv!$E:$E,"–"),"") -> 420 | E134: =IFERROR(_xlfn.XLOOKUP(A134,Aktiv!$A:$A,Aktiv!$F:$F,"–"),"") -> 180 | F134: =IFERROR(_xlfn.XLOOKUP(A134,Aktiv!$A:$A,Aktiv!$G:$G,"–"),"") -> 299 | G134: =IFERROR(_xlfn.XLOOKUP(A134,Aktiv!$A:$A,Aktiv!$H:$H,"–"),"") -> 355 | H134: =IFERROR(_xlfn.XLOOKUP(A134,Aktiv!$A:$A,Aktiv!$I:$I,"–"),"") -> 386 | I134: =IFERROR(_xlfn.XLOOKUP(A134,Aktiv!$A:$A,Aktiv!$J:$J,"–"),"") -> - | J134: =IFERROR(IF(OR(F134=0,G134=0,F134="",G134=""),"-",(G134-F134)/F134),"–") -> 0.18729097 | K134: =IFERROR(IF(OR(F134=0,H134=0,F134="",H134=""),"-",(H134-F134)/F134),"–") -> 0.2909699 | L134: =IFERROR(IF(OR(F134=0,I134=0,F134="",I134=""),"-",(I134-F134)/F134),"–") -> – | M134: =IFERROR(IF(OR(G134=0,H134=0,G134="",H134=""),"-",(H134-G134)/G134),"–") -> 0.087323944 | N134: =IFERROR(IF(OR(G134=0,I134=0,G134="",I134=""),"-",(I134-G134)/G134),"–") -> – | O134: =IFERROR(IF(OR(H134=0,I134=0,H134="",I134=""),"-",(I134-H134)/H134),"–") -> – | P134: =IFERROR(ROUND(AVERAGEIF(F134:I134,"<>0"),0),"–") -> 347
A135: 5401 | B135: =IFERROR(_xlfn.XLOOKUP(A135,Aktiv!$A:$A,Aktiv!$C:$C,"–"),"") -> Schublade LB 1 | C135: =IFERROR(_xlfn.XLOOKUP(A135,Aktiv!$A:$A,Aktiv!$D:$D,"–"),"") -> Schublade LB 1 (420x360) | D135: =IFERROR(_xlfn.XLOOKUP(A135,Aktiv!$A:$A,Aktiv!$E:$E,"–"),"") -> 420 | E135: =IFERROR(_xlfn.XLOOKUP(A135,Aktiv!$A:$A,Aktiv!$F:$F,"–"),"") -> 360 | F135: =IFERROR(_xlfn.XLOOKUP(A135,Aktiv!$A:$A,Aktiv!$G:$G,"–"),"") -> 320 | G135: =IFERROR(_xlfn.XLOOKUP(A135,Aktiv!$A:$A,Aktiv!$H:$H,"–"),"") -> 381 | H135: =IFERROR(_xlfn.XLOOKUP(A135,Aktiv!$A:$A,Aktiv!$I:$I,"–"),"") -> 414 | I135: =IFERROR(_xlfn.XLOOKUP(A135,Aktiv!$A:$A,Aktiv!$J:$J,"–"),"") -> - | J135: =IFERROR(IF(OR(F135=0,G135=0,F135="",G135=""),"-",(G135-F135)/F135),"–") -> 0.190625 | K135: =IFERROR(IF(OR(F135=0,H135=0,F135="",H135=""),"-",(H135-F135)/F135),"–") -> 0.29375 | L135: =IFERROR(IF(OR(F135=0,I135=0,F135="",I135=""),"-",(I135-F135)/F135),"–") -> – | M135: =IFERROR(IF(OR(G135=0,H135=0,G135="",H135=""),"-",(H135-G135)/G135),"–") -> 0.086614173 | N135: =IFERROR(IF(OR(G135=0,I135=0,G135="",I135=""),"-",(I135-G135)/G135),"–") -> – | O135: =IFERROR(IF(OR(H135=0,I135=0,H135="",I135=""),"-",(I135-H135)/H135),"–") -> – | P135: =IFERROR(ROUND(AVERAGEIF(F135:I135,"<>0"),0),"–") -> 372
A136: 5402 | B136: =IFERROR(_xlfn.XLOOKUP(A136,Aktiv!$A:$A,Aktiv!$C:$C,"–"),"") -> Schublade LB 1 | C136: =IFERROR(_xlfn.XLOOKUP(A136,Aktiv!$A:$A,Aktiv!$D:$D,"–"),"") -> Schublade LB 1 (580x180) | D136: =IFERROR(_xlfn.XLOOKUP(A136,Aktiv!$A:$A,Aktiv!$E:$E,"–"),"") -> 580 | E136: =IFERROR(_xlfn.XLOOKUP(A136,Aktiv!$A:$A,Aktiv!$F:$F,"–"),"") -> 180 | F136: =IFERROR(_xlfn.XLOOKUP(A136,Aktiv!$A:$A,Aktiv!$G:$G,"–"),"") -> 309 | G136: =IFERROR(_xlfn.XLOOKUP(A136,Aktiv!$A:$A,Aktiv!$H:$H,"–"),"") -> 367 | H136: =IFERROR(_xlfn.XLOOKUP(A136,Aktiv!$A:$A,Aktiv!$I:$I,"–"),"") -> 399 | I136: =IFERROR(_xlfn.XLOOKUP(A136,Aktiv!$A:$A,Aktiv!$J:$J,"–"),"") -> - | J136: =IFERROR(IF(OR(F136=0,G136=0,F136="",G136=""),"-",(G136-F136)/F136),"–") -> 0.18770227 | K136: =IFERROR(IF(OR(F136=0,H136=0,F136="",H136=""),"-",(H136-F136)/F136),"–") -> 0.29126214 | L136: =IFERROR(IF(OR(F136=0,I136=0,F136="",I136=""),"-",(I136-F136)/F136),"–") -> – | M136: =IFERROR(IF(OR(G136=0,H136=0,G136="",H136=""),"-",(H136-G136)/G136),"–") -> 0.08719346 | N136: =IFERROR(IF(OR(G136=0,I136=0,G136="",I136=""),"-",(I136-G136)/G136),"–") -> – | O136: =IFERROR(IF(OR(H136=0,I136=0,H136="",I136=""),"-",(I136-H136)/H136),"–") -> – | P136: =IFERROR(ROUND(AVERAGEIF(F136:I136,"<>0"),0),"–") -> 358
A137: 5403 | B137: =IFERROR(_xlfn.XLOOKUP(A137,Aktiv!$A:$A,Aktiv!$C:$C,"–"),"") -> Schublade LB 1 | C137: =IFERROR(_xlfn.XLOOKUP(A137,Aktiv!$A:$A,Aktiv!$D:$D,"–"),"") -> Schublade LB 1 (580x360) | D137: =IFERROR(_xlfn.XLOOKUP(A137,Aktiv!$A:$A,Aktiv!$E:$E,"–"),"") -> 580 | E137: =IFERROR(_xlfn.XLOOKUP(A137,Aktiv!$A:$A,Aktiv!$F:$F,"–"),"") -> 360 | F137: =IFERROR(_xlfn.XLOOKUP(A137,Aktiv!$A:$A,Aktiv!$G:$G,"–"),"") -> 331 | G137: =IFERROR(_xlfn.XLOOKUP(A137,Aktiv!$A:$A,Aktiv!$H:$H,"–"),"") -> 393 | H137: =IFERROR(_xlfn.XLOOKUP(A137,Aktiv!$A:$A,Aktiv!$I:$I,"–"),"") -> 428 | I137: =IFERROR(_xlfn.XLOOKUP(A137,Aktiv!$A:$A,Aktiv!$J:$J,"–"),"") -> - | J137: =IFERROR(IF(OR(F137=0,G137=0,F137="",G137=""),"-",(G137-F137)/F137),"–") -> 0.18731118 | K137: =IFERROR(IF(OR(F137=0,H137=0,F137="",H137=""),"-",(H137-F137)/F137),"–") -> 0.29305136 | L137: =IFERROR(IF(OR(F137=0,I137=0,F137="",I137=""),"-",(I137-F137)/F137),"–") -> – | M137: =IFERROR(IF(OR(G137=0,H137=0,G137="",H137=""),"-",(H137-G137)/G137),"–") -> 0.089058524 | N137: =IFERROR(IF(OR(G137=0,I137=0,G137="",I137=""),"-",(I137-G137)/G137),"–") -> – | O137: =IFERROR(IF(OR(H137=0,I137=0,H137="",I137=""),"-",(I137-H137)/H137),"–") -> – | P137: =IFERROR(ROUND(AVERAGEIF(F137:I137,"<>0"),0),"–") -> 384
A138: 5404 | B138: =IFERROR(_xlfn.XLOOKUP(A138,Aktiv!$A:$A,Aktiv!$C:$C,"–"),"") -> Schublade LB 1 | C138: =IFERROR(_xlfn.XLOOKUP(A138,Aktiv!$A:$A,Aktiv!$D:$D,"–"),"") -> Schublade LB 1 (780x180) | D138: =IFERROR(_xlfn.XLOOKUP(A138,Aktiv!$A:$A,Aktiv!$E:$E,"–"),"") -> 780 | E138: =IFERROR(_xlfn.XLOOKUP(A138,Aktiv!$A:$A,Aktiv!$F:$F,"–"),"") -> 180 | F138: =IFERROR(_xlfn.XLOOKUP(A138,Aktiv!$A:$A,Aktiv!$G:$G,"–"),"") -> 318 | G138: =IFERROR(_xlfn.XLOOKUP(A138,Aktiv!$A:$A,Aktiv!$H:$H,"–"),"") -> 378 | H138: =IFERROR(_xlfn.XLOOKUP(A138,Aktiv!$A:$A,Aktiv!$I:$I,"–"),"") -> 411 | I138: =IFERROR(_xlfn.XLOOKUP(A138,Aktiv!$A:$A,Aktiv!$J:$J,"–"),"") -> - | J138: =IFERROR(IF(OR(F138=0,G138=0,F138="",G138=""),"-",(G138-F138)/F138),"–") -> 0.18867925 | K138: =IFERROR(IF(OR(F138=0,H138=0,F138="",H138=""),"-",(H138-F138)/F138),"–") -> 0.29245283 | L138: =IFERROR(IF(OR(F138=0,I138=0,F138="",I138=""),"-",(I138-F138)/F138),"–") -> – | M138: =IFERROR(IF(OR(G138=0,H138=0,G138="",H138=""),"-",(H138-G138)/G138),"–") -> 0.087301587 | N138: =IFERROR(IF(OR(G138=0,I138=0,G138="",I138=""),"-",(I138-G138)/G138),"–") -> – | O138: =IFERROR(IF(OR(H138=0,I138=0,H138="",I138=""),"-",(I138-H138)/H138),"–") -> – | P138: =IFERROR(ROUND(AVERAGEIF(F138:I138,"<>0"),0),"–") -> 369
A139: 5405 | B139: =IFERROR(_xlfn.XLOOKUP(A139,Aktiv!$A:$A,Aktiv!$C:$C,"–"),"") -> Schublade LB 1 | C139: =IFERROR(_xlfn.XLOOKUP(A139,Aktiv!$A:$A,Aktiv!$D:$D,"–"),"") -> Schublade LB 1 (780x360) | D139: =IFERROR(_xlfn.XLOOKUP(A139,Aktiv!$A:$A,Aktiv!$E:$E,"–"),"") -> 780 | E139: =IFERROR(_xlfn.XLOOKUP(A139,Aktiv!$A:$A,Aktiv!$F:$F,"–"),"") -> 360 | F139: =IFERROR(_xlfn.XLOOKUP(A139,Aktiv!$A:$A,Aktiv!$G:$G,"–"),"") -> 341 | G139: =IFERROR(_xlfn.XLOOKUP(A139,Aktiv!$A:$A,Aktiv!$H:$H,"–"),"") -> 405 | H139: =IFERROR(_xlfn.XLOOKUP(A139,Aktiv!$A:$A,Aktiv!$I:$I,"–"),"") -> 441 | I139: =IFERROR(_xlfn.XLOOKUP(A139,Aktiv!$A:$A,Aktiv!$J:$J,"–"),"") -> - | J139: =IFERROR(IF(OR(F139=0,G139=0,F139="",G139=""),"-",(G139-F139)/F139),"–") -> 0.18768328 | K139: =IFERROR(IF(OR(F139=0,H139=0,F139="",H139=""),"-",(H139-F139)/F139),"–") -> 0.29325513 | L139: =IFERROR(IF(OR(F139=0,I139=0,F139="",I139=""),"-",(I139-F139)/F139),"–") -> – | M139: =IFERROR(IF(OR(G139=0,H139=0,G139="",H139=""),"-",(H139-G139)/G139),"–") -> 0.088888889 | N139: =IFERROR(IF(OR(G139=0,I139=0,G139="",I139=""),"-",(I139-G139)/G139),"–") -> – | O139: =IFERROR(IF(OR(H139=0,I139=0,H139="",I139=""),"-",(I139-H139)/H139),"–") -> – | P139: =IFERROR(ROUND(AVERAGEIF(F139:I139,"<>0"),0),"–") -> 396
A140: 5406 | B140: =IFERROR(_xlfn.XLOOKUP(A140,Aktiv!$A:$A,Aktiv!$C:$C,"–"),"") -> Schublade LB 1 | C140: =IFERROR(_xlfn.XLOOKUP(A140,Aktiv!$A:$A,Aktiv!$D:$D,"–"),"") -> Schublade LB 1 (980x180) | D140: =IFERROR(_xlfn.XLOOKUP(A140,Aktiv!$A:$A,Aktiv!$E:$E,"–"),"") -> 980 | E140: =IFERROR(_xlfn.XLOOKUP(A140,Aktiv!$A:$A,Aktiv!$F:$F,"–"),"") -> 180 | F140: =IFERROR(_xlfn.XLOOKUP(A140,Aktiv!$A:$A,Aktiv!$G:$G,"–"),"") -> 325 | G140: =IFERROR(_xlfn.XLOOKUP(A140,Aktiv!$A:$A,Aktiv!$H:$H,"–"),"") -> 386 | H140: =IFERROR(_xlfn.XLOOKUP(A140,Aktiv!$A:$A,Aktiv!$I:$I,"–"),"") -> 421 | I140: =IFERROR(_xlfn.XLOOKUP(A140,Aktiv!$A:$A,Aktiv!$J:$J,"–"),"") -> - | J140: =IFERROR(IF(OR(F140=0,G140=0,F140="",G140=""),"-",(G140-F140)/F140),"–") -> 0.18769231 | K140: =IFERROR(IF(OR(F140=0,H140=0,F140="",H140=""),"-",(H140-F140)/F140),"–") -> 0.29538462 | L140: =IFERROR(IF(OR(F140=0,I140=0,F140="",I140=""),"-",(I140-F140)/F140),"–") -> – | M140: =IFERROR(IF(OR(G140=0,H140=0,G140="",H140=""),"-",(H140-G140)/G140),"–") -> 0.090673575 | N140: =IFERROR(IF(OR(G140=0,I140=0,G140="",I140=""),"-",(I140-G140)/G140),"–") -> – | O140: =IFERROR(IF(OR(H140=0,I140=0,H140="",I140=""),"-",(I140-H140)/H140),"–") -> – | P140: =IFERROR(ROUND(AVERAGEIF(F140:I140,"<>0"),0),"–") -> 377
A141: 5407 | B141: =IFERROR(_xlfn.XLOOKUP(A141,Aktiv!$A:$A,Aktiv!$C:$C,"–"),"") -> Schublade LB 1 | C141: =IFERROR(_xlfn.XLOOKUP(A141,Aktiv!$A:$A,Aktiv!$D:$D,"–"),"") -> Schublade LB 1 (980x360) | D141: =IFERROR(_xlfn.XLOOKUP(A141,Aktiv!$A:$A,Aktiv!$E:$E,"–"),"") -> 980 | E141: =IFERROR(_xlfn.XLOOKUP(A141,Aktiv!$A:$A,Aktiv!$F:$F,"–"),"") -> 360 | F141: =IFERROR(_xlfn.XLOOKUP(A141,Aktiv!$A:$A,Aktiv!$G:$G,"–"),"") -> 349 | G141: =IFERROR(_xlfn.XLOOKUP(A141,Aktiv!$A:$A,Aktiv!$H:$H,"–"),"") -> 414 | H141: =IFERROR(_xlfn.XLOOKUP(A141,Aktiv!$A:$A,Aktiv!$I:$I,"–"),"") -> 451 | I141: =IFERROR(_xlfn.XLOOKUP(A141,Aktiv!$A:$A,Aktiv!$J:$J,"–"),"") -> - | J141: =IFERROR(IF(OR(F141=0,G141=0,F141="",G141=""),"-",(G141-F141)/F141),"–") -> 0.18624642 | K141: =IFERROR(IF(OR(F141=0,H141=0,F141="",H141=""),"-",(H141-F141)/F141),"–") -> 0.29226361 | L141: =IFERROR(IF(OR(F141=0,I141=0,F141="",I141=""),"-",(I141-F141)/F141),"–") -> – | M141: =IFERROR(IF(OR(G141=0,H141=0,G141="",H141=""),"-",(H141-G141)/G141),"–") -> 0.089371981 | N141: =IFERROR(IF(OR(G141=0,I141=0,G141="",I141=""),"-",(I141-G141)/G141),"–") -> – | O141: =IFERROR(IF(OR(H141=0,I141=0,H141="",I141=""),"-",(I141-H141)/H141),"–") -> – | P141: =IFERROR(ROUND(AVERAGEIF(F141:I141,"<>0"),0),"–") -> 405
A142: 5500 | B142: =IFERROR(_xlfn.XLOOKUP(A142,Aktiv!$A:$A,Aktiv!$C:$C,"–"),"") -> Schublade LB 2 | C142: =IFERROR(_xlfn.XLOOKUP(A142,Aktiv!$A:$A,Aktiv!$D:$D,"–"),"") -> Schublade LB 2 (420x180) | D142: =IFERROR(_xlfn.XLOOKUP(A142,Aktiv!$A:$A,Aktiv!$E:$E,"–"),"") -> 420 | E142: =IFERROR(_xlfn.XLOOKUP(A142,Aktiv!$A:$A,Aktiv!$F:$F,"–"),"") -> 180 | F142: =IFERROR(_xlfn.XLOOKUP(A142,Aktiv!$A:$A,Aktiv!$G:$G,"–"),"") -> 299 | G142: =IFERROR(_xlfn.XLOOKUP(A142,Aktiv!$A:$A,Aktiv!$H:$H,"–"),"") -> 355 | H142: =IFERROR(_xlfn.XLOOKUP(A142,Aktiv!$A:$A,Aktiv!$I:$I,"–"),"") -> 386 | I142: =IFERROR(_xlfn.XLOOKUP(A142,Aktiv!$A:$A,Aktiv!$J:$J,"–"),"") -> - | J142: =IFERROR(IF(OR(F142=0,G142=0,F142="",G142=""),"-",(G142-F142)/F142),"–") -> 0.18729097 | K142: =IFERROR(IF(OR(F142=0,H142=0,F142="",H142=""),"-",(H142-F142)/F142),"–") -> 0.2909699 | L142: =IFERROR(IF(OR(F142=0,I142=0,F142="",I142=""),"-",(I142-F142)/F142),"–") -> – | M142: =IFERROR(IF(OR(G142=0,H142=0,G142="",H142=""),"-",(H142-G142)/G142),"–") -> 0.087323944 | N142: =IFERROR(IF(OR(G142=0,I142=0,G142="",I142=""),"-",(I142-G142)/G142),"–") -> – | O142: =IFERROR(IF(OR(H142=0,I142=0,H142="",I142=""),"-",(I142-H142)/H142),"–") -> – | P142: =IFERROR(ROUND(AVERAGEIF(F142:I142,"<>0"),0),"–") -> 347
A143: 5501 | B143: =IFERROR(_xlfn.XLOOKUP(A143,Aktiv!$A:$A,Aktiv!$C:$C,"–"),"") -> Schublade LB 2 | C143: =IFERROR(_xlfn.XLOOKUP(A143,Aktiv!$A:$A,Aktiv!$D:$D,"–"),"") -> Schublade LB 2 (420x360) | D143: =IFERROR(_xlfn.XLOOKUP(A143,Aktiv!$A:$A,Aktiv!$E:$E,"–"),"") -> 420 | E143: =IFERROR(_xlfn.XLOOKUP(A143,Aktiv!$A:$A,Aktiv!$F:$F,"–"),"") -> 360 | F143: =IFERROR(_xlfn.XLOOKUP(A143,Aktiv!$A:$A,Aktiv!$G:$G,"–"),"") -> 320 | G143: =IFERROR(_xlfn.XLOOKUP(A143,Aktiv!$A:$A,Aktiv!$H:$H,"–"),"") -> 381 | H143: =IFERROR(_xlfn.XLOOKUP(A143,Aktiv!$A:$A,Aktiv!$I:$I,"–"),"") -> 414 | I143: =IFERROR(_xlfn.XLOOKUP(A143,Aktiv!$A:$A,Aktiv!$J:$J,"–"),"") -> - | J143: =IFERROR(IF(OR(F143=0,G143=0,F143="",G143=""),"-",(G143-F143)/F143),"–") -> 0.190625 | K143: =IFERROR(IF(OR(F143=0,H143=0,F143="",H143=""),"-",(H143-F143)/F143),"–") -> 0.29375 | L143: =IFERROR(IF(OR(F143=0,I143=0,F143="",I143=""),"-",(I143-F143)/F143),"–") -> – | M143: =IFERROR(IF(OR(G143=0,H143=0,G143="",H143=""),"-",(H143-G143)/G143),"–") -> 0.086614173 | N143: =IFERROR(IF(OR(G143=0,I143=0,G143="",I143=""),"-",(I143-G143)/G143),"–") -> – | O143: =IFERROR(IF(OR(H143=0,I143=0,H143="",I143=""),"-",(I143-H143)/H143),"–") -> – | P143: =IFERROR(ROUND(AVERAGEIF(F143:I143,"<>0"),0),"–") -> 372
A144: 5502 | B144: =IFERROR(_xlfn.XLOOKUP(A144,Aktiv!$A:$A,Aktiv!$C:$C,"–"),"") -> Schublade LB 2 | C144: =IFERROR(_xlfn.XLOOKUP(A144,Aktiv!$A:$A,Aktiv!$D:$D,"–"),"") -> Schublade LB 2 (580x180) | D144: =IFERROR(_xlfn.XLOOKUP(A144,Aktiv!$A:$A,Aktiv!$E:$E,"–"),"") -> 580 | E144: =IFERROR(_xlfn.XLOOKUP(A144,Aktiv!$A:$A,Aktiv!$F:$F,"–"),"") -> 180 | F144: =IFERROR(_xlfn.XLOOKUP(A144,Aktiv!$A:$A,Aktiv!$G:$G,"–"),"") -> 309 | G144: =IFERROR(_xlfn.XLOOKUP(A144,Aktiv!$A:$A,Aktiv!$H:$H,"–"),"") -> 367 | H144: =IFERROR(_xlfn.XLOOKUP(A144,Aktiv!$A:$A,Aktiv!$I:$I,"–"),"") -> 399 | I144: =IFERROR(_xlfn.XLOOKUP(A144,Aktiv!$A:$A,Aktiv!$J:$J,"–"),"") -> - | J144: =IFERROR(IF(OR(F144=0,G144=0,F144="",G144=""),"-",(G144-F144)/F144),"–") -> 0.18770227 | K144: =IFERROR(IF(OR(F144=0,H144=0,F144="",H144=""),"-",(H144-F144)/F144),"–") -> 0.29126214 | L144: =IFERROR(IF(OR(F144=0,I144=0,F144="",I144=""),"-",(I144-F144)/F144),"–") -> – | M144: =IFERROR(IF(OR(G144=0,H144=0,G144="",H144=""),"-",(H144-G144)/G144),"–") -> 0.08719346 | N144: =IFERROR(IF(OR(G144=0,I144=0,G144="",I144=""),"-",(I144-G144)/G144),"–") -> – | O144: =IFERROR(IF(OR(H144=0,I144=0,H144="",I144=""),"-",(I144-H144)/H144),"–") -> – | P144: =IFERROR(ROUND(AVERAGEIF(F144:I144,"<>0"),0),"–") -> 358
A145: 5503 | B145: =IFERROR(_xlfn.XLOOKUP(A145,Aktiv!$A:$A,Aktiv!$C:$C,"–"),"") -> Schublade LB 2 | C145: =IFERROR(_xlfn.XLOOKUP(A145,Aktiv!$A:$A,Aktiv!$D:$D,"–"),"") -> Schublade LB 2 (580x360) | D145: =IFERROR(_xlfn.XLOOKUP(A145,Aktiv!$A:$A,Aktiv!$E:$E,"–"),"") -> 580 | E145: =IFERROR(_xlfn.XLOOKUP(A145,Aktiv!$A:$A,Aktiv!$F:$F,"–"),"") -> 360 | F145: =IFERROR(_xlfn.XLOOKUP(A145,Aktiv!$A:$A,Aktiv!$G:$G,"–"),"") -> 331 | G145: =IFERROR(_xlfn.XLOOKUP(A145,Aktiv!$A:$A,Aktiv!$H:$H,"–"),"") -> 393 | H145: =IFERROR(_xlfn.XLOOKUP(A145,Aktiv!$A:$A,Aktiv!$I:$I,"–"),"") -> 428 | I145: =IFERROR(_xlfn.XLOOKUP(A145,Aktiv!$A:$A,Aktiv!$J:$J,"–"),"") -> - | J145: =IFERROR(IF(OR(F145=0,G145=0,F145="",G145=""),"-",(G145-F145)/F145),"–") -> 0.18731118 | K145: =IFERROR(IF(OR(F145=0,H145=0,F145="",H145=""),"-",(H145-F145)/F145),"–") -> 0.29305136 | L145: =IFERROR(IF(OR(F145=0,I145=0,F145="",I145=""),"-",(I145-F145)/F145),"–") -> – | M145: =IFERROR(IF(OR(G145=0,H145=0,G145="",H145=""),"-",(H145-G145)/G145),"–") -> 0.089058524 | N145: =IFERROR(IF(OR(G145=0,I145=0,G145="",I145=""),"-",(I145-G145)/G145),"–") -> – | O145: =IFERROR(IF(OR(H145=0,I145=0,H145="",I145=""),"-",(I145-H145)/H145),"–") -> – | P145: =IFERROR(ROUND(AVERAGEIF(F145:I145,"<>0"),0),"–") -> 384
... A174: 3124 | B174: =IFERROR(_xlfn.XLOOKUP(A174,Aktiv!$A:$A,Aktiv!$C:$C,"–"),"") -> Seite außen | C174: =IFERROR(_xlfn.XLOOKUP(A174,Aktiv!$A:$A,Aktiv!$D:$D,"–"),"") -> Seite außen (580x580) | D174: =IFERROR(_xlfn.XLOOKUP(A174,Aktiv!$A:$A,Aktiv!$E:$E,"–"),"") -> 580 | E174: =IFERROR(_xlfn.XLOOKUP(A174,Aktiv!$A:$A,Aktiv!$F:$F,"–"),"") -> 580 | F174: =IFERROR(_xlfn.XLOOKUP(A174,Aktiv!$A:$A,Aktiv!$G:$G,"–"),"") -> 59 | G174: =IFERROR(_xlfn.XLOOKUP(A174,Aktiv!$A:$A,Aktiv!$H:$H,"–"),"") -> 203 | H174: =IFERROR(_xlfn.XLOOKUP(A174,Aktiv!$A:$A,Aktiv!$I:$I,"–"),"") -> 211 | I174: =IFERROR(_xlfn.XLOOKUP(A174,Aktiv!$A:$A,Aktiv!$J:$J,"–"),"") -> - | J174: =IFERROR(IF(OR(F174=0,G174=0,F174="",G174=""),"-",(G174-F174)/F174),"–") -> 2.440678 | K174: =IFERROR(IF(OR(F174=0,H174=0,F174="",H174=""),"-",(H174-F174)/F174),"–") -> 2.5762712 | L174: =IFERROR(IF(OR(F174=0,I174=0,F174="",I174=""),"-",(I174-F174)/F174),"–") -> – | M174: =IFERROR(IF(OR(G174=0,H174=0,G174="",H174=""),"-",(H174-G174)/G174),"–") -> 0.039408867 | N174: =IFERROR(IF(OR(G174=0,I174=0,G174="",I174=""),"-",(I174-G174)/G174),"–") -> – | O174: =IFERROR(IF(OR(H174=0,I174=0,H174="",I174=""),"-",(I174-H174)/H174),"–") -> – | P174: =IFERROR(ROUND(AVERAGEIF(F174:I174,"<>0"),0),"–") -> 158
A175: S_0020 | B175: =IFERROR(_xlfn.XLOOKUP(A175,Aktiv!$A:$A,Aktiv!$C:$C,"–"),"") -> Seite außen | C175: =IFERROR(_xlfn.XLOOKUP(A175,Aktiv!$A:$A,Aktiv!$D:$D,"–"),"") -> Seite außen (660x360) | D175: =IFERROR(_xlfn.XLOOKUP(A175,Aktiv!$A:$A,Aktiv!$E:$E,"–"),"") -> 660 | E175: =IFERROR(_xlfn.XLOOKUP(A175,Aktiv!$A:$A,Aktiv!$F:$F,"–"),"") -> 360 | F175: =IFERROR(_xlfn.XLOOKUP(A175,Aktiv!$A:$A,Aktiv!$G:$G,"–"),"") -> 42 | G175: =IFERROR(_xlfn.XLOOKUP(A175,Aktiv!$A:$A,Aktiv!$H:$H,"–"),"") -> 143 | H175: =IFERROR(_xlfn.XLOOKUP(A175,Aktiv!$A:$A,Aktiv!$I:$I,"–"),"") -> 149 | I175: =IFERROR(_xlfn.XLOOKUP(A175,Aktiv!$A:$A,Aktiv!$J:$J,"–"),"") -> - | J175: =IFERROR(IF(OR(F175=0,G175=0,F175="",G175=""),"-",(G175-F175)/F175),"–") -> 2.4047619 | K175: =IFERROR(IF(OR(F175=0,H175=0,F175="",H175=""),"-",(H175-F175)/F175),"–") -> 2.547619 | L175: =IFERROR(IF(OR(F175=0,I175=0,F175="",I175=""),"-",(I175-F175)/F175),"–") -> – | M175: =IFERROR(IF(OR(G175=0,H175=0,G175="",H175=""),"-",(H175-G175)/G175),"–") -> 0.041958042 | N175: =IFERROR(IF(OR(G175=0,I175=0,G175="",I175=""),"-",(I175-G175)/G175),"–") -> – | O175: =IFERROR(IF(OR(H175=0,I175=0,H175="",I175=""),"-",(I175-H175)/H175),"–") -> – | P175: =IFERROR(ROUND(AVERAGEIF(F175:I175,"<>0"),0),"–") -> 111
A176: 3200 | B176: =IFERROR(_xlfn.XLOOKUP(A176,Aktiv!$A:$A,Aktiv!$C:$C,"–"),"") -> Seite außen SY32 | C176: =IFERROR(_xlfn.XLOOKUP(A176,Aktiv!$A:$A,Aktiv!$D:$D,"–"),"") -> Seite außen SY32 (360x360) | D176: =IFERROR(_xlfn.XLOOKUP(A176,Aktiv!$A:$A,Aktiv!$E:$E,"–"),"") -> 360 | E176: =IFERROR(_xlfn.XLOOKUP(A176,Aktiv!$A:$A,Aktiv!$F:$F,"–"),"") -> 360 | F176: =IFERROR(_xlfn.XLOOKUP(A176,Aktiv!$A:$A,Aktiv!$G:$G,"–"),"") -> 25 | G176: =IFERROR(_xlfn.XLOOKUP(A176,Aktiv!$A:$A,Aktiv!$H:$H,"–"),"") -> 103 | H176: =IFERROR(_xlfn.XLOOKUP(A176,Aktiv!$A:$A,Aktiv!$I:$I,"–"),"") -> 120 | I176: =IFERROR(_xlfn.XLOOKUP(A176,Aktiv!$A:$A,Aktiv!$J:$J,"–"),"") -> 145 | J176: =IFERROR(IF(OR(F176=0,G176=0,F176="",G176=""),"-",(G176-F176)/F176),"–") -> 3.12 | K176: =IFERROR(IF(OR(F176=0,H176=0,F176="",H176=""),"-",(H176-F176)/F176),"–") -> 3.8 | L176: =IFERROR(IF(OR(F176=0,I176=0,F176="",I176=""),"-",(I176-F176)/F176),"–") -> 4.8 | M176: =IFERROR(IF(OR(G176=0,H176=0,G176="",H176=""),"-",(H176-G176)/G176),"–") -> 0.16504854 | N176: =IFERROR(IF(OR(G176=0,I176=0,G176="",I176=""),"-",(I176-G176)/G176),"–") -> 0.40776699 | O176: =IFERROR(IF(OR(H176=0,I176=0,H176="",I176=""),"-",(I176-H176)/H176),"–") -> 0.20833333 | P176: =IFERROR(ROUND(AVERAGEIF(F176:I176,"<>0"),0),"–") -> 98
A177: 3201 | B177: =IFERROR(_xlfn.XLOOKUP(A177,Aktiv!$A:$A,Aktiv!$C:$C,"–"),"") -> Seite außen SY32 | C177: =IFERROR(_xlfn.XLOOKUP(A177,Aktiv!$A:$A,Aktiv!$D:$D,"–"),"") -> Seite außen SY32 (360x720) | D177: =IFERROR(_xlfn.XLOOKUP(A177,Aktiv!$A:$A,Aktiv!$E:$E,"–"),"") -> 360 | E177: =IFERROR(_xlfn.XLOOKUP(A177,Aktiv!$A:$A,Aktiv!$F:$F,"–"),"") -> 720 | F177: =IFERROR(_xlfn.XLOOKUP(A177,Aktiv!$A:$A,Aktiv!$G:$G,"–"),"") -> 46 | G177: =IFERROR(_xlfn.XLOOKUP(A177,Aktiv!$A:$A,Aktiv!$H:$H,"–"),"") -> 156 | H177: =IFERROR(_xlfn.XLOOKUP(A177,Aktiv!$A:$A,Aktiv!$I:$I,"–"),"") -> 163 | I177: =IFERROR(_xlfn.XLOOKUP(A177,Aktiv!$A:$A,Aktiv!$J:$J,"–"),"") -> 181 | J177: =IFERROR(IF(OR(F177=0,G177=0,F177="",G177=""),"-",(G177-F177)/F177),"–") -> 2.3913043 | K177: =IFERROR(IF(OR(F177=0,H177=0,F177="",H177=""),"-",(H177-F177)/F177),"–") -> 2.5434783 | L177: =IFERROR(IF(OR(F177=0,I177=0,F177="",I177=""),"-",(I177-F177)/F177),"–") -> 2.9347826 | M177: =IFERROR(IF(OR(G177=0,H177=0,G177="",H177=""),"-",(H177-G177)/G177),"–") -> 0.044871795 | N177: =IFERROR(IF(OR(G177=0,I177=0,G177="",I177=""),"-",(I177-G177)/G177),"–") -> 0.16025641 | O177: =IFERROR(IF(OR(H177=0,I177=0,H177="",I177=""),"-",(I177-H177)/H177),"–") -> 0.11042945 | P177: =IFERROR(ROUND(AVERAGEIF(F177:I177,"<>0"),0),"–") -> 137
A178: 3202 | B178: =IFERROR(_xlfn.XLOOKUP(A178,Aktiv!$A:$A,Aktiv!$C:$C,"–"),"") -> Seite außen SY32 | C178: =IFERROR(_xlfn.XLOOKUP(A178,Aktiv!$A:$A,Aktiv!$D:$D,"–"),"") -> Seite außen SY32 (360x1080) | D178: =IFERROR(_xlfn.XLOOKUP(A178,Aktiv!$A:$A,Aktiv!$E:$E,"–"),"") -> 360 | E178: =IFERROR(_xlfn.XLOOKUP(A178,Aktiv!$A:$A,Aktiv!$F:$F,"–"),"") -> 1080 | F178: =IFERROR(_xlfn.XLOOKUP(A178,Aktiv!$A:$A,Aktiv!$G:$G,"–"),"") -> 68 | G178: =IFERROR(_xlfn.XLOOKUP(A178,Aktiv!$A:$A,Aktiv!$H:$H,"–"),"") -> 235 | H178: =IFERROR(_xlfn.XLOOKUP(A178,Aktiv!$A:$A,Aktiv!$I:$I,"–"),"") -> 244 | I178: =IFERROR(_xlfn.XLOOKUP(A178,Aktiv!$A:$A,Aktiv!$J:$J,"–"),"") -> 272 | J178: =IFERROR(IF(OR(F178=0,G178=0,F178="",G178=""),"-",(G178-F178)/F178),"–") -> 2.4558824 | K178: =IFERROR(IF(OR(F178=0,H178=0,F178="",H178=""),"-",(H178-F178)/F178),"–") -> 2.5882353 | L178: =IFERROR(IF(OR(F178=0,I178=0,F178="",I178=""),"-",(I178-F178)/F178),"–") -> 3 | M178: =IFERROR(IF(OR(G178=0,H178=0,G178="",H178=""),"-",(H178-G178)/G178),"–") -> 0.038297872 | N178: =IFERROR(IF(OR(G178=0,I178=0,G178="",I178=""),"-",(I178-G178)/G178),"–") -> 0.15744681 | O178: =IFERROR(IF(OR(H178=0,I178=0,H178="",I178=""),"-",(I178-H178)/H178),"–") -> 0.1147541 | P178: =IFERROR(ROUND(AVERAGEIF(F178:I178,"<>0"),0),"–") -> 205
A179: 3203 | B179: =IFERROR(_xlfn.XLOOKUP(A179,Aktiv!$A:$A,Aktiv!$C:$C,"–"),"") -> Seite außen SY32 | C179: =IFERROR(_xlfn.XLOOKUP(A179,Aktiv!$A:$A,Aktiv!$D:$D,"–"),"") -> Seite außen SY32 (360x1440) | D179: =IFERROR(_xlfn.XLOOKUP(A179,Aktiv!$A:$A,Aktiv!$E:$E,"–"),"") -> 360 | E179: =IFERROR(_xlfn.XLOOKUP(A179,Aktiv!$A:$A,Aktiv!$F:$F,"–"),"") -> 1440 | F179: =IFERROR(_xlfn.XLOOKUP(A179,Aktiv!$A:$A,Aktiv!$G:$G,"–"),"") -> 91 | G179: =IFERROR(_xlfn.XLOOKUP(A179,Aktiv!$A:$A,Aktiv!$H:$H,"–"),"") -> 313 | H179: =IFERROR(_xlfn.XLOOKUP(A179,Aktiv!$A:$A,Aktiv!$I:$I,"–"),"") -> 326 | I179: =IFERROR(_xlfn.XLOOKUP(A179,Aktiv!$A:$A,Aktiv!$J:$J,"–"),"") -> 363 | J179: =IFERROR(IF(OR(F179=0,G179=0,F179="",G179=""),"-",(G179-F179)/F179),"–") -> 2.4395604 | K179: =IFERROR(IF(OR(F179=0,H179=0,F179="",H179=""),"-",(H179-F179)/F179),"–") -> 2.5824176 | L179: =IFERROR(IF(OR(F179=0,I179=0,F179="",I179=""),"-",(I179-F179)/F179),"–") -> 2.989011 | M179: =IFERROR(IF(OR(G179=0,H179=0,G179="",H179=""),"-",(H179-G179)/G179),"–") -> 0.041533546 | N179: =IFERROR(IF(OR(G179=0,I179=0,G179="",I179=""),"-",(I179-G179)/G179),"–") -> 0.15974441 | O179: =IFERROR(IF(OR(H179=0,I179=0,H179="",I179=""),"-",(I179-H179)/H179),"–") -> 0.11349693 | P179: =IFERROR(ROUND(AVERAGEIF(F179:I179,"<>0"),0),"–") -> 273
A180: 3204 | B180: =IFERROR(_xlfn.XLOOKUP(A180,Aktiv!$A:$A,Aktiv!$C:$C,"–"),"") -> Seite außen SY32 | C180: =IFERROR(_xlfn.XLOOKUP(A180,Aktiv!$A:$A,Aktiv!$D:$D,"–"),"") -> Seite außen SY32 (360x1800) | D180: =IFERROR(_xlfn.XLOOKUP(A180,Aktiv!$A:$A,Aktiv!$E:$E,"–"),"") -> 360 | E180: =IFERROR(_xlfn.XLOOKUP(A180,Aktiv!$A:$A,Aktiv!$F:$F,"–"),"") -> 1800 | F180: =IFERROR(_xlfn.XLOOKUP(A180,Aktiv!$A:$A,Aktiv!$G:$G,"–"),"") -> 114 | G180: =IFERROR(_xlfn.XLOOKUP(A180,Aktiv!$A:$A,Aktiv!$H:$H,"–"),"") -> 391 | H180: =IFERROR(_xlfn.XLOOKUP(A180,Aktiv!$A:$A,Aktiv!$I:$I,"–"),"") -> 407 | I180: =IFERROR(_xlfn.XLOOKUP(A180,Aktiv!$A:$A,Aktiv!$J:$J,"–"),"") -> 453 | J180: =IFERROR(IF(OR(F180=0,G180=0,F180="",G180=""),"-",(G180-F180)/F180),"–") -> 2.4298246 | K180: =IFERROR(IF(OR(F180=0,H180=0,F180="",H180=""),"-",(H180-F180)/F180),"–") -> 2.5701754 | L180: =IFERROR(IF(OR(F180=0,I180=0,F180="",I180=""),"-",(I180-F180)/F180),"–") -> 2.9736842 | M180: =IFERROR(IF(OR(G180=0,H180=0,G180="",H180=""),"-",(H180-G180)/G180),"–") -> 0.040920716 | N180: =IFERROR(IF(OR(G180=0,I180=0,G180="",I180=""),"-",(I180-G180)/G180),"–") -> 0.15856777 | O180: =IFERROR(IF(OR(H180=0,I180=0,H180="",I180=""),"-",(I180-H180)/H180),"–") -> 0.11302211 | P180: =IFERROR(ROUND(AVERAGEIF(F180:I180,"<>0"),0),"–") -> 341
A181: 3205 | B181: =IFERROR(_xlfn.XLOOKUP(A181,Aktiv!$A:$A,Aktiv!$C:$C,"–"),"") -> Seite außen SY32 | C181: =IFERROR(_xlfn.XLOOKUP(A181,Aktiv!$A:$A,Aktiv!$D:$D,"–"),"") -> Seite außen SY32 (580x360) | D181: =IFERROR(_xlfn.XLOOKUP(A181,Aktiv!$A:$A,Aktiv!$E:$E,"–"),"") -> 580 | E181: =IFERROR(_xlfn.XLOOKUP(A181,Aktiv!$A:$A,Aktiv!$F:$F,"–"),"") -> 360 | F181: =IFERROR(_xlfn.XLOOKUP(A181,Aktiv!$A:$A,Aktiv!$G:$G,"–"),"") -> 37 | G181: =IFERROR(_xlfn.XLOOKUP(A181,Aktiv!$A:$A,Aktiv!$H:$H,"–"),"") -> 126 | H181: =IFERROR(_xlfn.XLOOKUP(A181,Aktiv!$A:$A,Aktiv!$I:$I,"–"),"") -> 131 | I181: =IFERROR(_xlfn.XLOOKUP(A181,Aktiv!$A:$A,Aktiv!$J:$J,"–"),"") -> 146 | J181: =IFERROR(IF(OR(F181=0,G181=0,F181="",G181=""),"-",(G181-F181)/F181),"–") -> 2.4054054 | K181: =IFERROR(IF(OR(F181=0,H181=0,F181="",H181=""),"-",(H181-F181)/F181),"–") -> 2.5405405 | L181: =IFERROR(IF(OR(F181=0,I181=0,F181="",I181=""),"-",(I181-F181)/F181),"–") -> 2.9459459 | M181: =IFERROR(IF(OR(G181=0,H181=0,G181="",H181=""),"-",(H181-G181)/G181),"–") -> 0.03968254 | N181: =IFERROR(IF(OR(G181=0,I181=0,G181="",I181=""),"-",(I181-G181)/G181),"–") -> 0.15873016 | O181: =IFERROR(IF(OR(H181=0,I181=0,H181="",I181=""),"-",(I181-H181)/H181),"–") -> 0.11450382 | P181: =IFERROR(ROUND(AVERAGEIF(F181:I181,"<>0"),0),"–") -> 110
A182: 3206 | B182: =IFERROR(_xlfn.XLOOKUP(A182,Aktiv!$A:$A,Aktiv!$C:$C,"–"),"") -> Seite außen SY32 | C182: =IFERROR(_xlfn.XLOOKUP(A182,Aktiv!$A:$A,Aktiv!$D:$D,"–"),"") -> Seite außen SY32 (580x720) | D182: =IFERROR(_xlfn.XLOOKUP(A182,Aktiv!$A:$A,Aktiv!$E:$E,"–"),"") -> 580 | E182: =IFERROR(_xlfn.XLOOKUP(A182,Aktiv!$A:$A,Aktiv!$F:$F,"–"),"") -> 720 | F182: =IFERROR(_xlfn.XLOOKUP(A182,Aktiv!$A:$A,Aktiv!$G:$G,"–"),"") -> 73 | G182: =IFERROR(_xlfn.XLOOKUP(A182,Aktiv!$A:$A,Aktiv!$H:$H,"–"),"") -> 252 | H182: =IFERROR(_xlfn.XLOOKUP(A182,Aktiv!$A:$A,Aktiv!$I:$I,"–"),"") -> 262 | I182: =IFERROR(_xlfn.XLOOKUP(A182,Aktiv!$A:$A,Aktiv!$J:$J,"–"),"") -> 292 | J182: =IFERROR(IF(OR(F182=0,G182=0,F182="",G182=""),"-",(G182-F182)/F182),"–") -> 2.4520548 | K182: =IFERROR(IF(OR(F182=0,H182=0,F182="",H182=""),"-",(H182-F182)/F182),"–") -> 2.5890411 | L182: =IFERROR(IF(OR(F182=0,I182=0,F182="",I182=""),"-",(I182-F182)/F182),"–") -> 3 | M182: =IFERROR(IF(OR(G182=0,H182=0,G182="",H182=""),"-",(H182-G182)/G182),"–") -> 0.03968254 | N182: =IFERROR(IF(OR(G182=0,I182=0,G182="",I182=""),"-",(I182-G182)/G182),"–") -> 0.15873016 | O182: =IFERROR(IF(OR(H182=0,I182=0,H182="",I182=""),"-",(I182-H182)/H182),"–") -> 0.11450382 | P182: =IFERROR(ROUND(AVERAGEIF(F182:I182,"<>0"),0),"–") -> 220
A183: 3207 | B183: =IFERROR(_xlfn.XLOOKUP(A183,Aktiv!$A:$A,Aktiv!$C:$C,"–"),"") -> Seite außen SY32 | C183: =IFERROR(_xlfn.XLOOKUP(A183,Aktiv!$A:$A,Aktiv!$D:$D,"–"),"") -> Seite außen SY32 (580x1080) | D183: =IFERROR(_xlfn.XLOOKUP(A183,Aktiv!$A:$A,Aktiv!$E:$E,"–"),"") -> 580 | E183: =IFERROR(_xlfn.XLOOKUP(A183,Aktiv!$A:$A,Aktiv!$F:$F,"–"),"") -> 1080 | F183: =IFERROR(_xlfn.XLOOKUP(A183,Aktiv!$A:$A,Aktiv!$G:$G,"–"),"") -> 110 | G183: =IFERROR(_xlfn.XLOOKUP(A183,Aktiv!$A:$A,Aktiv!$H:$H,"–"),"") -> 378 | H183: =IFERROR(_xlfn.XLOOKUP(A183,Aktiv!$A:$A,Aktiv!$I:$I,"–"),"") -> 394 | I183: =IFERROR(_xlfn.XLOOKUP(A183,Aktiv!$A:$A,Aktiv!$J:$J,"–"),"") -> 438 | J183: =IFERROR(IF(OR(F183=0,G183=0,F183="",G183=""),"-",(G183-F183)/F183),"–") -> 2.4363636 | K183: =IFERROR(IF(OR(F183=0,H183=0,F183="",H183=""),"-",(H183-F183)/F183),"–") -> 2.5818182 | L183: =IFERROR(IF(OR(F183=0,I183=0,F183="",I183=""),"-",(I183-F183)/F183),"–") -> 2.9818182 | M183: =IFERROR(IF(OR(G183=0,H183=0,G183="",H183=""),"-",(H183-G183)/G183),"–") -> 0.042328042 | N183: =IFERROR(IF(OR(G183=0,I183=0,G183="",I183=""),"-",(I183-G183)/G183),"–") -> 0.15873016 | O183: =IFERROR(IF(OR(H183=0,I183=0,H183="",I183=""),"-",(I183-H183)/H183),"–") -> 0.11167513 | P183: =IFERROR(ROUND(AVERAGEIF(F183:I183,"<>0"),0),"–") -> 330
A184: 3208 | B184: =IFERROR(_xlfn.XLOOKUP(A184,Aktiv!$A:$A,Aktiv!$C:$C,"–"),"") -> Seite außen SY32 | C184: =IFERROR(_xlfn.XLOOKUP(A184,Aktiv!$A:$A,Aktiv!$D:$D,"–"),"") -> Seite außen SY32 (580x1440) | D184: =IFERROR(_xlfn.XLOOKUP(A184,Aktiv!$A:$A,Aktiv!$E:$E,"–"),"") -> 580 | E184: =IFERROR(_xlfn.XLOOKUP(A184,Aktiv!$A:$A,Aktiv!$F:$F,"–"),"") -> 1440 | F184: =IFERROR(_xlfn.XLOOKUP(A184,Aktiv!$A:$A,Aktiv!$G:$G,"–"),"") -> 147 | G184: =IFERROR(_xlfn.XLOOKUP(A184,Aktiv!$A:$A,Aktiv!$H:$H,"–"),"") -> 504 | H184: =IFERROR(_xlfn.XLOOKUP(A184,Aktiv!$A:$A,Aktiv!$I:$I,"–"),"") -> 525 | I184: =IFERROR(_xlfn.XLOOKUP(A184,Aktiv!$A:$A,Aktiv!$J:$J,"–"),"") -> 584 | J184: =IFERROR(IF(OR(F184=0,G184=0,F184="",G184=""),"-",(G184-F184)/F184),"–") -> 2.4285714 | K184: =IFERROR(IF(OR(F184=0,H184=0,F184="",H184=""),"-",(H184-F184)/F184),"–") -> 2.5714286 | L184: =IFERROR(IF(OR(F184=0,I184=0,F184="",I184=""),"-",(I184-F184)/F184),"–") -> 2.9727891 | M184: =IFERROR(IF(OR(G184=0,H184=0,G184="",H184=""),"-",(H184-G184)/G184),"–") -> 0.041666667 | N184: =IFERROR(IF(OR(G184=0,I184=0,G184="",I184=""),"-",(I184-G184)/G184),"–") -> 0.15873016 | O184: =IFERROR(IF(OR(H184=0,I184=0,H184="",I184=""),"-",(I184-H184)/H184),"–") -> 0.11238095 | P184: =IFERROR(ROUND(AVERAGEIF(F184:I184,"<>0"),0),"–") -> 440
A185: 3209 | B185: =IFERROR(_xlfn.XLOOKUP(A185,Aktiv!$A:$A,Aktiv!$C:$C,"–"),"") -> Seite außen SY32 | C185: =IFERROR(_xlfn.XLOOKUP(A185,Aktiv!$A:$A,Aktiv!$D:$D,"–"),"") -> Seite außen SY32 (580x1800) | D185: =IFERROR(_xlfn.XLOOKUP(A185,Aktiv!$A:$A,Aktiv!$E:$E,"–"),"") -> 580 | E185: =IFERROR(_xlfn.XLOOKUP(A185,Aktiv!$A:$A,Aktiv!$F:$F,"–"),"") -> 1800 | F185: =IFERROR(_xlfn.XLOOKUP(A185,Aktiv!$A:$A,Aktiv!$G:$G,"–"),"") -> 184 | G185: =IFERROR(_xlfn.XLOOKUP(A185,Aktiv!$A:$A,Aktiv!$H:$H,"–"),"") -> 630 | H185: =IFERROR(_xlfn.XLOOKUP(A185,Aktiv!$A:$A,Aktiv!$I:$I,"–"),"") -> 656 | I185: =IFERROR(_xlfn.XLOOKUP(A185,Aktiv!$A:$A,Aktiv!$J:$J,"–"),"") -> 730 | J185: =IFERROR(IF(OR(F185=0,G185=0,F185="",G185=""),"-",(G185-F185)/F185),"–") -> 2.423913 | K185: =IFERROR(IF(OR(F185=0,H185=0,F185="",H185=""),"-",(H185-F185)/F185),"–") -> 2.5652174 | L185: =IFERROR(IF(OR(F185=0,I185=0,F185="",I185=""),"-",(I185-F185)/F185),"–") -> 2.9673913 | M185: =IFERROR(IF(OR(G185=0,H185=0,G185="",H185=""),"-",(H185-G185)/G185),"–") -> 0.041269841 | N185: =IFERROR(IF(OR(G185=0,I185=0,G185="",I185=""),"-",(I185-G185)/G185),"–") -> 0.15873016 | O185: =IFERROR(IF(OR(H185=0,I185=0,H185="",I185=""),"-",(I185-H185)/H185),"–") -> 0.11280488 | P185: =IFERROR(ROUND(AVERAGEIF(F185:I185,"<>0"),0),"–") -> 550
A186: 3210 | B186: =IFERROR(_xlfn.XLOOKUP(A186,Aktiv!$A:$A,Aktiv!$C:$C,"–"),"") -> Seite außen SY32 | C186: =IFERROR(_xlfn.XLOOKUP(A186,Aktiv!$A:$A,Aktiv!$D:$D,"–"),"") -> Seite außen SY32 (180x780) | D186: =IFERROR(_xlfn.XLOOKUP(A186,Aktiv!$A:$A,Aktiv!$E:$E,"–"),"") -> 180 | E186: =IFERROR(_xlfn.XLOOKUP(A186,Aktiv!$A:$A,Aktiv!$F:$F,"–"),"") -> 780 | F186: =IFERROR(_xlfn.XLOOKUP(A186,Aktiv!$A:$A,Aktiv!$G:$G,"–"),"") -> 25 | G186: =IFERROR(_xlfn.XLOOKUP(A186,Aktiv!$A:$A,Aktiv!$H:$H,"–"),"") -> 103 | H186: =IFERROR(_xlfn.XLOOKUP(A186,Aktiv!$A:$A,Aktiv!$I:$I,"–"),"") -> 120 | I186: =IFERROR(_xlfn.XLOOKUP(A186,Aktiv!$A:$A,Aktiv!$J:$J,"–"),"") -> 145 | J186: =IFERROR(IF(OR(F186=0,G186=0,F186="",G186=""),"-",(G186-F186)/F186),"–") -> 3.12 | K186: =IFERROR(IF(OR(F186=0,H186=0,F186="",H186=""),"-",(H186-F186)/F186),"–") -> 3.8 | L186: =IFERROR(IF(OR(F186=0,I186=0,F186="",I186=""),"-",(I186-F186)/F186),"–") -> 4.8 | M186: =IFERROR(IF(OR(G186=0,H186=0,G186="",H186=""),"-",(H186-G186)/G186),"–") -> 0.16504854 | N186: =IFERROR(IF(OR(G186=0,I186=0,G186="",I186=""),"-",(I186-G186)/G186),"–") -> 0.40776699 | O186: =IFERROR(IF(OR(H186=0,I186=0,H186="",I186=""),"-",(I186-H186)/H186),"–") -> 0.20833333 | P186: =IFERROR(ROUND(AVERAGEIF(F186:I186,"<>0"),0),"–") -> 98
A187: 3211 | B187: =IFERROR(_xlfn.XLOOKUP(A187,Aktiv!$A:$A,Aktiv!$C:$C,"–"),"") -> Seite außen SY32 | C187: =IFERROR(_xlfn.XLOOKUP(A187,Aktiv!$A:$A,Aktiv!$D:$D,"–"),"") -> Seite außen SY32 (180x980) | D187: =IFERROR(_xlfn.XLOOKUP(A187,Aktiv!$A:$A,Aktiv!$E:$E,"–"),"") -> 180 | E187: =IFERROR(_xlfn.XLOOKUP(A187,Aktiv!$A:$A,Aktiv!$F:$F,"–"),"") -> 980 | F187: =IFERROR(_xlfn.XLOOKUP(A187,Aktiv!$A:$A,Aktiv!$G:$G,"–"),"") -> 31 | G187: =IFERROR(_xlfn.XLOOKUP(A187,Aktiv!$A:$A,Aktiv!$H:$H,"–"),"") -> 106 | H187: =IFERROR(_xlfn.XLOOKUP(A187,Aktiv!$A:$A,Aktiv!$I:$I,"–"),"") -> 120 | I187: =IFERROR(_xlfn.XLOOKUP(A187,Aktiv!$A:$A,Aktiv!$J:$J,"–"),"") -> 145 | J187: =IFERROR(IF(OR(F187=0,G187=0,F187="",G187=""),"-",(G187-F187)/F187),"–") -> 2.4193548 | K187: =IFERROR(IF(OR(F187=0,H187=0,F187="",H187=""),"-",(H187-F187)/F187),"–") -> 2.8709677 | L187: =IFERROR(IF(OR(F187=0,I187=0,F187="",I187=""),"-",(I187-F187)/F187),"–") -> 3.6774194 | M187: =IFERROR(IF(OR(G187=0,H187=0,G187="",H187=""),"-",(H187-G187)/G187),"–") -> 0.13207547 | N187: =IFERROR(IF(OR(G187=0,I187=0,G187="",I187=""),"-",(I187-G187)/G187),"–") -> 0.36792453 | O187: =IFERROR(IF(OR(H187=0,I187=0,H187="",I187=""),"-",(I187-H187)/H187),"–") -> 0.20833333 | P187: =IFERROR(ROUND(AVERAGEIF(F187:I187,"<>0"),0),"–") -> 101
... A262: 5111 | B262: =IFERROR(_xlfn.XLOOKUP(A262,Aktiv!$A:$A,Aktiv!$C:$C,"–"),"") -> Tür | C262: =IFERROR(_xlfn.XLOOKUP(A262,Aktiv!$A:$A,Aktiv!$D:$D,"–"),"") -> Tür (780x360) | D262: =IFERROR(_xlfn.XLOOKUP(A262,Aktiv!$A:$A,Aktiv!$E:$E,"–"),"") -> 780 | E262: =IFERROR(_xlfn.XLOOKUP(A262,Aktiv!$A:$A,Aktiv!$F:$F,"–"),"") -> 360 | F262: =IFERROR(_xlfn.XLOOKUP(A262,Aktiv!$A:$A,Aktiv!$G:$G,"–"),"") -> - | G262: =IFERROR(_xlfn.XLOOKUP(A262,Aktiv!$A:$A,Aktiv!$H:$H,"–"),"") -> - | H262: =IFERROR(_xlfn.XLOOKUP(A262,Aktiv!$A:$A,Aktiv!$I:$I,"–"),"") -> - | I262: =IFERROR(_xlfn.XLOOKUP(A262,Aktiv!$A:$A,Aktiv!$J:$J,"–"),"") -> - | J262: =IFERROR(IF(OR(F262=0,G262=0,F262="",G262=""),"-",(G262-F262)/F262),"–") -> – | K262: =IFERROR(IF(OR(F262=0,H262=0,F262="",H262=""),"-",(H262-F262)/F262),"–") -> – | L262: =IFERROR(IF(OR(F262=0,I262=0,F262="",I262=""),"-",(I262-F262)/F262),"–") -> – | M262: =IFERROR(IF(OR(G262=0,H262=0,G262="",H262=""),"-",(H262-G262)/G262),"–") -> – | N262: =IFERROR(IF(OR(G262=0,I262=0,G262="",I262=""),"-",(I262-G262)/G262),"–") -> – | O262: =IFERROR(IF(OR(H262=0,I262=0,H262="",I262=""),"-",(I262-H262)/H262),"–") -> – | P262: =IFERROR(ROUND(AVERAGEIF(F262:I262,"<>0"),0),"–") -> –
A265: 📊 Zusammenfassung nach Kategorie (EUR)
A266: Kategorie | B266: Anzahl | C266: Ø PG1 | D266: Ø PG2 | E266: Ø PG3 | F266: Ø PG4 | G266: Ø PG2/PG1 | H266: Ø PG3/PG1 | I266: Ø PG4/PG1 | J266: Ø PG3/PG2 | K266: Ø PG4/PG2 | L266: Ø PG4/PG3 | P266: Ø Preis
A267: Boden | B267: =COUNTIF(B$5:B$262,"Boden") -> 16 | C267: =IFERROR(ROUND(AVERAGEIF(B$5:B$262,"Boden",F$5:F$262),0),"-") -> 68 | D267: =IFERROR(ROUND(AVERAGEIF(B$5:B$262,"Boden",G$5:G$262),0),"-") -> 235 | E267: =IFERROR(ROUND(AVERAGEIF(B$5:B$262,"Boden",H$5:H$262),0),"-") -> 247 | F267: =IFERROR(ROUND(AVERAGEIF(B$5:B$262,"Boden",I$5:I$262),0),"-") -> 277 | G267: =IFERROR(AVERAGEIF(B$5:B$262,"Boden",J$5:J$262),"-") -> 2.4928836 | H267: =IFERROR(AVERAGEIF(B$5:B$262,"Boden",K$5:K$262),"-") -> 2.7182721 | I267: =IFERROR(AVERAGEIF(B$5:B$262,"Boden",L$5:L$262),"-") -> 3.2161857 | J267: =IFERROR(AVERAGEIF(B$5:B$262,"Boden",M$5:M$262),"-") -> 0.062542992 | K267: =IFERROR(AVERAGEIF(B$5:B$262,"Boden",N$5:N$262),"-") -> 0.20312649 | L267: =IFERROR(AVERAGEIF(B$5:B$262,"Boden",O$5:O$262),"-") -> 0.13076944 | P267: =IFERROR(ROUND(AVERAGEIF(B$5:B$262,"Boden",P$5:P$262),0),"-") -> 207
A268: Doppeltür | B268: =COUNTIF(B$5:B$262,"Doppeltür") -> 11 | C268: =IFERROR(ROUND(AVERAGEIF(B$5:B$262,"Doppeltür",F$5:F$262),0),"-") -> 415 | D268: =IFERROR(ROUND(AVERAGEIF(B$5:B$262,"Doppeltür",G$5:G$262),0),"-") -> 587 | E268: =IFERROR(ROUND(AVERAGEIF(B$5:B$262,"Doppeltür",H$5:H$262),0),"-") -> 620 | F268: =IFERROR(ROUND(AVERAGEIF(B$5:B$262,"Doppeltür",I$5:I$262),0),"-") -> 1366 | G268: =IFERROR(AVERAGEIF(B$5:B$262,"Doppeltür",J$5:J$262),"-") -> 0.41584097 | H268: =IFERROR(AVERAGEIF(B$5:B$262,"Doppeltür",K$5:K$262),"-") -> 0.4939729 | I268: =IFERROR(AVERAGEIF(B$5:B$262,"Doppeltür",L$5:L$262),"-") -> 2.2940895 | J268: =IFERROR(AVERAGEIF(B$5:B$262,"Doppeltür",M$5:M$262),"-") -> 0.055184253 | K268: =IFERROR(AVERAGEIF(B$5:B$262,"Doppeltür",N$5:N$262),"-") -> 1.3265959 | L268: =IFERROR(AVERAGEIF(B$5:B$262,"Doppeltür",O$5:O$262),"-") -> 1.2049194 | P268: =IFERROR(ROUND(AVERAGEIF(B$5:B$262,"Doppeltür",P$5:P$262),0),"-") -> 747
A269: Fachboden groß | B269: =COUNTIF(B$5:B$262,"Fachboden groß") -> 13 | C269: =IFERROR(ROUND(AVERAGEIF(B$5:B$262,"Fachboden groß",F$5:F$262),0),"-") -> 52 | D269: =IFERROR(ROUND(AVERAGEIF(B$5:B$262,"Fachboden groß",G$5:G$262),0),"-") -> 181 | E269: =IFERROR(ROUND(AVERAGEIF(B$5:B$262,"Fachboden groß",H$5:H$262),0),"-") -> 191 | F269: =IFERROR(ROUND(AVERAGEIF(B$5:B$262,"Fachboden groß",I$5:I$262),0),"-") -> 214 | G269: =IFERROR(AVERAGEIF(B$5:B$262,"Fachboden groß",J$5:J$262),"-") -> 2.5331872 | H269: =IFERROR(AVERAGEIF(B$5:B$262,"Fachboden groß",K$5:K$262),"-") -> 2.7772826 | I269: =IFERROR(AVERAGEIF(B$5:B$262,"Fachboden groß",L$5:L$262),"-") -> 3.2912672 | J269: =IFERROR(AVERAGEIF(B$5:B$262,"Fachboden groß",M$5:M$262),"-") -> 0.066038753 | K269: =IFERROR(AVERAGEIF(B$5:B$262,"Fachboden groß",N$5:N$262),"-") -> 0.20843391 | L269: =IFERROR(AVERAGEIF(B$5:B$262,"Fachboden groß",O$5:O$262),"-") -> 0.13180087 | P269: =IFERROR(ROUND(AVERAGEIF(B$5:B$262,"Fachboden groß",P$5:P$262),0),"-") -> 159
A270: Fachboden klein | B270: =COUNTIF(B$5:B$262,"Fachboden klein") -> 13 | C270: =IFERROR(ROUND(AVERAGEIF(B$5:B$262,"Fachboden klein",F$5:F$262),0),"-") -> 52 | D270: =IFERROR(ROUND(AVERAGEIF(B$5:B$262,"Fachboden klein",G$5:G$262),0),"-") -> 181 | E270: =IFERROR(ROUND(AVERAGEIF(B$5:B$262,"Fachboden klein",H$5:H$262),0),"-") -> 191 | F270: =IFERROR(ROUND(AVERAGEIF(B$5:B$262,"Fachboden klein",I$5:I$262),0),"-") -> 214 | G270: =IFERROR(AVERAGEIF(B$5:B$262,"Fachboden klein",J$5:J$262),"-") -> 2.5331872 | H270: =IFERROR(AVERAGEIF(B$5:B$262,"Fachboden klein",K$5:K$262),"-") -> 2.7772826 | I270: =IFERROR(AVERAGEIF(B$5:B$262,"Fachboden klein",L$5:L$262),"-") -> 3.2912672 | J270: =IFERROR(AVERAGEIF(B$5:B$262,"Fachboden klein",M$5:M$262),"-") -> 0.066038753 | K270: =IFERROR(AVERAGEIF(B$5:B$262,"Fachboden klein",N$5:N$262),"-") -> 0.20843391 | L270: =IFERROR(AVERAGEIF(B$5:B$262,"Fachboden klein",O$5:O$262),"-") -> 0.13180087 | P270: =IFERROR(ROUND(AVERAGEIF(B$5:B$262,"Fachboden klein",P$5:P$262),0),"-") -> 159
A271: Klappe | B271: =COUNTIF(B$5:B$262,"Klappe") -> 11 | C271: =IFERROR(ROUND(AVERAGEIF(B$5:B$262,"Klappe",F$5:F$262),0),"-") -> 158 | D271: =IFERROR(ROUND(AVERAGEIF(B$5:B$262,"Klappe",G$5:G$262),0),"-") -> 261 | E271: =IFERROR(ROUND(AVERAGEIF(B$5:B$262,"Klappe",H$5:H$262),0),"-") -> 275 | F271: =IFERROR(ROUND(AVERAGEIF(B$5:B$262,"Klappe",I$5:I$262),0),"-") -> 371 | G271: =IFERROR(AVERAGEIF(B$5:B$262,"Klappe",J$5:J$262),"-") -> 0.65267512 | H271: =IFERROR(AVERAGEIF(B$5:B$262,"Klappe",K$5:K$262),"-") -> 0.73919998 | I271: =IFERROR(AVERAGEIF(B$5:B$262,"Klappe",L$5:L$262),"-") -> 1.3489273 | J271: =IFERROR(AVERAGEIF(B$5:B$262,"Klappe",M$5:M$262),"-") -> 0.052355035 | K271: =IFERROR(AVERAGEIF(B$5:B$262,"Klappe",N$5:N$262),"-") -> 0.42128741 | L271: =IFERROR(AVERAGEIF(B$5:B$262,"Klappe",O$5:O$262),"-") -> 0.35058013 | P271: =IFERROR(ROUND(AVERAGEIF(B$5:B$262,"Klappe",P$5:P$262),0),"-") -> 267
A272: Klappenboden | B272: =COUNTIF(B$5:B$262,"Klappenboden") -> 16 | C272: =IFERROR(ROUND(AVERAGEIF(B$5:B$262,"Klappenboden",F$5:F$262),0),"-") -> 52 | D272: =IFERROR(ROUND(AVERAGEIF(B$5:B$262,"Klappenboden",G$5:G$262),0),"-") -> 181 | E272: =IFERROR(ROUND(AVERAGEIF(B$5:B$262,"Klappenboden",H$5:H$262),0),"-") -> 191 | F272: =IFERROR(ROUND(AVERAGEIF(B$5:B$262,"Klappenboden",I$5:I$262),0),"-") -> 214 | G272: =IFERROR(AVERAGEIF(B$5:B$262,"Klappenboden",J$5:J$262),"-") -> 2.5331872 | H272: =IFERROR(AVERAGEIF(B$5:B$262,"Klappenboden",K$5:K$262),"-") -> 2.7772826 | I272: =IFERROR(AVERAGEIF(B$5:B$262,"Klappenboden",L$5:L$262),"-") -> 3.2912672 | J272: =IFERROR(AVERAGEIF(B$5:B$262,"Klappenboden",M$5:M$262),"-") -> 0.066038753 | K272: =IFERROR(AVERAGEIF(B$5:B$262,"Klappenboden",N$5:N$262),"-") -> 0.20843391 | L272: =IFERROR(AVERAGEIF(B$5:B$262,"Klappenboden",O$5:O$262),"-") -> 0.13180087 | P272: =IFERROR(ROUND(AVERAGEIF(B$5:B$262,"Klappenboden",P$5:P$262),0),"-") -> 159
A273: Rücken | B273: =COUNTIF(B$5:B$262,"Rücken") -> 30 | C273: =IFERROR(ROUND(AVERAGEIF(B$5:B$262,"Rücken",F$5:F$262),0),"-") -> 91 | D273: =IFERROR(ROUND(AVERAGEIF(B$5:B$262,"Rücken",G$5:G$262),0),"-") -> 315 | E273: =IFERROR(ROUND(AVERAGEIF(B$5:B$262,"Rücken",H$5:H$262),0),"-") -> 331 | F273: =IFERROR(ROUND(AVERAGEIF(B$5:B$262,"Rücken",I$5:I$262),0),"-") -> 371 | G273: =IFERROR(AVERAGEIF(B$5:B$262,"Rücken",J$5:J$262),"-") -> 2.5678504 | H273: =IFERROR(AVERAGEIF(B$5:B$262,"Rücken",K$5:K$262),"-") -> 2.8353327 | I273: =IFERROR(AVERAGEIF(B$5:B$262,"Rücken",L$5:L$262),"-") -> 3.3781757 | J273: =IFERROR(AVERAGEIF(B$5:B$262,"Rücken",M$5:M$262),"-") -> 0.071392877 | K273: =IFERROR(AVERAGEIF(B$5:B$262,"Rücken",N$5:N$262),"-") -> 0.21994676 | L273: =IFERROR(AVERAGEIF(B$5:B$262,"Rücken",O$5:O$262),"-") -> 0.13667349 | P273: =IFERROR(ROUND(AVERAGEIF(B$5:B$262,"Rücken",P$5:P$262),0),"-") -> 277
A274: Schublade | B274: =COUNTIF(B$5:B$262,"Schublade") -> 19 | C274: =IFERROR(ROUND(AVERAGEIF(B$5:B$262,"Schublade",F$5:F$262),0),"-") -> 323 | D274: =IFERROR(ROUND(AVERAGEIF(B$5:B$262,"Schublade",G$5:G$262),0),"-") -> 384 | E274: =IFERROR(ROUND(AVERAGEIF(B$5:B$262,"Schublade",H$5:H$262),0),"-") -> 418 | F274: =IFERROR(ROUND(AVERAGEIF(B$5:B$262,"Schublade",I$5:I$262),0),"-") -> - | G274: =IFERROR(AVERAGEIF(B$5:B$262,"Schublade",J$5:J$262),"-") -> 0.18798999 | H274: =IFERROR(AVERAGEIF(B$5:B$262,"Schublade",K$5:K$262),"-") -> 0.29276027 | I274: =IFERROR(AVERAGEIF(B$5:B$262,"Schublade",L$5:L$262),"-") -> - | J274: =IFERROR(AVERAGEIF(B$5:B$262,"Schublade",M$5:M$262),"-") -> 0.088191969 | K274: =IFERROR(AVERAGEIF(B$5:B$262,"Schublade",N$5:N$262),"-") -> - | L274: =IFERROR(AVERAGEIF(B$5:B$262,"Schublade",O$5:O$262),"-") -> - | P274: =IFERROR(ROUND(AVERAGEIF(B$5:B$262,"Schublade",P$5:P$262),0),"-") -> 375
A275: Schublade LB 1 | B275: =COUNTIF(B$5:B$262,"Schublade LB 1") -> 8 | C275: =IFERROR(ROUND(AVERAGEIF(B$5:B$262,"Schublade LB 1",F$5:F$262),0),"-") -> 324 | D275: =IFERROR(ROUND(AVERAGEIF(B$5:B$262,"Schublade LB 1",G$5:G$262),0),"-") -> 385 | E275: =IFERROR(ROUND(AVERAGEIF(B$5:B$262,"Schublade LB 1",H$5:H$262),0),"-") -> 419 | F275: =IFERROR(ROUND(AVERAGEIF(B$5:B$262,"Schublade LB 1",I$5:I$262),0),"-") -> - | G275: =IFERROR(AVERAGEIF(B$5:B$262,"Schublade LB 1",J$5:J$262),"-") -> 0.18790383 | H275: =IFERROR(AVERAGEIF(B$5:B$262,"Schublade LB 1",K$5:K$262),"-") -> 0.2927987 | I275: =IFERROR(AVERAGEIF(B$5:B$262,"Schublade LB 1",L$5:L$262),"-") -> - | J275: =IFERROR(AVERAGEIF(B$5:B$262,"Schublade LB 1",M$5:M$262),"-") -> 0.088303267 | K275: =IFERROR(AVERAGEIF(B$5:B$262,"Schublade LB 1",N$5:N$262),"-") -> - | L275: =IFERROR(AVERAGEIF(B$5:B$262,"Schublade LB 1",O$5:O$262),"-") -> - | P275: =IFERROR(ROUND(AVERAGEIF(B$5:B$262,"Schublade LB 1",P$5:P$262),0),"-") -> 376
A276: Schublade LB 2 | B276: =COUNTIF(B$5:B$262,"Schublade LB 2") -> 8 | C276: =IFERROR(ROUND(AVERAGEIF(B$5:B$262,"Schublade LB 2",F$5:F$262),0),"-") -> 324 | D276: =IFERROR(ROUND(AVERAGEIF(B$5:B$262,"Schublade LB 2",G$5:G$262),0),"-") -> 385 | E276: =IFERROR(ROUND(AVERAGEIF(B$5:B$262,"Schublade LB 2",H$5:H$262),0),"-") -> 419 | F276: =IFERROR(ROUND(AVERAGEIF(B$5:B$262,"Schublade LB 2",I$5:I$262),0),"-") -> - | G276: =IFERROR(AVERAGEIF(B$5:B$262,"Schublade LB 2",J$5:J$262),"-") -> 0.18790383 | H276: =IFERROR(AVERAGEIF(B$5:B$262,"Schublade LB 2",K$5:K$262),"-") -> 0.2927987 | I276: =IFERROR(AVERAGEIF(B$5:B$262,"Schublade LB 2",L$5:L$262),"-") -> - | J276: =IFERROR(AVERAGEIF(B$5:B$262,"Schublade LB 2",M$5:M$262),"-") -> 0.088303267 | K276: =IFERROR(AVERAGEIF(B$5:B$262,"Schublade LB 2",N$5:N$262),"-") -> - | L276: =IFERROR(AVERAGEIF(B$5:B$262,"Schublade LB 2",O$5:O$262),"-") -> - | P276: =IFERROR(ROUND(AVERAGEIF(B$5:B$262,"Schublade LB 2",P$5:P$262),0),"-") -> 376
A277: Seite außen | B277: =COUNTIF(B$5:B$262,"Seite außen") -> 26 | C277: =IFERROR(ROUND(AVERAGEIF(B$5:B$262,"Seite außen",F$5:F$262),0),"-") -> 107 | D277: =IFERROR(ROUND(AVERAGEIF(B$5:B$262,"Seite außen",G$5:G$262),0),"-") -> 369 | E277: =IFERROR(ROUND(AVERAGEIF(B$5:B$262,"Seite außen",H$5:H$262),0),"-") -> 386 | F277: =IFERROR(ROUND(AVERAGEIF(B$5:B$262,"Seite außen",I$5:I$262),0),"-") -> 306 | G277: =IFERROR(AVERAGEIF(B$5:B$262,"Seite außen",J$5:J$262),"-") -> 2.536189 | H277: =IFERROR(AVERAGEIF(B$5:B$262,"Seite außen",K$5:K$262),"-") -> 2.7737438 | I277: =IFERROR(AVERAGEIF(B$5:B$262,"Seite außen",L$5:L$262),"-") -> 3.4211267 | J277: =IFERROR(AVERAGEIF(B$5:B$262,"Seite außen",M$5:M$262),"-") -> 0.064161614 | K277: =IFERROR(AVERAGEIF(B$5:B$262,"Seite außen",N$5:N$262),"-") -> 0.22594238 | L277: =IFERROR(AVERAGEIF(B$5:B$262,"Seite außen",O$5:O$262),"-") -> 0.13917345 | P277: =IFERROR(ROUND(AVERAGEIF(B$5:B$262,"Seite außen",P$5:P$262),0),"-") -> 305
A278: Seite außen SY32 | B278: =COUNTIF(B$5:B$262,"Seite außen SY32") -> 22 | C278: =IFERROR(ROUND(AVERAGEIF(B$5:B$262,"Seite außen SY32",F$5:F$262),0),"-") -> 119 | D278: =IFERROR(ROUND(AVERAGEIF(B$5:B$262,"Seite außen SY32",G$5:G$262),0),"-") -> 411 | E278: =IFERROR(ROUND(AVERAGEIF(B$5:B$262,"Seite außen SY32",H$5:H$262),0),"-") -> 429 | F278: =IFERROR(ROUND(AVERAGEIF(B$5:B$262,"Seite außen SY32",I$5:I$262),0),"-") -> 479 | G278: =IFERROR(AVERAGEIF(B$5:B$262,"Seite außen SY32",J$5:J$262),"-") -> 2.4934307 | H278: =IFERROR(AVERAGEIF(B$5:B$262,"Seite außen SY32",K$5:K$262),"-") -> 2.6997022 | I278: =IFERROR(AVERAGEIF(B$5:B$262,"Seite außen SY32",L$5:L$262),"-") -> 3.1747452 | J278: =IFERROR(AVERAGEIF(B$5:B$262,"Seite außen SY32",M$5:M$262),"-") -> 0.057124453 | K278: =IFERROR(AVERAGEIF(B$5:B$262,"Seite außen SY32",N$5:N$262),"-") -> 0.19117456 | L278: =IFERROR(AVERAGEIF(B$5:B$262,"Seite außen SY32",O$5:O$262),"-") -> 0.1256111 | P278: =IFERROR(ROUND(AVERAGEIF(B$5:B$262,"Seite außen SY32",P$5:P$262),0),"-") -> 360
A279: Seite innen | B279: =COUNTIF(B$5:B$262,"Seite innen") -> 25 | C279: =IFERROR(ROUND(AVERAGEIF(B$5:B$262,"Seite innen",F$5:F$262),0),"-") -> 79 | D279: =IFERROR(ROUND(AVERAGEIF(B$5:B$262,"Seite innen",G$5:G$262),0),"-") -> 275 | E279: =IFERROR(ROUND(AVERAGEIF(B$5:B$262,"Seite innen",H$5:H$262),0),"-") -> 289 | F279: =IFERROR(ROUND(AVERAGEIF(B$5:B$262,"Seite innen",I$5:I$262),0),"-") -> 325 | G279: =IFERROR(AVERAGEIF(B$5:B$262,"Seite innen",J$5:J$262),"-") -> 2.6019067 | H279: =IFERROR(AVERAGEIF(B$5:B$262,"Seite innen",K$5:K$262),"-") -> 2.877696 | I279: =IFERROR(AVERAGEIF(B$5:B$262,"Seite innen",L$5:L$262),"-") -> 3.4304519 | J279: =IFERROR(AVERAGEIF(B$5:B$262,"Seite innen",M$5:M$262),"-") -> 0.072116599 | K279: =IFERROR(AVERAGEIF(B$5:B$262,"Seite innen",N$5:N$262),"-") -> 0.2210806 | L279: =IFERROR(AVERAGEIF(B$5:B$262,"Seite innen",O$5:O$262),"-") -> 0.13688093 | P279: =IFERROR(ROUND(AVERAGEIF(B$5:B$262,"Seite innen",P$5:P$262),0),"-") -> 242
A280: Seite innen SY32 | B280: =COUNTIF(B$5:B$262,"Seite innen SY32") -> 18 | C280: =IFERROR(ROUND(AVERAGEIF(B$5:B$262,"Seite innen SY32",F$5:F$262),0),"-") -> 90 | D280: =IFERROR(ROUND(AVERAGEIF(B$5:B$262,"Seite innen SY32",G$5:G$262),0),"-") -> 309 | E280: =IFERROR(ROUND(AVERAGEIF(B$5:B$262,"Seite innen SY32",H$5:H$262),0),"-") -> 323 | F280: =IFERROR(ROUND(AVERAGEIF(B$5:B$262,"Seite innen SY32",I$5:I$262),0),"-") -> 360 | G280: =IFERROR(AVERAGEIF(B$5:B$262,"Seite innen SY32",J$5:J$262),"-") -> 2.498288 | H280: =IFERROR(AVERAGEIF(B$5:B$262,"Seite innen SY32",K$5:K$262),"-") -> 2.6932352 | I280: =IFERROR(AVERAGEIF(B$5:B$262,"Seite innen SY32",L$5:L$262),"-") -> 3.1565422 | J280: =IFERROR(AVERAGEIF(B$5:B$262,"Seite innen SY32",M$5:M$262),"-") -> 0.05353021 | K280: =IFERROR(AVERAGEIF(B$5:B$262,"Seite innen SY32",N$5:N$262),"-") -> 0.18374332 | L280: =IFERROR(AVERAGEIF(B$5:B$262,"Seite innen SY32",O$5:O$262),"-") -> 0.12259045 | P280: =IFERROR(ROUND(AVERAGEIF(B$5:B$262,"Seite innen SY32",P$5:P$262),0),"-") -> 270
A281: Seite innen SY32 DB | B281: =COUNTIF(B$5:B$262,"Seite innen SY32 DB") -> 10 | C281: =IFERROR(ROUND(AVERAGEIF(B$5:B$262,"Seite innen SY32 DB",F$5:F$262),0),"-") -> 90 | D281: =IFERROR(ROUND(AVERAGEIF(B$5:B$262,"Seite innen SY32 DB",G$5:G$262),0),"-") -> 309 | E281: =IFERROR(ROUND(AVERAGEIF(B$5:B$262,"Seite innen SY32 DB",H$5:H$262),0),"-") -> 323 | F281: =IFERROR(ROUND(AVERAGEIF(B$5:B$262,"Seite innen SY32 DB",I$5:I$262),0),"-") -> 360 | G281: =IFERROR(AVERAGEIF(B$5:B$262,"Seite innen SY32 DB",J$5:J$262),"-") -> 2.498288 | H281: =IFERROR(AVERAGEIF(B$5:B$262,"Seite innen SY32 DB",K$5:K$262),"-") -> 2.6932352 | I281: =IFERROR(AVERAGEIF(B$5:B$262,"Seite innen SY32 DB",L$5:L$262),"-") -> 3.1565422 | J281: =IFERROR(AVERAGEIF(B$5:B$262,"Seite innen SY32 DB",M$5:M$262),"-") -> 0.05353021 | K281: =IFERROR(AVERAGEIF(B$5:B$262,"Seite innen SY32 DB",N$5:N$262),"-") -> 0.18374332 | L281: =IFERROR(AVERAGEIF(B$5:B$262,"Seite innen SY32 DB",O$5:O$262),"-") -> 0.12259045 | P281: =IFERROR(ROUND(AVERAGEIF(B$5:B$262,"Seite innen SY32 DB",P$5:P$262),0),"-") -> 270
A282: Tür | B282: =COUNTIF(B$5:B$262,"Tür") -> 12 | C282: =IFERROR(ROUND(AVERAGEIF(B$5:B$262,"Tür",F$5:F$262),0),"-") -> 232 | D282: =IFERROR(ROUND(AVERAGEIF(B$5:B$262,"Tür",G$5:G$262),0),"-") -> 498 | E282: =IFERROR(ROUND(AVERAGEIF(B$5:B$262,"Tür",H$5:H$262),0),"-") -> 544 | F282: =IFERROR(ROUND(AVERAGEIF(B$5:B$262,"Tür",I$5:I$262),0),"-") -> 790 | G282: =IFERROR(AVERAGEIF(B$5:B$262,"Tür",J$5:J$262),"-") -> 1.1462904 | H282: =IFERROR(AVERAGEIF(B$5:B$262,"Tür",K$5:K$262),"-") -> 1.3457773 | I282: =IFERROR(AVERAGEIF(B$5:B$262,"Tür",L$5:L$262),"-") -> 2.4047409 | J282: =IFERROR(AVERAGEIF(B$5:B$262,"Tür",M$5:M$262),"-") -> 0.092945604 | K282: =IFERROR(AVERAGEIF(B$5:B$262,"Tür",N$5:N$262),"-") -> 0.58633784 | L282: =IFERROR(AVERAGEIF(B$5:B$262,"Tür",O$5:O$262),"-") -> 0.45143396 | P282: =IFERROR(ROUND(AVERAGEIF(B$5:B$262,"Tür",P$5:P$262),0),"-") -> 516

Sheet Konfigurator_Export
A1: art_nr | B1: typ | C1: kategorie | D1: bezeichnung | E1: breite_mm | F1: tiefe_mm | G1: pg1_mdf_eur | H1: pg2_furnier_eur | I1: pg3_alu_eur | J1: pg4_glas_eur | K1: pg1_mdf_chf | L1: pg2_furnier_chf | M1: pg3_alu_chf | N1: pg4_glas_chf | O1: warnung
A2: 3000 | B2: Platte | C2: Boden | D2: Boden (360x360) | E2: 360 | F2: 360 | G2: =IFERROR(INDEX(Aktiv!$G$6:$G$326,MATCH(A2,Aktiv!$A$6:$A$326,0)),"") -> 25 | H2: =IFERROR(INDEX(Aktiv!$H$6:$H$326,MATCH(A2,Aktiv!$A$6:$A$326,0)),"") -> 103 | I2: =IFERROR(INDEX(Aktiv!$I$6:$I$326,MATCH(A2,Aktiv!$A$6:$A$326,0)),"") -> 120 | J2: =IFERROR(INDEX(Aktiv!$J$6:$J$326,MATCH(A2,Aktiv!$A$6:$A$326,0)),"") -> 145 | K2: =IFERROR(ROUND(G2*Steuerungsdaten!$B$5,0),"-") -> 29 | L2: =IFERROR(ROUND(H2*Steuerungsdaten!$B$5,0),"-") -> 118 | M2: =IFERROR(ROUND(I2*Steuerungsdaten!$B$5,0),"-") -> 138 | N2: =IFERROR(ROUND(J2*Steuerungsdaten!$B$5,0),"-") -> 167 | O2: =IF(ISNA(MATCH(A2,Aktiv!$A$6:$A$326,0)),"⚠ nicht im Modell","")
A3: 3001 | B3: Platte | C3: Boden | D3: Boden (420x360) | E3: 420 | F3: 360 | G3: =IFERROR(INDEX(Aktiv!$G$6:$G$326,MATCH(A3,Aktiv!$A$6:$A$326,0)),"") -> 27 | H3: =IFERROR(INDEX(Aktiv!$H$6:$H$326,MATCH(A3,Aktiv!$A$6:$A$326,0)),"") -> 103 | I3: =IFERROR(INDEX(Aktiv!$I$6:$I$326,MATCH(A3,Aktiv!$A$6:$A$326,0)),"") -> 120 | J3: =IFERROR(INDEX(Aktiv!$J$6:$J$326,MATCH(A3,Aktiv!$A$6:$A$326,0)),"") -> 145 | K3: =IFERROR(ROUND(G3*Steuerungsdaten!$B$5,0),"-") -> 31 | L3: =IFERROR(ROUND(H3*Steuerungsdaten!$B$5,0),"-") -> 118 | M3: =IFERROR(ROUND(I3*Steuerungsdaten!$B$5,0),"-") -> 138 | N3: =IFERROR(ROUND(J3*Steuerungsdaten!$B$5,0),"-") -> 167 | O3: =IF(ISNA(MATCH(A3,Aktiv!$A$6:$A$326,0)),"⚠ nicht im Modell","")
A4: 3002 | B4: Platte | C4: Boden | D4: Boden (580x360) | E4: 580 | F4: 360 | G4: =IFERROR(INDEX(Aktiv!$G$6:$G$326,MATCH(A4,Aktiv!$A$6:$A$326,0)),"") -> 37 | H4: =IFERROR(INDEX(Aktiv!$H$6:$H$326,MATCH(A4,Aktiv!$A$6:$A$326,0)),"") -> 126 | I4: =IFERROR(INDEX(Aktiv!$I$6:$I$326,MATCH(A4,Aktiv!$A$6:$A$326,0)),"") -> 131 | J4: =IFERROR(INDEX(Aktiv!$J$6:$J$326,MATCH(A4,Aktiv!$A$6:$A$326,0)),"") -> 146 | K4: =IFERROR(ROUND(G4*Steuerungsdaten!$B$5,0),"-") -> 43 | L4: =IFERROR(ROUND(H4*Steuerungsdaten!$B$5,0),"-") -> 145 | M4: =IFERROR(ROUND(I4*Steuerungsdaten!$B$5,0),"-") -> 151 | N4: =IFERROR(ROUND(J4*Steuerungsdaten!$B$5,0),"-") -> 168 | O4: =IF(ISNA(MATCH(A4,Aktiv!$A$6:$A$326,0)),"⚠ nicht im Modell","")
A5: 3003 | B5: Platte | C5: Boden | D5: Boden (780x360) | E5: 780 | F5: 360 | G5: =IFERROR(INDEX(Aktiv!$G$6:$G$326,MATCH(A5,Aktiv!$A$6:$A$326,0)),"") -> 49 | H5: =IFERROR(INDEX(Aktiv!$H$6:$H$326,MATCH(A5,Aktiv!$A$6:$A$326,0)),"") -> 169 | I5: =IFERROR(INDEX(Aktiv!$I$6:$I$326,MATCH(A5,Aktiv!$A$6:$A$326,0)),"") -> 177 | J5: =IFERROR(INDEX(Aktiv!$J$6:$J$326,MATCH(A5,Aktiv!$A$6:$A$326,0)),"") -> 196 | K5: =IFERROR(ROUND(G5*Steuerungsdaten!$B$5,0),"-") -> 56 | L5: =IFERROR(ROUND(H5*Steuerungsdaten!$B$5,0),"-") -> 194 | M5: =IFERROR(ROUND(I5*Steuerungsdaten!$B$5,0),"-") -> 204 | N5: =IFERROR(ROUND(J5*Steuerungsdaten!$B$5,0),"-") -> 225 | O5: =IF(ISNA(MATCH(A5,Aktiv!$A$6:$A$326,0)),"⚠ nicht im Modell","")
A6: 3004 | B6: Platte | C6: Boden | D6: Boden (980x360) | E6: 980 | F6: 360 | G6: =IFERROR(INDEX(Aktiv!$G$6:$G$326,MATCH(A6,Aktiv!$A$6:$A$326,0)),"") -> 62 | H6: =IFERROR(INDEX(Aktiv!$H$6:$H$326,MATCH(A6,Aktiv!$A$6:$A$326,0)),"") -> 213 | I6: =IFERROR(INDEX(Aktiv!$I$6:$I$326,MATCH(A6,Aktiv!$A$6:$A$326,0)),"") -> 222 | J6: =IFERROR(INDEX(Aktiv!$J$6:$J$326,MATCH(A6,Aktiv!$A$6:$A$326,0)),"") -> 247 | K6: =IFERROR(ROUND(G6*Steuerungsdaten!$B$5,0),"-") -> 71 | L6: =IFERROR(ROUND(H6*Steuerungsdaten!$B$5,0),"-") -> 245 | M6: =IFERROR(ROUND(I6*Steuerungsdaten!$B$5,0),"-") -> 255 | N6: =IFERROR(ROUND(J6*Steuerungsdaten!$B$5,0),"-") -> 284 | O6: =IF(ISNA(MATCH(A6,Aktiv!$A$6:$A$326,0)),"⚠ nicht im Modell","")
A7: 3005 | B7: Platte | C7: Boden | D7: Boden (360x580) | E7: 360 | F7: 580 | G7: =IFERROR(INDEX(Aktiv!$G$6:$G$326,MATCH(A7,Aktiv!$A$6:$A$326,0)),"") -> 37 | H7: =IFERROR(INDEX(Aktiv!$H$6:$H$326,MATCH(A7,Aktiv!$A$6:$A$326,0)),"") -> 126 | I7: =IFERROR(INDEX(Aktiv!$I$6:$I$326,MATCH(A7,Aktiv!$A$6:$A$326,0)),"") -> 131 | J7: =IFERROR(INDEX(Aktiv!$J$6:$J$326,MATCH(A7,Aktiv!$A$6:$A$326,0)),"") -> 146 | K7: =IFERROR(ROUND(G7*Steuerungsdaten!$B$5,0),"-") -> 43 | L7: =IFERROR(ROUND(H7*Steuerungsdaten!$B$5,0),"-") -> 145 | M7: =IFERROR(ROUND(I7*Steuerungsdaten!$B$5,0),"-") -> 151 | N7: =IFERROR(ROUND(J7*Steuerungsdaten!$B$5,0),"-") -> 168 | O7: =IF(ISNA(MATCH(A7,Aktiv!$A$6:$A$326,0)),"⚠ nicht im Modell","")
A8: 3006 | B8: Platte | C8: Boden | D8: Boden (420x580) | E8: 420 | F8: 580 | G8: =IFERROR(INDEX(Aktiv!$G$6:$G$326,MATCH(A8,Aktiv!$A$6:$A$326,0)),"") -> 43 | H8: =IFERROR(INDEX(Aktiv!$H$6:$H$326,MATCH(A8,Aktiv!$A$6:$A$326,0)),"") -> 147 | I8: =IFERROR(INDEX(Aktiv!$I$6:$I$326,MATCH(A8,Aktiv!$A$6:$A$326,0)),"") -> 153 | J8: =IFERROR(INDEX(Aktiv!$J$6:$J$326,MATCH(A8,Aktiv!$A$6:$A$326,0)),"") -> 170 | K8: =IFERROR(ROUND(G8*Steuerungsdaten!$B$5,0),"-") -> 49 | L8: =IFERROR(ROUND(H8*Steuerungsdaten!$B$5,0),"-") -> 169 | M8: =IFERROR(ROUND(I8*Steuerungsdaten!$B$5,0),"-") -> 176 | N8: =IFERROR(ROUND(J8*Steuerungsdaten!$B$5,0),"-") -> 196 | O8: =IF(ISNA(MATCH(A8,Aktiv!$A$6:$A$326,0)),"⚠ nicht im Modell","")
A9: 3007 | B9: Platte | C9: Boden | D9: Boden (580x580) | E9: 580 | F9: 580 | G9: =IFERROR(INDEX(Aktiv!$G$6:$G$326,MATCH(A9,Aktiv!$A$6:$A$326,0)),"") -> 59 | H9: =IFERROR(INDEX(Aktiv!$H$6:$H$326,MATCH(A9,Aktiv!$A$6:$A$326,0)),"") -> 203 | I9: =IFERROR(INDEX(Aktiv!$I$6:$I$326,MATCH(A9,Aktiv!$A$6:$A$326,0)),"") -> 211 | J9: =IFERROR(INDEX(Aktiv!$J$6:$J$326,MATCH(A9,Aktiv!$A$6:$A$326,0)),"") -> 235 | K9: =IFERROR(ROUND(G9*Steuerungsdaten!$B$5,0),"-") -> 68 | L9: =IFERROR(ROUND(H9*Steuerungsdaten!$B$5,0),"-") -> 233 | M9: =IFERROR(ROUND(I9*Steuerungsdaten!$B$5,0),"-") -> 243 | N9: =IFERROR(ROUND(J9*Steuerungsdaten!$B$5,0),"-") -> 270 | O9: =IF(ISNA(MATCH(A9,Aktiv!$A$6:$A$326,0)),"⚠ nicht im Modell","")
A10: 3008 | B10: Platte | C10: Boden | D10: Boden (780x580) | E10: 780 | F10: 580 | G10: =IFERROR(INDEX(Aktiv!$G$6:$G$326,MATCH(A10,Aktiv!$A$6:$A$326,0)),"") -> 80 | H10: =IFERROR(INDEX(Aktiv!$H$6:$H$326,MATCH(A10,Aktiv!$A$6:$A$326,0)),"") -> 273 | I10: =IFERROR(INDEX(Aktiv!$I$6:$I$326,MATCH(A10,Aktiv!$A$6:$A$326,0)),"") -> 284 | J10: =IFERROR(INDEX(Aktiv!$J$6:$J$326,MATCH(A10,Aktiv!$A$6:$A$326,0)),"") -> 316 | K10: =IFERROR(ROUND(G10*Steuerungsdaten!$B$5,0),"-") -> 92 | L10: =IFERROR(ROUND(H10*Steuerungsdaten!$B$5,0),"-") -> 314 | M10: =IFERROR(ROUND(I10*Steuerungsdaten!$B$5,0),"-") -> 327 | N10: =IFERROR(ROUND(J10*Steuerungsdaten!$B$5,0),"-") -> 363 | O10: =IF(ISNA(MATCH(A10,Aktiv!$A$6:$A$326,0)),"⚠ nicht im Modell","")
A11: 3009 | B11: Platte | C11: Boden | D11: Boden (980x580) | E11: 980 | F11: 580 | G11: =IFERROR(INDEX(Aktiv!$G$6:$G$326,MATCH(A11,Aktiv!$A$6:$A$326,0)),"") -> 100 | H11: =IFERROR(INDEX(Aktiv!$H$6:$H$326,MATCH(A11,Aktiv!$A$6:$A$326,0)),"") -> 343 | I11: =IFERROR(INDEX(Aktiv!$I$6:$I$326,MATCH(A11,Aktiv!$A$6:$A$326,0)),"") -> 357 | J11: =IFERROR(INDEX(Aktiv!$J$6:$J$326,MATCH(A11,Aktiv!$A$6:$A$326,0)),"") -> 398 | K11: =IFERROR(ROUND(G11*Steuerungsdaten!$B$5,0),"-") -> 115 | L11: =IFERROR(ROUND(H11*Steuerungsdaten!$B$5,0),"-") -> 394 | M11: =IFERROR(ROUND(I11*Steuerungsdaten!$B$5,0),"-") -> 411 | N11: =IFERROR(ROUND(J11*Steuerungsdaten!$B$5,0),"-") -> 458 | O11: =IF(ISNA(MATCH(A11,Aktiv!$A$6:$A$326,0)),"⚠ nicht im Modell","")
A12: 3010 | B12: Platte | C12: Boden | D12: Boden (780x780) | E12: 780 | F12: 780 | G12: =IFERROR(INDEX(Aktiv!$G$6:$G$326,MATCH(A12,Aktiv!$A$6:$A$326,0)),"") -> 107 | H12: =IFERROR(INDEX(Aktiv!$H$6:$H$326,MATCH(A12,Aktiv!$A$6:$A$326,0)),"") -> 367 | I12: =IFERROR(INDEX(Aktiv!$I$6:$I$326,MATCH(A12,Aktiv!$A$6:$A$326,0)),"") -> 382 | J12: =IFERROR(INDEX(Aktiv!$J$6:$J$326,MATCH(A12,Aktiv!$A$6:$A$326,0)),"") -> 426 | K12: =IFERROR(ROUND(G12*Steuerungsdaten!$B$5,0),"-") -> 123 | L12: =IFERROR(ROUND(H12*Steuerungsdaten!$B$5,0),"-") -> 422 | M12: =IFERROR(ROUND(I12*Steuerungsdaten!$B$5,0),"-") -> 439 | N12: =IFERROR(ROUND(J12*Steuerungsdaten!$B$5,0),"-") -> 490 | O12: =IF(ISNA(MATCH(A12,Aktiv!$A$6:$A$326,0)),"⚠ nicht im Modell","")
A13: 3011 | B13: Platte | C13: Boden | D13: Boden (980x780) | E13: 980 | F13: 780 | G13: =IFERROR(INDEX(Aktiv!$G$6:$G$326,MATCH(A13,Aktiv!$A$6:$A$326,0)),"") -> 135 | H13: =IFERROR(INDEX(Aktiv!$H$6:$H$326,MATCH(A13,Aktiv!$A$6:$A$326,0)),"") -> 461 | I13: =IFERROR(INDEX(Aktiv!$I$6:$I$326,MATCH(A13,Aktiv!$A$6:$A$326,0)),"") -> 480 | J13: =IFERROR(INDEX(Aktiv!$J$6:$J$326,MATCH(A13,Aktiv!$A$6:$A$326,0)),"") -> 535 | K13: =IFERROR(ROUND(G13*Steuerungsdaten!$B$5,0),"-") -> 155 | L13: =IFERROR(ROUND(H13*Steuerungsdaten!$B$5,0),"-") -> 530 | M13: =IFERROR(ROUND(I13*Steuerungsdaten!$B$5,0),"-") -> 552 | N13: =IFERROR(ROUND(J13*Steuerungsdaten!$B$5,0),"-") -> 615 | O13: =IF(ISNA(MATCH(A13,Aktiv!$A$6:$A$326,0)),"⚠ nicht im Modell","")
... A16: 3014 | B16: Platte | C16: Boden | D16: Boden (420x980) | E16: 420 | F16: 980 | G16: =IFERROR(INDEX(Aktiv!$G$6:$G$326,MATCH(A16,Aktiv!$A$6:$A$326,0)),"") -> 72 | H16: =IFERROR(INDEX(Aktiv!$H$6:$H$326,MATCH(A16,Aktiv!$A$6:$A$326,0)),"") -> 248 | I16: =IFERROR(INDEX(Aktiv!$I$6:$I$326,MATCH(A16,Aktiv!$A$6:$A$326,0)),"") -> 259 | J16: =IFERROR(INDEX(Aktiv!$J$6:$J$326,MATCH(A16,Aktiv!$A$6:$A$326,0)),"") -> 288 | K16: =IFERROR(ROUND(G16*Steuerungsdaten!$B$5,0),"-") -> 83 | L16: =IFERROR(ROUND(H16*Steuerungsdaten!$B$5,0),"-") -> 285 | M16: =IFERROR(ROUND(I16*Steuerungsdaten!$B$5,0),"-") -> 298 | N16: =IFERROR(ROUND(J16*Steuerungsdaten!$B$5,0),"-") -> 331 | O16: =IF(ISNA(MATCH(A16,Aktiv!$A$6:$A$326,0)),"⚠ nicht im Modell","")
A17: S_0003 | B17: Platte | C17: Boden | D17: Boden (420x420) | E17: 420 | F17: 420 | G17: =IFERROR(INDEX(Aktiv!$G$6:$G$326,MATCH(A17,Aktiv!$A$6:$A$326,0)),"") -> 31 | H17: =IFERROR(INDEX(Aktiv!$H$6:$H$326,MATCH(A17,Aktiv!$A$6:$A$326,0)),"") -> 106 | I17: =IFERROR(INDEX(Aktiv!$I$6:$I$326,MATCH(A17,Aktiv!$A$6:$A$326,0)),"") -> 120 | J17: =IFERROR(INDEX(Aktiv!$J$6:$J$326,MATCH(A17,Aktiv!$A$6:$A$326,0)),"") -> 145 | K17: =IFERROR(ROUND(G17*Steuerungsdaten!$B$5,0),"-") -> 36 | L17: =IFERROR(ROUND(H17*Steuerungsdaten!$B$5,0),"-") -> 122 | M17: =IFERROR(ROUND(I17*Steuerungsdaten!$B$5,0),"-") -> 138 | N17: =IFERROR(ROUND(J17*Steuerungsdaten!$B$5,0),"-") -> 167 | O17: =IF(ISNA(MATCH(A17,Aktiv!$A$6:$A$326,0)),"⚠ nicht im Modell","")
A18: 3100 | B18: Platte | C18: Seite außen | D18: Seite außen (360x180) | E18: 360 | F18: 180 | G18: =IFERROR(INDEX(Aktiv!$G$6:$G$326,MATCH(A18,Aktiv!$A$6:$A$326,0)),"") -> 25 | H18: =IFERROR(INDEX(Aktiv!$H$6:$H$326,MATCH(A18,Aktiv!$A$6:$A$326,0)),"") -> 103 | I18: =IFERROR(INDEX(Aktiv!$I$6:$I$326,MATCH(A18,Aktiv!$A$6:$A$326,0)),"") -> 120 | J18: =IFERROR(INDEX(Aktiv!$J$6:$J$326,MATCH(A18,Aktiv!$A$6:$A$326,0)),"") -> 145 | K18: =IFERROR(ROUND(G18*Steuerungsdaten!$B$5,0),"-") -> 29 | L18: =IFERROR(ROUND(H18*Steuerungsdaten!$B$5,0),"-") -> 118 | M18: =IFERROR(ROUND(I18*Steuerungsdaten!$B$5,0),"-") -> 138 | N18: =IFERROR(ROUND(J18*Steuerungsdaten!$B$5,0),"-") -> 167 | O18: =IF(ISNA(MATCH(A18,Aktiv!$A$6:$A$326,0)),"⚠ nicht im Modell","")
A19: 3101 | B19: Platte | C19: Seite außen | D19: Seite außen (360x360) | E19: 360 | F19: 360 | G19: =IFERROR(INDEX(Aktiv!$G$6:$G$326,MATCH(A19,Aktiv!$A$6:$A$326,0)),"") -> 25 | H19: =IFERROR(INDEX(Aktiv!$H$6:$H$326,MATCH(A19,Aktiv!$A$6:$A$326,0)),"") -> 103 | I19: =IFERROR(INDEX(Aktiv!$I$6:$I$326,MATCH(A19,Aktiv!$A$6:$A$326,0)),"") -> 120 | J19: =IFERROR(INDEX(Aktiv!$J$6:$J$326,MATCH(A19,Aktiv!$A$6:$A$326,0)),"") -> 145 | K19: =IFERROR(ROUND(G19*Steuerungsdaten!$B$5,0),"-") -> 29 | L19: =IFERROR(ROUND(H19*Steuerungsdaten!$B$5,0),"-") -> 118 | M19: =IFERROR(ROUND(I19*Steuerungsdaten!$B$5,0),"-") -> 138 | N19: =IFERROR(ROUND(J19*Steuerungsdaten!$B$5,0),"-") -> 167 | O19: =IF(ISNA(MATCH(A19,Aktiv!$A$6:$A$326,0)),"⚠ nicht im Modell","")
A20: 3102 | B20: Platte | C20: Seite außen | D20: Seite außen (360x720) | E20: 360 | F20: 720 | G20: =IFERROR(INDEX(Aktiv!$G$6:$G$326,MATCH(A20,Aktiv!$A$6:$A$326,0)),"") -> 46 | H20: =IFERROR(INDEX(Aktiv!$H$6:$H$326,MATCH(A20,Aktiv!$A$6:$A$326,0)),"") -> 156 | I20: =IFERROR(INDEX(Aktiv!$I$6:$I$326,MATCH(A20,Aktiv!$A$6:$A$326,0)),"") -> 163 | J20: =IFERROR(INDEX(Aktiv!$J$6:$J$326,MATCH(A20,Aktiv!$A$6:$A$326,0)),"") -> 181 | K20: =IFERROR(ROUND(G20*Steuerungsdaten!$B$5,0),"-") -> 53 | L20: =IFERROR(ROUND(H20*Steuerungsdaten!$B$5,0),"-") -> 179 | M20: =IFERROR(ROUND(I20*Steuerungsdaten!$B$5,0),"-") -> 187 | N20: =IFERROR(ROUND(J20*Steuerungsdaten!$B$5,0),"-") -> 208 | O20: =IF(ISNA(MATCH(A20,Aktiv!$A$6:$A$326,0)),"⚠ nicht im Modell","")
A21: 3103 | B21: Platte | C21: Seite außen | D21: Seite außen (360x1080) | E21: 360 | F21: 1080 | G21: =IFERROR(INDEX(Aktiv!$G$6:$G$326,MATCH(A21,Aktiv!$A$6:$A$326,0)),"") -> 68 | H21: =IFERROR(INDEX(Aktiv!$H$6:$H$326,MATCH(A21,Aktiv!$A$6:$A$326,0)),"") -> 235 | I21: =IFERROR(INDEX(Aktiv!$I$6:$I$326,MATCH(A21,Aktiv!$A$6:$A$326,0)),"") -> 244 | J21: =IFERROR(INDEX(Aktiv!$J$6:$J$326,MATCH(A21,Aktiv!$A$6:$A$326,0)),"") -> 272 | K21: =IFERROR(ROUND(G21*Steuerungsdaten!$B$5,0),"-") -> 78 | L21: =IFERROR(ROUND(H21*Steuerungsdaten!$B$5,0),"-") -> 270 | M21: =IFERROR(ROUND(I21*Steuerungsdaten!$B$5,0),"-") -> 281 | N21: =IFERROR(ROUND(J21*Steuerungsdaten!$B$5,0),"-") -> 313 | O21: =IF(ISNA(MATCH(A21,Aktiv!$A$6:$A$326,0)),"⚠ nicht im Modell","")
A22: 3104 | B22: Platte | C22: Seite außen | D22: Seite außen (360x1440) | E22: 360 | F22: 1440 | G22: =IFERROR(INDEX(Aktiv!$G$6:$G$326,MATCH(A22,Aktiv!$A$6:$A$326,0)),"") -> 91 | H22: =IFERROR(INDEX(Aktiv!$H$6:$H$326,MATCH(A22,Aktiv!$A$6:$A$326,0)),"") -> 313 | I22: =IFERROR(INDEX(Aktiv!$I$6:$I$326,MATCH(A22,Aktiv!$A$6:$A$326,0)),"") -> 326 | J22: =IFERROR(INDEX(Aktiv!$J$6:$J$326,MATCH(A22,Aktiv!$A$6:$A$326,0)),"") -> 363 | K22: =IFERROR(ROUND(G22*Steuerungsdaten!$B$5,0),"-") -> 105 | L22: =IFERROR(ROUND(H22*Steuerungsdaten!$B$5,0),"-") -> 360 | M22: =IFERROR(ROUND(I22*Steuerungsdaten!$B$5,0),"-") -> 375 | N22: =IFERROR(ROUND(J22*Steuerungsdaten!$B$5,0),"-") -> 417 | O22: =IF(ISNA(MATCH(A22,Aktiv!$A$6:$A$326,0)),"⚠ nicht im Modell","")
A23: 3105 | B23: Platte | C23: Seite außen | D23: Seite außen (360x1800) | E23: 360 | F23: 1800 | G23: =IFERROR(INDEX(Aktiv!$G$6:$G$326,MATCH(A23,Aktiv!$A$6:$A$326,0)),"") -> 114 | H23: =IFERROR(INDEX(Aktiv!$H$6:$H$326,MATCH(A23,Aktiv!$A$6:$A$326,0)),"") -> 391 | I23: =IFERROR(INDEX(Aktiv!$I$6:$I$326,MATCH(A23,Aktiv!$A$6:$A$326,0)),"") -> 407 | J23: =IFERROR(INDEX(Aktiv!$J$6:$J$326,MATCH(A23,Aktiv!$A$6:$A$326,0)),"") -> 453 | K23: =IFERROR(ROUND(G23*Steuerungsdaten!$B$5,0),"-") -> 131 | L23: =IFERROR(ROUND(H23*Steuerungsdaten!$B$5,0),"-") -> 450 | M23: =IFERROR(ROUND(I23*Steuerungsdaten!$B$5,0),"-") -> 468 | N23: =IFERROR(ROUND(J23*Steuerungsdaten!$B$5,0),"-") -> 521 | O23: =IF(ISNA(MATCH(A23,Aktiv!$A$6:$A$326,0)),"⚠ nicht im Modell","")
A24: 3106 | B24: Platte | C24: Seite außen | D24: Seite außen (580x180) | E24: 580 | F24: 180 | G24: =IFERROR(INDEX(Aktiv!$G$6:$G$326,MATCH(A24,Aktiv!$A$6:$A$326,0)),"") -> 25 | H24: =IFERROR(INDEX(Aktiv!$H$6:$H$326,MATCH(A24,Aktiv!$A$6:$A$326,0)),"") -> 103 | I24: =IFERROR(INDEX(Aktiv!$I$6:$I$326,MATCH(A24,Aktiv!$A$6:$A$326,0)),"") -> 120 | J24: =IFERROR(INDEX(Aktiv!$J$6:$J$326,MATCH(A24,Aktiv!$A$6:$A$326,0)),"") -> 145 | K24: =IFERROR(ROUND(G24*Steuerungsdaten!$B$5,0),"-") -> 29 | L24: =IFERROR(ROUND(H24*Steuerungsdaten!$B$5,0),"-") -> 118 | M24: =IFERROR(ROUND(I24*Steuerungsdaten!$B$5,0),"-") -> 138 | N24: =IFERROR(ROUND(J24*Steuerungsdaten!$B$5,0),"-") -> 167 | O24: =IF(ISNA(MATCH(A24,Aktiv!$A$6:$A$326,0)),"⚠ nicht im Modell","")
A25: 3107 | B25: Platte | C25: Seite außen | D25: Seite außen (580x360) | E25: 580 | F25: 360 | G25: =IFERROR(INDEX(Aktiv!$G$6:$G$326,MATCH(A25,Aktiv!$A$6:$A$326,0)),"") -> 37 | H25: =IFERROR(INDEX(Aktiv!$H$6:$H$326,MATCH(A25,Aktiv!$A$6:$A$326,0)),"") -> 126 | I25: =IFERROR(INDEX(Aktiv!$I$6:$I$326,MATCH(A25,Aktiv!$A$6:$A$326,0)),"") -> 131 | J25: =IFERROR(INDEX(Aktiv!$J$6:$J$326,MATCH(A25,Aktiv!$A$6:$A$326,0)),"") -> 146 | K25: =IFERROR(ROUND(G25*Steuerungsdaten!$B$5,0),"-") -> 43 | L25: =IFERROR(ROUND(H25*Steuerungsdaten!$B$5,0),"-") -> 145 | M25: =IFERROR(ROUND(I25*Steuerungsdaten!$B$5,0),"-") -> 151 | N25: =IFERROR(ROUND(J25*Steuerungsdaten!$B$5,0),"-") -> 168 | O25: =IF(ISNA(MATCH(A25,Aktiv!$A$6:$A$326,0)),"⚠ nicht im Modell","")
A26: 3108 | B26: Platte | C26: Seite außen | D26: Seite außen (580x720) | E26: 580 | F26: 720 | G26: =IFERROR(INDEX(Aktiv!$G$6:$G$326,MATCH(A26,Aktiv!$A$6:$A$326,0)),"") -> 73 | H26: =IFERROR(INDEX(Aktiv!$H$6:$H$326,MATCH(A26,Aktiv!$A$6:$A$326,0)),"") -> 252 | I26: =IFERROR(INDEX(Aktiv!$I$6:$I$326,MATCH(A26,Aktiv!$A$6:$A$326,0)),"") -> 262 | J26: =IFERROR(INDEX(Aktiv!$J$6:$J$326,MATCH(A26,Aktiv!$A$6:$A$326,0)),"") -> 292 | K26: =IFERROR(ROUND(G26*Steuerungsdaten!$B$5,0),"-") -> 84 | L26: =IFERROR(ROUND(H26*Steuerungsdaten!$B$5,0),"-") -> 290 | M26: =IFERROR(ROUND(I26*Steuerungsdaten!$B$5,0),"-") -> 301 | N26: =IFERROR(ROUND(J26*Steuerungsdaten!$B$5,0),"-") -> 336 | O26: =IF(ISNA(MATCH(A26,Aktiv!$A$6:$A$326,0)),"⚠ nicht im Modell","")
A27: 3109 | B27: Platte | C27: Seite außen | D27: Seite außen (580x1080) | E27: 580 | F27: 1080 | G27: =IFERROR(INDEX(Aktiv!$G$6:$G$326,MATCH(A27,Aktiv!$A$6:$A$326,0)),"") -> 110 | H27: =IFERROR(INDEX(Aktiv!$H$6:$H$326,MATCH(A27,Aktiv!$A$6:$A$326,0)),"") -> 378 | I27: =IFERROR(INDEX(Aktiv!$I$6:$I$326,MATCH(A27,Aktiv!$A$6:$A$326,0)),"") -> 394 | J27: =IFERROR(INDEX(Aktiv!$J$6:$J$326,MATCH(A27,Aktiv!$A$6:$A$326,0)),"") -> 438 | K27: =IFERROR(ROUND(G27*Steuerungsdaten!$B$5,0),"-") -> 127 | L27: =IFERROR(ROUND(H27*Steuerungsdaten!$B$5,0),"-") -> 435 | M27: =IFERROR(ROUND(I27*Steuerungsdaten!$B$5,0),"-") -> 453 | N27: =IFERROR(ROUND(J27*Steuerungsdaten!$B$5,0),"-") -> 504 | O27: =IF(ISNA(MATCH(A27,Aktiv!$A$6:$A$326,0)),"⚠ nicht im Modell","")
A28: 3110 | B28: Platte | C28: Seite außen | D28: Seite außen (580x1440) | E28: 580 | F28: 1440 | G28: =IFERROR(INDEX(Aktiv!$G$6:$G$326,MATCH(A28,Aktiv!$A$6:$A$326,0)),"") -> 147 | H28: =IFERROR(INDEX(Aktiv!$H$6:$H$326,MATCH(A28,Aktiv!$A$6:$A$326,0)),"") -> 504 | I28: =IFERROR(INDEX(Aktiv!$I$6:$I$326,MATCH(A28,Aktiv!$A$6:$A$326,0)),"") -> 525 | J28: =IFERROR(INDEX(Aktiv!$J$6:$J$326,MATCH(A28,Aktiv!$A$6:$A$326,0)),"") -> 584 | K28: =IFERROR(ROUND(G28*Steuerungsdaten!$B$5,0),"-") -> 169 | L28: =IFERROR(ROUND(H28*Steuerungsdaten!$B$5,0),"-") -> 580 | M28: =IFERROR(ROUND(I28*Steuerungsdaten!$B$5,0),"-") -> 604 | N28: =IFERROR(ROUND(J28*Steuerungsdaten!$B$5,0),"-") -> 672 | O28: =IF(ISNA(MATCH(A28,Aktiv!$A$6:$A$326,0)),"⚠ nicht im Modell","")
A29: 3111 | B29: Platte | C29: Seite außen | D29: Seite außen (580x1800) | E29: 580 | F29: 1800 | G29: =IFERROR(INDEX(Aktiv!$G$6:$G$326,MATCH(A29,Aktiv!$A$6:$A$326,0)),"") -> 184 | H29: =IFERROR(INDEX(Aktiv!$H$6:$H$326,MATCH(A29,Aktiv!$A$6:$A$326,0)),"") -> 630 | I29: =IFERROR(INDEX(Aktiv!$I$6:$I$326,MATCH(A29,Aktiv!$A$6:$A$326,0)),"") -> 656 | J29: =IFERROR(INDEX(Aktiv!$J$6:$J$326,MATCH(A29,Aktiv!$A$6:$A$326,0)),"") -> 730 | K29: =IFERROR(ROUND(G29*Steuerungsdaten!$B$5,0),"-") -> 212 | L29: =IFERROR(ROUND(H29*Steuerungsdaten!$B$5,0),"-") -> 725 | M29: =IFERROR(ROUND(I29*Steuerungsdaten!$B$5,0),"-") -> 754 | N29: =IFERROR(ROUND(J29*Steuerungsdaten!$B$5,0),"-") -> 840 | O29: =IF(ISNA(MATCH(A29,Aktiv!$A$6:$A$326,0)),"⚠ nicht im Modell","")
... A42: 3124 | B42: Platte | C42: Seite außen | D42: Seite außen (580x580) | E42: 580 | F42: 580 | G42: =IFERROR(INDEX(Aktiv!$G$6:$G$326,MATCH(A42,Aktiv!$A$6:$A$326,0)),"") -> 59 | H42: =IFERROR(INDEX(Aktiv!$H$6:$H$326,MATCH(A42,Aktiv!$A$6:$A$326,0)),"") -> 203 | I42: =IFERROR(INDEX(Aktiv!$I$6:$I$326,MATCH(A42,Aktiv!$A$6:$A$326,0)),"") -> 211 | J42: =IFERROR(INDEX(Aktiv!$J$6:$J$326,MATCH(A42,Aktiv!$A$6:$A$326,0)),"") -> - | K42: =IFERROR(ROUND(G42*Steuerungsdaten!$B$5,0),"-") -> 68 | L42: =IFERROR(ROUND(H42*Steuerungsdaten!$B$5,0),"-") -> 233 | M42: =IFERROR(ROUND(I42*Steuerungsdaten!$B$5,0),"-") -> 243 | N42: =IFERROR(ROUND(J42*Steuerungsdaten!$B$5,0),"-") -> - | O42: =IF(ISNA(MATCH(A42,Aktiv!$A$6:$A$326,0)),"⚠ nicht im Modell","")
A43: S_0020 | B43: Platte | C43: Seite außen | D43: Seite außen (660x360) | E43: 660 | F43: 360 | G43: =IFERROR(INDEX(Aktiv!$G$6:$G$326,MATCH(A43,Aktiv!$A$6:$A$326,0)),"") -> 42 | H43: =IFERROR(INDEX(Aktiv!$H$6:$H$326,MATCH(A43,Aktiv!$A$6:$A$326,0)),"") -> 143 | I43: =IFERROR(INDEX(Aktiv!$I$6:$I$326,MATCH(A43,Aktiv!$A$6:$A$326,0)),"") -> 149 | J43: =IFERROR(INDEX(Aktiv!$J$6:$J$326,MATCH(A43,Aktiv!$A$6:$A$326,0)),"") -> - | K43: =IFERROR(ROUND(G43*Steuerungsdaten!$B$5,0),"-") -> 48 | L43: =IFERROR(ROUND(H43*Steuerungsdaten!$B$5,0),"-") -> 164 | M43: =IFERROR(ROUND(I43*Steuerungsdaten!$B$5,0),"-") -> 171 | N43: =IFERROR(ROUND(J43*Steuerungsdaten!$B$5,0),"-") -> - | O43: =IF(ISNA(MATCH(A43,Aktiv!$A$6:$A$326,0)),"⚠ nicht im Modell","")
A44: 3200 | B44: Platte | C44: Seite außen SY32 | D44: Seite außen SY32 (360x360) | E44: 360 | F44: 360 | G44: =IFERROR(INDEX(Aktiv!$G$6:$G$326,MATCH(A44,Aktiv!$A$6:$A$326,0)),"") -> 25 | H44: =IFERROR(INDEX(Aktiv!$H$6:$H$326,MATCH(A44,Aktiv!$A$6:$A$326,0)),"") -> 103 | I44: =IFERROR(INDEX(Aktiv!$I$6:$I$326,MATCH(A44,Aktiv!$A$6:$A$326,0)),"") -> 120 | J44: =IFERROR(INDEX(Aktiv!$J$6:$J$326,MATCH(A44,Aktiv!$A$6:$A$326,0)),"") -> 145 | K44: =IFERROR(ROUND(G44*Steuerungsdaten!$B$5,0),"-") -> 29 | L44: =IFERROR(ROUND(H44*Steuerungsdaten!$B$5,0),"-") -> 118 | M44: =IFERROR(ROUND(I44*Steuerungsdaten!$B$5,0),"-") -> 138 | N44: =IFERROR(ROUND(J44*Steuerungsdaten!$B$5,0),"-") -> 167 | O44: =IF(ISNA(MATCH(A44,Aktiv!$A$6:$A$326,0)),"⚠ nicht im Modell","")
A45: 3201 | B45: Platte | C45: Seite außen SY32 | D45: Seite außen SY32 (360x720) | E45: 360 | F45: 720 | G45: =IFERROR(INDEX(Aktiv!$G$6:$G$326,MATCH(A45,Aktiv!$A$6:$A$326,0)),"") -> 46 | H45: =IFERROR(INDEX(Aktiv!$H$6:$H$326,MATCH(A45,Aktiv!$A$6:$A$326,0)),"") -> 156 | I45: =IFERROR(INDEX(Aktiv!$I$6:$I$326,MATCH(A45,Aktiv!$A$6:$A$326,0)),"") -> 163 | J45: =IFERROR(INDEX(Aktiv!$J$6:$J$326,MATCH(A45,Aktiv!$A$6:$A$326,0)),"") -> 181 | K45: =IFERROR(ROUND(G45*Steuerungsdaten!$B$5,0),"-") -> 53 | L45: =IFERROR(ROUND(H45*Steuerungsdaten!$B$5,0),"-") -> 179 | M45: =IFERROR(ROUND(I45*Steuerungsdaten!$B$5,0),"-") -> 187 | N45: =IFERROR(ROUND(J45*Steuerungsdaten!$B$5,0),"-") -> 208 | O45: =IF(ISNA(MATCH(A45,Aktiv!$A$6:$A$326,0)),"⚠ nicht im Modell","")
A46: 3202 | B46: Platte | C46: Seite außen SY32 | D46: Seite außen SY32 (360x1080) | E46: 360 | F46: 1080 | G46: =IFERROR(INDEX(Aktiv!$G$6:$G$326,MATCH(A46,Aktiv!$A$6:$A$326,0)),"") -> 68 | H46: =IFERROR(INDEX(Aktiv!$H$6:$H$326,MATCH(A46,Aktiv!$A$6:$A$326,0)),"") -> 235 | I46: =IFERROR(INDEX(Aktiv!$I$6:$I$326,MATCH(A46,Aktiv!$A$6:$A$326,0)),"") -> 244 | J46: =IFERROR(INDEX(Aktiv!$J$6:$J$326,MATCH(A46,Aktiv!$A$6:$A$326,0)),"") -> 272 | K46: =IFERROR(ROUND(G46*Steuerungsdaten!$B$5,0),"-") -> 78 | L46: =IFERROR(ROUND(H46*Steuerungsdaten!$B$5,0),"-") -> 270 | M46: =IFERROR(ROUND(I46*Steuerungsdaten!$B$5,0),"-") -> 281 | N46: =IFERROR(ROUND(J46*Steuerungsdaten!$B$5,0),"-") -> 313 | O46: =IF(ISNA(MATCH(A46,Aktiv!$A$6:$A$326,0)),"⚠ nicht im Modell","")
A47: 3203 | B47: Platte | C47: Seite außen SY32 | D47: Seite außen SY32 (360x1440) | E47: 360 | F47: 1440 | G47: =IFERROR(INDEX(Aktiv!$G$6:$G$326,MATCH(A47,Aktiv!$A$6:$A$326,0)),"") -> 91 | H47: =IFERROR(INDEX(Aktiv!$H$6:$H$326,MATCH(A47,Aktiv!$A$6:$A$326,0)),"") -> 313 | I47: =IFERROR(INDEX(Aktiv!$I$6:$I$326,MATCH(A47,Aktiv!$A$6:$A$326,0)),"") -> 326 | J47: =IFERROR(INDEX(Aktiv!$J$6:$J$326,MATCH(A47,Aktiv!$A$6:$A$326,0)),"") -> 363 | K47: =IFERROR(ROUND(G47*Steuerungsdaten!$B$5,0),"-") -> 105 | L47: =IFERROR(ROUND(H47*Steuerungsdaten!$B$5,0),"-") -> 360 | M47: =IFERROR(ROUND(I47*Steuerungsdaten!$B$5,0),"-") -> 375 | N47: =IFERROR(ROUND(J47*Steuerungsdaten!$B$5,0),"-") -> 417 | O47: =IF(ISNA(MATCH(A47,Aktiv!$A$6:$A$326,0)),"⚠ nicht im Modell","")
A48: 3204 | B48: Platte | C48: Seite außen SY32 | D48: Seite außen SY32 (360x1800) | E48: 360 | F48: 1800 | G48: =IFERROR(INDEX(Aktiv!$G$6:$G$326,MATCH(A48,Aktiv!$A$6:$A$326,0)),"") -> 114 | H48: =IFERROR(INDEX(Aktiv!$H$6:$H$326,MATCH(A48,Aktiv!$A$6:$A$326,0)),"") -> 391 | I48: =IFERROR(INDEX(Aktiv!$I$6:$I$326,MATCH(A48,Aktiv!$A$6:$A$326,0)),"") -> 407 | J48: =IFERROR(INDEX(Aktiv!$J$6:$J$326,MATCH(A48,Aktiv!$A$6:$A$326,0)),"") -> 453 | K48: =IFERROR(ROUND(G48*Steuerungsdaten!$B$5,0),"-") -> 131 | L48: =IFERROR(ROUND(H48*Steuerungsdaten!$B$5,0),"-") -> 450 | M48: =IFERROR(ROUND(I48*Steuerungsdaten!$B$5,0),"-") -> 468 | N48: =IFERROR(ROUND(J48*Steuerungsdaten!$B$5,0),"-") -> 521 | O48: =IF(ISNA(MATCH(A48,Aktiv!$A$6:$A$326,0)),"⚠ nicht im Modell","")
A49: 3205 | B49: Platte | C49: Seite außen SY32 | D49: Seite außen SY32 (580x360) | E49: 580 | F49: 360 | G49: =IFERROR(INDEX(Aktiv!$G$6:$G$326,MATCH(A49,Aktiv!$A$6:$A$326,0)),"") -> 37 | H49: =IFERROR(INDEX(Aktiv!$H$6:$H$326,MATCH(A49,Aktiv!$A$6:$A$326,0)),"") -> 126 | I49: =IFERROR(INDEX(Aktiv!$I$6:$I$326,MATCH(A49,Aktiv!$A$6:$A$326,0)),"") -> 131 | J49: =IFERROR(INDEX(Aktiv!$J$6:$J$326,MATCH(A49,Aktiv!$A$6:$A$326,0)),"") -> 146 | K49: =IFERROR(ROUND(G49*Steuerungsdaten!$B$5,0),"-") -> 43 | L49: =IFERROR(ROUND(H49*Steuerungsdaten!$B$5,0),"-") -> 145 | M49: =IFERROR(ROUND(I49*Steuerungsdaten!$B$5,0),"-") -> 151 | N49: =IFERROR(ROUND(J49*Steuerungsdaten!$B$5,0),"-") -> 168 | O49: =IF(ISNA(MATCH(A49,Aktiv!$A$6:$A$326,0)),"⚠ nicht im Modell","")
A50: 3206 | B50: Platte | C50: Seite außen SY32 | D50: Seite außen SY32 (580x720) | E50: 580 | F50: 720 | G50: =IFERROR(INDEX(Aktiv!$G$6:$G$326,MATCH(A50,Aktiv!$A$6:$A$326,0)),"") -> 73 | H50: =IFERROR(INDEX(Aktiv!$H$6:$H$326,MATCH(A50,Aktiv!$A$6:$A$326,0)),"") -> 252 | I50: =IFERROR(INDEX(Aktiv!$I$6:$I$326,MATCH(A50,Aktiv!$A$6:$A$326,0)),"") -> 262 | J50: =IFERROR(INDEX(Aktiv!$J$6:$J$326,MATCH(A50,Aktiv!$A$6:$A$326,0)),"") -> 292 | K50: =IFERROR(ROUND(G50*Steuerungsdaten!$B$5,0),"-") -> 84 | L50: =IFERROR(ROUND(H50*Steuerungsdaten!$B$5,0),"-") -> 290 | M50: =IFERROR(ROUND(I50*Steuerungsdaten!$B$5,0),"-") -> 301 | N50: =IFERROR(ROUND(J50*Steuerungsdaten!$B$5,0),"-") -> 336 | O50: =IF(ISNA(MATCH(A50,Aktiv!$A$6:$A$326,0)),"⚠ nicht im Modell","")
A51: 3207 | B51: Platte | C51: Seite außen SY32 | D51: Seite außen SY32 (580x1080) | E51: 580 | F51: 1080 | G51: =IFERROR(INDEX(Aktiv!$G$6:$G$326,MATCH(A51,Aktiv!$A$6:$A$326,0)),"") -> 110 | H51: =IFERROR(INDEX(Aktiv!$H$6:$H$326,MATCH(A51,Aktiv!$A$6:$A$326,0)),"") -> 378 | I51: =IFERROR(INDEX(Aktiv!$I$6:$I$326,MATCH(A51,Aktiv!$A$6:$A$326,0)),"") -> 394 | J51: =IFERROR(INDEX(Aktiv!$J$6:$J$326,MATCH(A51,Aktiv!$A$6:$A$326,0)),"") -> 438 | K51: =IFERROR(ROUND(G51*Steuerungsdaten!$B$5,0),"-") -> 127 | L51: =IFERROR(ROUND(H51*Steuerungsdaten!$B$5,0),"-") -> 435 | M51: =IFERROR(ROUND(I51*Steuerungsdaten!$B$5,0),"-") -> 453 | N51: =IFERROR(ROUND(J51*Steuerungsdaten!$B$5,0),"-") -> 504 | O51: =IF(ISNA(MATCH(A51,Aktiv!$A$6:$A$326,0)),"⚠ nicht im Modell","")
A52: 3208 | B52: Platte | C52: Seite außen SY32 | D52: Seite außen SY32 (580x1440) | E52: 580 | F52: 1440 | G52: =IFERROR(INDEX(Aktiv!$G$6:$G$326,MATCH(A52,Aktiv!$A$6:$A$326,0)),"") -> 147 | H52: =IFERROR(INDEX(Aktiv!$H$6:$H$326,MATCH(A52,Aktiv!$A$6:$A$326,0)),"") -> 504 | I52: =IFERROR(INDEX(Aktiv!$I$6:$I$326,MATCH(A52,Aktiv!$A$6:$A$326,0)),"") -> 525 | J52: =IFERROR(INDEX(Aktiv!$J$6:$J$326,MATCH(A52,Aktiv!$A$6:$A$326,0)),"") -> 584 | K52: =IFERROR(ROUND(G52*Steuerungsdaten!$B$5,0),"-") -> 169 | L52: =IFERROR(ROUND(H52*Steuerungsdaten!$B$5,0),"-") -> 580 | M52: =IFERROR(ROUND(I52*Steuerungsdaten!$B$5,0),"-") -> 604 | N52: =IFERROR(ROUND(J52*Steuerungsdaten!$B$5,0),"-") -> 672 | O52: =IF(ISNA(MATCH(A52,Aktiv!$A$6:$A$326,0)),"⚠ nicht im Modell","")
A53: 3209 | B53: Platte | C53: Seite außen SY32 | D53: Seite außen SY32 (580x1800) | E53: 580 | F53: 1800 | G53: =IFERROR(INDEX(Aktiv!$G$6:$G$326,MATCH(A53,Aktiv!$A$6:$A$326,0)),"") -> 184 | H53: =IFERROR(INDEX(Aktiv!$H$6:$H$326,MATCH(A53,Aktiv!$A$6:$A$326,0)),"") -> 630 | I53: =IFERROR(INDEX(Aktiv!$I$6:$I$326,MATCH(A53,Aktiv!$A$6:$A$326,0)),"") -> 656 | J53: =IFERROR(INDEX(Aktiv!$J$6:$J$326,MATCH(A53,Aktiv!$A$6:$A$326,0)),"") -> 730 | K53: =IFERROR(ROUND(G53*Steuerungsdaten!$B$5,0),"-") -> 212 | L53: =IFERROR(ROUND(H53*Steuerungsdaten!$B$5,0),"-") -> 725 | M53: =IFERROR(ROUND(I53*Steuerungsdaten!$B$5,0),"-") -> 754 | N53: =IFERROR(ROUND(J53*Steuerungsdaten!$B$5,0),"-") -> 840 | O53: =IF(ISNA(MATCH(A53,Aktiv!$A$6:$A$326,0)),"⚠ nicht im Modell","")
A54: 3210 | B54: Platte | C54: Seite außen SY32 | D54: Seite außen SY32 (180x780) | E54: 180 | F54: 780 | G54: =IFERROR(INDEX(Aktiv!$G$6:$G$326,MATCH(A54,Aktiv!$A$6:$A$326,0)),"") -> 25 | H54: =IFERROR(INDEX(Aktiv!$H$6:$H$326,MATCH(A54,Aktiv!$A$6:$A$326,0)),"") -> 103 | I54: =IFERROR(INDEX(Aktiv!$I$6:$I$326,MATCH(A54,Aktiv!$A$6:$A$326,0)),"") -> 120 | J54: =IFERROR(INDEX(Aktiv!$J$6:$J$326,MATCH(A54,Aktiv!$A$6:$A$326,0)),"") -> 145 | K54: =IFERROR(ROUND(G54*Steuerungsdaten!$B$5,0),"-") -> 29 | L54: =IFERROR(ROUND(H54*Steuerungsdaten!$B$5,0),"-") -> 118 | M54: =IFERROR(ROUND(I54*Steuerungsdaten!$B$5,0),"-") -> 138 | N54: =IFERROR(ROUND(J54*Steuerungsdaten!$B$5,0),"-") -> 167 | O54: =IF(ISNA(MATCH(A54,Aktiv!$A$6:$A$326,0)),"⚠ nicht im Modell","")
A55: 3211 | B55: Platte | C55: Seite außen SY32 | D55: Seite außen SY32 (180x980) | E55: 180 | F55: 980 | G55: =IFERROR(INDEX(Aktiv!$G$6:$G$326,MATCH(A55,Aktiv!$A$6:$A$326,0)),"") -> 31 | H55: =IFERROR(INDEX(Aktiv!$H$6:$H$326,MATCH(A55,Aktiv!$A$6:$A$326,0)),"") -> 106 | I55: =IFERROR(INDEX(Aktiv!$I$6:$I$326,MATCH(A55,Aktiv!$A$6:$A$326,0)),"") -> 120 | J55: =IFERROR(INDEX(Aktiv!$J$6:$J$326,MATCH(A55,Aktiv!$A$6:$A$326,0)),"") -> 145 | K55: =IFERROR(ROUND(G55*Steuerungsdaten!$B$5,0),"-") -> 36 | L55: =IFERROR(ROUND(H55*Steuerungsdaten!$B$5,0),"-") -> 122 | M55: =IFERROR(ROUND(I55*Steuerungsdaten!$B$5,0),"-") -> 138 | N55: =IFERROR(ROUND(J55*Steuerungsdaten!$B$5,0),"-") -> 167 | O55: =IF(ISNA(MATCH(A55,Aktiv!$A$6:$A$326,0)),"⚠ nicht im Modell","")
... A198: 5007 | B198: Platte | C198: Klappe | D198: Klappe (980x360) | E198: 980 | F198: 360 | G198: =IFERROR(INDEX(Aktiv!$G$6:$G$326,MATCH(A198,Aktiv!$A$6:$A$326,0)),"") -> 224 | H198: =IFERROR(INDEX(Aktiv!$H$6:$H$326,MATCH(A198,Aktiv!$A$6:$A$326,0)),"") -> 369 | I198: =IFERROR(INDEX(Aktiv!$I$6:$I$326,MATCH(A198,Aktiv!$A$6:$A$326,0)),"") -> 389 | J198: =IFERROR(INDEX(Aktiv!$J$6:$J$326,MATCH(A198,Aktiv!$A$6:$A$326,0)),"") -> 525 | K198: =IFERROR(ROUND(G198*Steuerungsdaten!$B$5,0),"-") -> 258 | L198: =IFERROR(ROUND(H198*Steuerungsdaten!$B$5,0),"-") -> 424 | M198: =IFERROR(ROUND(I198*Steuerungsdaten!$B$5,0),"-") -> 447 | N198: =IFERROR(ROUND(J198*Steuerungsdaten!$B$5,0),"-") -> 604 | O198: =IF(ISNA(MATCH(A198,Aktiv!$A$6:$A$326,0)),"⚠ nicht im Modell","")
A199: 5009 | B199: Platte | C199: Klappe | D199: Klappe (360x180) | E199: 360 | F199: 180 | G199: =IFERROR(INDEX(Aktiv!$G$6:$G$326,MATCH(A199,Aktiv!$A$6:$A$326,0)),"") -> - | H199: =IFERROR(INDEX(Aktiv!$H$6:$H$326,MATCH(A199,Aktiv!$A$6:$A$326,0)),"") -> - | I199: =IFERROR(INDEX(Aktiv!$I$6:$I$326,MATCH(A199,Aktiv!$A$6:$A$326,0)),"") -> - | J199: =IFERROR(INDEX(Aktiv!$J$6:$J$326,MATCH(A199,Aktiv!$A$6:$A$326,0)),"") -> - | K199: =IFERROR(ROUND(G199*Steuerungsdaten!$B$5,0),"-") -> - | L199: =IFERROR(ROUND(H199*Steuerungsdaten!$B$5,0),"-") -> - | M199: =IFERROR(ROUND(I199*Steuerungsdaten!$B$5,0),"-") -> - | N199: =IFERROR(ROUND(J199*Steuerungsdaten!$B$5,0),"-") -> - | O199: ⚠ Größe außerhalb Konfigurator-Standard
A200: 5008 | B200: Platte | C200: Klappe | D200: Klappe (360x360) | E200: 360 | F200: 360 | G200: =IFERROR(INDEX(Aktiv!$G$6:$G$326,MATCH(A200,Aktiv!$A$6:$A$326,0)),"") -> - | H200: =IFERROR(INDEX(Aktiv!$H$6:$H$326,MATCH(A200,Aktiv!$A$6:$A$326,0)),"") -> - | I200: =IFERROR(INDEX(Aktiv!$I$6:$I$326,MATCH(A200,Aktiv!$A$6:$A$326,0)),"") -> - | J200: =IFERROR(INDEX(Aktiv!$J$6:$J$326,MATCH(A200,Aktiv!$A$6:$A$326,0)),"") -> - | K200: =IFERROR(ROUND(G200*Steuerungsdaten!$B$5,0),"-") -> - | L200: =IFERROR(ROUND(H200*Steuerungsdaten!$B$5,0),"-") -> - | M200: =IFERROR(ROUND(I200*Steuerungsdaten!$B$5,0),"-") -> - | N200: =IFERROR(ROUND(J200*Steuerungsdaten!$B$5,0),"-") -> - | O200: ⚠ Größe außerhalb Konfigurator-Standard
A201: S_0046 | B201: Platte | C201: Klappe | D201: Klappe (980x420) | E201: 980 | F201: 420 | G201: =IFERROR(INDEX(Aktiv!$G$6:$G$326,MATCH(A201,Aktiv!$A$6:$A$326,0)),"") -> - | H201: =IFERROR(INDEX(Aktiv!$H$6:$H$326,MATCH(A201,Aktiv!$A$6:$A$326,0)),"") -> - | I201: =IFERROR(INDEX(Aktiv!$I$6:$I$326,MATCH(A201,Aktiv!$A$6:$A$326,0)),"") -> - | J201: =IFERROR(INDEX(Aktiv!$J$6:$J$326,MATCH(A201,Aktiv!$A$6:$A$326,0)),"") -> - | K201: =IFERROR(ROUND(G201*Steuerungsdaten!$B$5,0),"-") -> - | L201: =IFERROR(ROUND(H201*Steuerungsdaten!$B$5,0),"-") -> - | M201: =IFERROR(ROUND(I201*Steuerungsdaten!$B$5,0),"-") -> - | N201: =IFERROR(ROUND(J201*Steuerungsdaten!$B$5,0),"-") -> - | O201: ⚠ Größe außerhalb Konfigurator-Standard
A202: 5100 | B202: Platte | C202: Tür | D202: Tür (420x360) | E202: 420 | F202: 360 | G202: =IFERROR(INDEX(Aktiv!$G$6:$G$326,MATCH(A202,Aktiv!$A$6:$A$326,0)),"") -> 127 | H202: =IFERROR(INDEX(Aktiv!$H$6:$H$326,MATCH(A202,Aktiv!$A$6:$A$326,0)),"") -> 273 | I202: =IFERROR(INDEX(Aktiv!$I$6:$I$326,MATCH(A202,Aktiv!$A$6:$A$326,0)),"") -> 298 | J202: =IFERROR(INDEX(Aktiv!$J$6:$J$326,MATCH(A202,Aktiv!$A$6:$A$326,0)),"") -> 433 | K202: =IFERROR(ROUND(G202*Steuerungsdaten!$B$5,0),"-") -> 146 | L202: =IFERROR(ROUND(H202*Steuerungsdaten!$B$5,0),"-") -> 314 | M202: =IFERROR(ROUND(I202*Steuerungsdaten!$B$5,0),"-") -> 343 | N202: =IFERROR(ROUND(J202*Steuerungsdaten!$B$5,0),"-") -> 498 | O202: =IF(ISNA(MATCH(A202,Aktiv!$A$6:$A$326,0)),"⚠ nicht im Modell","")
A203: 5101 | B203: Platte | C203: Tür | D203: Tür (420x720) | E203: 420 | F203: 720 | G203: =IFERROR(INDEX(Aktiv!$G$6:$G$326,MATCH(A203,Aktiv!$A$6:$A$326,0)),"") -> 180 | H203: =IFERROR(INDEX(Aktiv!$H$6:$H$326,MATCH(A203,Aktiv!$A$6:$A$326,0)),"") -> 386 | I203: =IFERROR(INDEX(Aktiv!$I$6:$I$326,MATCH(A203,Aktiv!$A$6:$A$326,0)),"") -> 422 | J203: =IFERROR(INDEX(Aktiv!$J$6:$J$326,MATCH(A203,Aktiv!$A$6:$A$326,0)),"") -> 612 | K203: =IFERROR(ROUND(G203*Steuerungsdaten!$B$5,0),"-") -> 207 | L203: =IFERROR(ROUND(H203*Steuerungsdaten!$B$5,0),"-") -> 444 | M203: =IFERROR(ROUND(I203*Steuerungsdaten!$B$5,0),"-") -> 485 | N203: =IFERROR(ROUND(J203*Steuerungsdaten!$B$5,0),"-") -> 704 | O203: =IF(ISNA(MATCH(A203,Aktiv!$A$6:$A$326,0)),"⚠ nicht im Modell","")
A204: 5102 | B204: Platte | C204: Tür | D204: Tür (420x1080) | E204: 420 | F204: 1080 | G204: =IFERROR(INDEX(Aktiv!$G$6:$G$326,MATCH(A204,Aktiv!$A$6:$A$326,0)),"") -> 220 | H204: =IFERROR(INDEX(Aktiv!$H$6:$H$326,MATCH(A204,Aktiv!$A$6:$A$326,0)),"") -> 473 | I204: =IFERROR(INDEX(Aktiv!$I$6:$I$326,MATCH(A204,Aktiv!$A$6:$A$326,0)),"") -> 517 | J204: =IFERROR(INDEX(Aktiv!$J$6:$J$326,MATCH(A204,Aktiv!$A$6:$A$326,0)),"") -> 750 | K204: =IFERROR(ROUND(G204*Steuerungsdaten!$B$5,0),"-") -> 253 | L204: =IFERROR(ROUND(H204*Steuerungsdaten!$B$5,0),"-") -> 544 | M204: =IFERROR(ROUND(I204*Steuerungsdaten!$B$5,0),"-") -> 595 | N204: =IFERROR(ROUND(J204*Steuerungsdaten!$B$5,0),"-") -> 863 | O204: =IF(ISNA(MATCH(A204,Aktiv!$A$6:$A$326,0)),"⚠ nicht im Modell","")
A205: 5103 | B205: Platte | C205: Tür | D205: Tür (420x1440) | E205: 420 | F205: 1440 | G205: =IFERROR(INDEX(Aktiv!$G$6:$G$326,MATCH(A205,Aktiv!$A$6:$A$326,0)),"") -> 254 | H205: =IFERROR(INDEX(Aktiv!$H$6:$H$326,MATCH(A205,Aktiv!$A$6:$A$326,0)),"") -> 546 | I205: =IFERROR(INDEX(Aktiv!$I$6:$I$326,MATCH(A205,Aktiv!$A$6:$A$326,0)),"") -> 597 | J205: =IFERROR(INDEX(Aktiv!$J$6:$J$326,MATCH(A205,Aktiv!$A$6:$A$326,0)),"") -> 866 | K205: =IFERROR(ROUND(G205*Steuerungsdaten!$B$5,0),"-") -> 292 | L205: =IFERROR(ROUND(H205*Steuerungsdaten!$B$5,0),"-") -> 628 | M205: =IFERROR(ROUND(I205*Steuerungsdaten!$B$5,0),"-") -> 687 | N205: =IFERROR(ROUND(J205*Steuerungsdaten!$B$5,0),"-") -> 996 | O205: =IF(ISNA(MATCH(A205,Aktiv!$A$6:$A$326,0)),"⚠ nicht im Modell","")
A206: 5104 | B206: Platte | C206: Tür | D206: Tür (420x1800) | E206: 420 | F206: 1800 | G206: =IFERROR(INDEX(Aktiv!$G$6:$G$326,MATCH(A206,Aktiv!$A$6:$A$326,0)),"") -> 285 | H206: =IFERROR(INDEX(Aktiv!$H$6:$H$326,MATCH(A206,Aktiv!$A$6:$A$326,0)),"") -> 610 | I206: =IFERROR(INDEX(Aktiv!$I$6:$I$326,MATCH(A206,Aktiv!$A$6:$A$326,0)),"") -> 667 | J206: =IFERROR(INDEX(Aktiv!$J$6:$J$326,MATCH(A206,Aktiv!$A$6:$A$326,0)),"") -> 968 | K206: =IFERROR(ROUND(G206*Steuerungsdaten!$B$5,0),"-") -> 328 | L206: =IFERROR(ROUND(H206*Steuerungsdaten!$B$5,0),"-") -> 702 | M206: =IFERROR(ROUND(I206*Steuerungsdaten!$B$5,0),"-") -> 767 | N206: =IFERROR(ROUND(J206*Steuerungsdaten!$B$5,0),"-") -> 1113 | O206: =IF(ISNA(MATCH(A206,Aktiv!$A$6:$A$326,0)),"⚠ nicht im Modell","")
A207: 5105 | B207: Platte | C207: Tür | D207: Tür (580x360) | E207: 580 | F207: 360 | G207: =IFERROR(INDEX(Aktiv!$G$6:$G$326,MATCH(A207,Aktiv!$A$6:$A$326,0)),"") -> 150 | H207: =IFERROR(INDEX(Aktiv!$H$6:$H$326,MATCH(A207,Aktiv!$A$6:$A$326,0)),"") -> 321 | I207: =IFERROR(INDEX(Aktiv!$I$6:$I$326,MATCH(A207,Aktiv!$A$6:$A$326,0)),"") -> 351 | J207: =IFERROR(INDEX(Aktiv!$J$6:$J$326,MATCH(A207,Aktiv!$A$6:$A$326,0)),"") -> 509 | K207: =IFERROR(ROUND(G207*Steuerungsdaten!$B$5,0),"-") -> 173 | L207: =IFERROR(ROUND(H207*Steuerungsdaten!$B$5,0),"-") -> 369 | M207: =IFERROR(ROUND(I207*Steuerungsdaten!$B$5,0),"-") -> 404 | N207: =IFERROR(ROUND(J207*Steuerungsdaten!$B$5,0),"-") -> 585 | O207: =IF(ISNA(MATCH(A207,Aktiv!$A$6:$A$326,0)),"⚠ nicht im Modell","")
A208: 5106 | B208: Platte | C208: Tür | D208: Tür (580x720) | E208: 580 | F208: 720 | G208: =IFERROR(INDEX(Aktiv!$G$6:$G$326,MATCH(A208,Aktiv!$A$6:$A$326,0)),"") -> 211 | H208: =IFERROR(INDEX(Aktiv!$H$6:$H$326,MATCH(A208,Aktiv!$A$6:$A$326,0)),"") -> 454 | I208: =IFERROR(INDEX(Aktiv!$I$6:$I$326,MATCH(A208,Aktiv!$A$6:$A$326,0)),"") -> 496 | J208: =IFERROR(INDEX(Aktiv!$J$6:$J$326,MATCH(A208,Aktiv!$A$6:$A$326,0)),"") -> 720 | K208: =IFERROR(ROUND(G208*Steuerungsdaten!$B$5,0),"-") -> 243 | L208: =IFERROR(ROUND(H208*Steuerungsdaten!$B$5,0),"-") -> 522 | M208: =IFERROR(ROUND(I208*Steuerungsdaten!$B$5,0),"-") -> 570 | N208: =IFERROR(ROUND(J208*Steuerungsdaten!$B$5,0),"-") -> 828 | O208: =IF(ISNA(MATCH(A208,Aktiv!$A$6:$A$326,0)),"⚠ nicht im Modell","")
A209: 5107 | B209: Platte | C209: Tür | D209: Tür (580x1080) | E209: 580 | F209: 1080 | G209: =IFERROR(INDEX(Aktiv!$G$6:$G$326,MATCH(A209,Aktiv!$A$6:$A$326,0)),"") -> 259 | H209: =IFERROR(INDEX(Aktiv!$H$6:$H$326,MATCH(A209,Aktiv!$A$6:$A$326,0)),"") -> 556 | I209: =IFERROR(INDEX(Aktiv!$I$6:$I$326,MATCH(A209,Aktiv!$A$6:$A$326,0)),"") -> 607 | J209: =IFERROR(INDEX(Aktiv!$J$6:$J$326,MATCH(A209,Aktiv!$A$6:$A$326,0)),"") -> 882 | K209: =IFERROR(ROUND(G209*Steuerungsdaten!$B$5,0),"-") -> 298 | L209: =IFERROR(ROUND(H209*Steuerungsdaten!$B$5,0),"-") -> 639 | M209: =IFERROR(ROUND(I209*Steuerungsdaten!$B$5,0),"-") -> 698 | N209: =IFERROR(ROUND(J209*Steuerungsdaten!$B$5,0),"-") -> 1014 | O209: =IF(ISNA(MATCH(A209,Aktiv!$A$6:$A$326,0)),"⚠ nicht im Modell","")
A210: 5108 | B210: Platte | C210: Tür | D210: Tür (580x1440) | E210: 580 | F210: 1440 | G210: =IFERROR(INDEX(Aktiv!$G$6:$G$326,MATCH(A210,Aktiv!$A$6:$A$326,0)),"") -> 299 | H210: =IFERROR(INDEX(Aktiv!$H$6:$H$326,MATCH(A210,Aktiv!$A$6:$A$326,0)),"") -> 641 | I210: =IFERROR(INDEX(Aktiv!$I$6:$I$326,MATCH(A210,Aktiv!$A$6:$A$326,0)),"") -> 701 | J210: =IFERROR(INDEX(Aktiv!$J$6:$J$326,MATCH(A210,Aktiv!$A$6:$A$326,0)),"") -> 1018 | K210: =IFERROR(ROUND(G210*Steuerungsdaten!$B$5,0),"-") -> 344 | L210: =IFERROR(ROUND(H210*Steuerungsdaten!$B$5,0),"-") -> 737 | M210: =IFERROR(ROUND(I210*Steuerungsdaten!$B$5,0),"-") -> 806 | N210: =IFERROR(ROUND(J210*Steuerungsdaten!$B$5,0),"-") -> 1171 | O210: =IF(ISNA(MATCH(A210,Aktiv!$A$6:$A$326,0)),"⚠ nicht im Modell","")
A211: 5109 | B211: Platte | C211: Tür | D211: Tür (580x1800) | E211: 580 | F211: 1800 | G211: =IFERROR(INDEX(Aktiv!$G$6:$G$326,MATCH(A211,Aktiv!$A$6:$A$326,0)),"") -> 334 | H211: =IFERROR(INDEX(Aktiv!$H$6:$H$326,MATCH(A211,Aktiv!$A$6:$A$326,0)),"") -> 717 | I211: =IFERROR(INDEX(Aktiv!$I$6:$I$326,MATCH(A211,Aktiv!$A$6:$A$326,0)),"") -> 784 | J211: =IFERROR(INDEX(Aktiv!$J$6:$J$326,MATCH(A211,Aktiv!$A$6:$A$326,0)),"") -> 1138 | K211: =IFERROR(ROUND(G211*Steuerungsdaten!$B$5,0),"-") -> 384 | L211: =IFERROR(ROUND(H211*Steuerungsdaten!$B$5,0),"-") -> 825 | M211: =IFERROR(ROUND(I211*Steuerungsdaten!$B$5,0),"-") -> 902 | N211: =IFERROR(ROUND(J211*Steuerungsdaten!$B$5,0),"-") -> 1309 | O211: =IF(ISNA(MATCH(A211,Aktiv!$A$6:$A$326,0)),"⚠ nicht im Modell","")
A212: 5110 | B212: Platte | C212: Tür | D212: Tür (360x360) | E212: 360 | F212: 360 | G212: =IFERROR(INDEX(Aktiv!$G$6:$G$326,MATCH(A212,Aktiv!$A$6:$A$326,0)),"") -> - | H212: =IFERROR(INDEX(Aktiv!$H$6:$H$326,MATCH(A212,Aktiv!$A$6:$A$326,0)),"") -> - | I212: =IFERROR(INDEX(Aktiv!$I$6:$I$326,MATCH(A212,Aktiv!$A$6:$A$326,0)),"") -> - | J212: =IFERROR(INDEX(Aktiv!$J$6:$J$326,MATCH(A212,Aktiv!$A$6:$A$326,0)),"") -> - | K212: =IFERROR(ROUND(G212*Steuerungsdaten!$B$5,0),"-") -> - | L212: =IFERROR(ROUND(H212*Steuerungsdaten!$B$5,0),"-") -> - | M212: =IFERROR(ROUND(I212*Steuerungsdaten!$B$5,0),"-") -> - | N212: =IFERROR(ROUND(J212*Steuerungsdaten!$B$5,0),"-") -> - | O212: ⚠ Größe außerhalb Konfigurator-Standard
A213: 5111 | B213: Platte | C213: Tür | D213: Tür (780x360) | E213: 780 | F213: 360 | G213: =IFERROR(INDEX(Aktiv!$G$6:$G$326,MATCH(A213,Aktiv!$A$6:$A$326,0)),"") -> - | H213: =IFERROR(INDEX(Aktiv!$H$6:$H$326,MATCH(A213,Aktiv!$A$6:$A$326,0)),"") -> - | I213: =IFERROR(INDEX(Aktiv!$I$6:$I$326,MATCH(A213,Aktiv!$A$6:$A$326,0)),"") -> - | J213: =IFERROR(INDEX(Aktiv!$J$6:$J$326,MATCH(A213,Aktiv!$A$6:$A$326,0)),"") -> - | K213: =IFERROR(ROUND(G213*Steuerungsdaten!$B$5,0),"-") -> - | L213: =IFERROR(ROUND(H213*Steuerungsdaten!$B$5,0),"-") -> - | M213: =IFERROR(ROUND(I213*Steuerungsdaten!$B$5,0),"-") -> - | N213: =IFERROR(ROUND(J213*Steuerungsdaten!$B$5,0),"-") -> - | O213: ⚠ Größe außerhalb Konfigurator-Standard
A214: 5200 | B214: Platte | C214: Doppeltür | D214: Doppeltür (780x360) | E214: 780 | F214: 360 | G214: =IFERROR(INDEX(Aktiv!$G$6:$G$326,MATCH(A214,Aktiv!$A$6:$A$326,0)),"") -> 212 | H214: =IFERROR(INDEX(Aktiv!$H$6:$H$326,MATCH(A214,Aktiv!$A$6:$A$326,0)),"") -> 300 | I214: =IFERROR(INDEX(Aktiv!$I$6:$I$326,MATCH(A214,Aktiv!$A$6:$A$326,0)),"") -> 316 | J214: =IFERROR(INDEX(Aktiv!$J$6:$J$326,MATCH(A214,Aktiv!$A$6:$A$326,0)),"") -> 697 | K214: =IFERROR(ROUND(G214*Steuerungsdaten!$B$5,0),"-") -> 244 | L214: =IFERROR(ROUND(H214*Steuerungsdaten!$B$5,0),"-") -> 345 | M214: =IFERROR(ROUND(I214*Steuerungsdaten!$B$5,0),"-") -> 363 | N214: =IFERROR(ROUND(J214*Steuerungsdaten!$B$5,0),"-") -> 802 | O214: =IF(ISNA(MATCH(A214,Aktiv!$A$6:$A$326,0)),"⚠ nicht im Modell","")
A215: 5210 | B215: Platte | C215: Doppeltür | D215: Doppeltür (780x660) | E215: 780 | F215: 660 | G215: =IFERROR(INDEX(Aktiv!$G$6:$G$326,MATCH(A215,Aktiv!$A$6:$A$326,0)),"") -> 323 | H215: =IFERROR(INDEX(Aktiv!$H$6:$H$326,MATCH(A215,Aktiv!$A$6:$A$326,0)),"") -> 458 | I215: =IFERROR(INDEX(Aktiv!$I$6:$I$326,MATCH(A215,Aktiv!$A$6:$A$326,0)),"") -> 483 | J215: =IFERROR(INDEX(Aktiv!$J$6:$J$326,MATCH(A215,Aktiv!$A$6:$A$326,0)),"") -> 1065 | K215: =IFERROR(ROUND(G215*Steuerungsdaten!$B$5,0),"-") -> 371 | L215: =IFERROR(ROUND(H215*Steuerungsdaten!$B$5,0),"-") -> 527 | M215: =IFERROR(ROUND(I215*Steuerungsdaten!$B$5,0),"-") -> 555 | N215: =IFERROR(ROUND(J215*Steuerungsdaten!$B$5,0),"-") -> 1225 | O215: =IF(ISNA(MATCH(A215,Aktiv!$A$6:$A$326,0)),"⚠ nicht im Modell","")
A216: 5201 | B216: Platte | C216: Doppeltür | D216: Doppeltür (780x720) | E216: 780 | F216: 720 | G216: =IFERROR(INDEX(Aktiv!$G$6:$G$326,MATCH(A216,Aktiv!$A$6:$A$326,0)),"") -> 344 | H216: =IFERROR(INDEX(Aktiv!$H$6:$H$326,MATCH(A216,Aktiv!$A$6:$A$326,0)),"") -> 487 | I216: =IFERROR(INDEX(Aktiv!$I$6:$I$326,MATCH(A216,Aktiv!$A$6:$A$326,0)),"") -> 514 | J216: =IFERROR(INDEX(Aktiv!$J$6:$J$326,MATCH(A216,Aktiv!$A$6:$A$326,0)),"") -> 1132 | K216: =IFERROR(ROUND(G216*Steuerungsdaten!$B$5,0),"-") -> 396 | L216: =IFERROR(ROUND(H216*Steuerungsdaten!$B$5,0),"-") -> 560 | M216: =IFERROR(ROUND(I216*Steuerungsdaten!$B$5,0),"-") -> 591 | N216: =IFERROR(ROUND(J216*Steuerungsdaten!$B$5,0),"-") -> 1302 | O216: =IF(ISNA(MATCH(A216,Aktiv!$A$6:$A$326,0)),"⚠ nicht im Modell","")
A217: 5202 | B217: Platte | C217: Doppeltür | D217: Doppeltür (780x1080) | E217: 780 | F217: 1080 | G217: =IFERROR(INDEX(Aktiv!$G$6:$G$326,MATCH(A217,Aktiv!$A$6:$A$326,0)),"") -> 456 | H217: =IFERROR(INDEX(Aktiv!$H$6:$H$326,MATCH(A217,Aktiv!$A$6:$A$326,0)),"") -> 646 | I217: =IFERROR(INDEX(Aktiv!$I$6:$I$326,MATCH(A217,Aktiv!$A$6:$A$326,0)),"") -> 682 | J217: =IFERROR(INDEX(Aktiv!$J$6:$J$326,MATCH(A217,Aktiv!$A$6:$A$326,0)),"") -> 1504 | K217: =IFERROR(ROUND(G217*Steuerungsdaten!$B$5,0),"-") -> 524 | L217: =IFERROR(ROUND(H217*Steuerungsdaten!$B$5,0),"-") -> 743 | M217: =IFERROR(ROUND(I217*Steuerungsdaten!$B$5,0),"-") -> 784 | N217: =IFERROR(ROUND(J217*Steuerungsdaten!$B$5,0),"-") -> 1730 | O217: =IF(ISNA(MATCH(A217,Aktiv!$A$6:$A$326,0)),"⚠ nicht im Modell","")
A218: 5203 | B218: Platte | C218: Doppeltür | D218: Doppeltür (780x1440) | E218: 780 | F218: 1440 | G218: =IFERROR(INDEX(Aktiv!$G$6:$G$326,MATCH(A218,Aktiv!$A$6:$A$326,0)),"") -> 558 | H218: =IFERROR(INDEX(Aktiv!$H$6:$H$326,MATCH(A218,Aktiv!$A$6:$A$326,0)),"") -> 790 | I218: =IFERROR(INDEX(Aktiv!$I$6:$I$326,MATCH(A218,Aktiv!$A$6:$A$326,0)),"") -> 834 | J218: =IFERROR(INDEX(Aktiv!$J$6:$J$326,MATCH(A218,Aktiv!$A$6:$A$326,0)),"") -> 1839 | K218: =IFERROR(ROUND(G218*Steuerungsdaten!$B$5,0),"-") -> 642 | L218: =IFERROR(ROUND(H218*Steuerungsdaten!$B$5,0),"-") -> 909 | M218: =IFERROR(ROUND(I218*Steuerungsdaten!$B$5,0),"-") -> 959 | N218: =IFERROR(ROUND(J218*Steuerungsdaten!$B$5,0),"-") -> 2115 | O218: =IF(ISNA(MATCH(A218,Aktiv!$A$6:$A$326,0)),"⚠ nicht im Modell","")
A219: 5204 | B219: Platte | C219: Doppeltür | D219: Doppeltür (780x1800) | E219: 780 | F219: 1800 | G219: =IFERROR(INDEX(Aktiv!$G$6:$G$326,MATCH(A219,Aktiv!$A$6:$A$326,0)),"") -> 653 | H219: =IFERROR(INDEX(Aktiv!$H$6:$H$326,MATCH(A219,Aktiv!$A$6:$A$326,0)),"") -> 924 | I219: =IFERROR(INDEX(Aktiv!$I$6:$I$326,MATCH(A219,Aktiv!$A$6:$A$326,0)),"") -> 975 | J219: =IFERROR(INDEX(Aktiv!$J$6:$J$326,MATCH(A219,Aktiv!$A$6:$A$326,0)),"") -> 2150 | K219: =IFERROR(ROUND(G219*Steuerungsdaten!$B$5,0),"-") -> 751 | L219: =IFERROR(ROUND(H219*Steuerungsdaten!$B$5,0),"-") -> 1063 | M219: =IFERROR(ROUND(I219*Steuerungsdaten!$B$5,0),"-") -> 1121 | N219: =IFERROR(ROUND(J219*Steuerungsdaten!$B$5,0),"-") -> 2473 | O219: =IF(ISNA(MATCH(A219,Aktiv!$A$6:$A$326,0)),"⚠ nicht im Modell","")
A220: 5205 | B220: Platte | C220: Doppeltür | D220: Doppeltür (980x360) | E220: 980 | F220: 360 | G220: =IFERROR(INDEX(Aktiv!$G$6:$G$326,MATCH(A220,Aktiv!$A$6:$A$326,0)),"") -> 248 | H220: =IFERROR(INDEX(Aktiv!$H$6:$H$326,MATCH(A220,Aktiv!$A$6:$A$326,0)),"") -> 351 | I220: =IFERROR(INDEX(Aktiv!$I$6:$I$326,MATCH(A220,Aktiv!$A$6:$A$326,0)),"") -> 371 | J220: =IFERROR(INDEX(Aktiv!$J$6:$J$326,MATCH(A220,Aktiv!$A$6:$A$326,0)),"") -> 818 | K220: =IFERROR(ROUND(G220*Steuerungsdaten!$B$5,0),"-") -> 285 | L220: =IFERROR(ROUND(H220*Steuerungsdaten!$B$5,0),"-") -> 404 | M220: =IFERROR(ROUND(I220*Steuerungsdaten!$B$5,0),"-") -> 427 | N220: =IFERROR(ROUND(J220*Steuerungsdaten!$B$5,0),"-") -> 941 | O220: =IF(ISNA(MATCH(A220,Aktiv!$A$6:$A$326,0)),"⚠ nicht im Modell","")
A221: 5206 | B221: Platte | C221: Doppeltür | D221: Doppeltür (980x720) | E221: 980 | F221: 720 | G221: =IFERROR(INDEX(Aktiv!$G$6:$G$326,MATCH(A221,Aktiv!$A$6:$A$326,0)),"") -> 403 | H221: =IFERROR(INDEX(Aktiv!$H$6:$H$326,MATCH(A221,Aktiv!$A$6:$A$326,0)),"") -> 571 | I221: =IFERROR(INDEX(Aktiv!$I$6:$I$326,MATCH(A221,Aktiv!$A$6:$A$326,0)),"") -> 602 | J221: =IFERROR(INDEX(Aktiv!$J$6:$J$326,MATCH(A221,Aktiv!$A$6:$A$326,0)),"") -> 1328 | K221: =IFERROR(ROUND(G221*Steuerungsdaten!$B$5,0),"-") -> 463 | L221: =IFERROR(ROUND(H221*Steuerungsdaten!$B$5,0),"-") -> 657 | M221: =IFERROR(ROUND(I221*Steuerungsdaten!$B$5,0),"-") -> 692 | N221: =IFERROR(ROUND(J221*Steuerungsdaten!$B$5,0),"-") -> 1527 | O221: =IF(ISNA(MATCH(A221,Aktiv!$A$6:$A$326,0)),"⚠ nicht im Modell","")
A222: 5207 | B222: Platte | C222: Doppeltür | D222: Doppeltür (980x1080) | E222: 980 | F222: 1080 | G222: =IFERROR(INDEX(Aktiv!$G$6:$G$326,MATCH(A222,Aktiv!$A$6:$A$326,0)),"") -> 536 | H222: =IFERROR(INDEX(Aktiv!$H$6:$H$326,MATCH(A222,Aktiv!$A$6:$A$326,0)),"") -> 758 | I222: =IFERROR(INDEX(Aktiv!$I$6:$I$326,MATCH(A222,Aktiv!$A$6:$A$326,0)),"") -> 800 | J222: =IFERROR(INDEX(Aktiv!$J$6:$J$326,MATCH(A222,Aktiv!$A$6:$A$326,0)),"") -> 1764 | K222: =IFERROR(ROUND(G222*Steuerungsdaten!$B$5,0),"-") -> 616 | L222: =IFERROR(ROUND(H222*Steuerungsdaten!$B$5,0),"-") -> 872 | M222: =IFERROR(ROUND(I222*Steuerungsdaten!$B$5,0),"-") -> 920 | N222: =IFERROR(ROUND(J222*Steuerungsdaten!$B$5,0),"-") -> 2029 | O222: =IF(ISNA(MATCH(A222,Aktiv!$A$6:$A$326,0)),"⚠ nicht im Modell","")
A223: 5208 | B223: Platte | C223: Doppeltür | D223: Doppeltür (980x1440) | E223: 980 | F223: 1440 | G223: =IFERROR(INDEX(Aktiv!$G$6:$G$326,MATCH(A223,Aktiv!$A$6:$A$326,0)),"") -> - | H223: =IFERROR(INDEX(Aktiv!$H$6:$H$326,MATCH(A223,Aktiv!$A$6:$A$326,0)),"") -> - | I223: =IFERROR(INDEX(Aktiv!$I$6:$I$326,MATCH(A223,Aktiv!$A$6:$A$326,0)),"") -> - | J223: =IFERROR(INDEX(Aktiv!$J$6:$J$326,MATCH(A223,Aktiv!$A$6:$A$326,0)),"") -> - | K223: =IFERROR(ROUND(G223*Steuerungsdaten!$B$5,0),"-") -> - | L223: =IFERROR(ROUND(H223*Steuerungsdaten!$B$5,0),"-") -> - | M223: =IFERROR(ROUND(I223*Steuerungsdaten!$B$5,0),"-") -> - | N223: =IFERROR(ROUND(J223*Steuerungsdaten!$B$5,0),"-") -> - | O223: =IF(ISNA(MATCH(A223,Aktiv!$A$6:$A$326,0)),"⚠ nicht im Modell","")
A224: 5209 | B224: Platte | C224: Doppeltür | D224: Doppeltür (980x1800) | E224: 980 | F224: 1800 | G224: =IFERROR(INDEX(Aktiv!$G$6:$G$326,MATCH(A224,Aktiv!$A$6:$A$326,0)),"") -> - | H224: =IFERROR(INDEX(Aktiv!$H$6:$H$326,MATCH(A224,Aktiv!$A$6:$A$326,0)),"") -> - | I224: =IFERROR(INDEX(Aktiv!$I$6:$I$326,MATCH(A224,Aktiv!$A$6:$A$326,0)),"") -> - | J224: =IFERROR(INDEX(Aktiv!$J$6:$J$326,MATCH(A224,Aktiv!$A$6:$A$326,0)),"") -> - | K224: =IFERROR(ROUND(G224*Steuerungsdaten!$B$5,0),"-") -> - | L224: =IFERROR(ROUND(H224*Steuerungsdaten!$B$5,0),"-") -> - | M224: =IFERROR(ROUND(I224*Steuerungsdaten!$B$5,0),"-") -> - | N224: =IFERROR(ROUND(J224*Steuerungsdaten!$B$5,0),"-") -> - | O224: =IF(ISNA(MATCH(A224,Aktiv!$A$6:$A$326,0)),"⚠ nicht im Modell","")
A225: 5300 | B225: Platte | C225: Schublade | D225: Schublade (420x180) | E225: 420 | F225: 180 | G225: =IFERROR(INDEX(Aktiv!$G$6:$G$326,MATCH(A225,Aktiv!$A$6:$A$326,0)),"") -> 299 | H225: =IFERROR(INDEX(Aktiv!$H$6:$H$326,MATCH(A225,Aktiv!$A$6:$A$326,0)),"") -> 355 | I225: =IFERROR(INDEX(Aktiv!$I$6:$I$326,MATCH(A225,Aktiv!$A$6:$A$326,0)),"") -> 386 | J225: =IFERROR(INDEX(Aktiv!$J$6:$J$326,MATCH(A225,Aktiv!$A$6:$A$326,0)),"") -> - | K225: =IFERROR(ROUND(G225*Steuerungsdaten!$B$5,0),"-") -> 344 | L225: =IFERROR(ROUND(H225*Steuerungsdaten!$B$5,0),"-") -> 408 | M225: =IFERROR(ROUND(I225*Steuerungsdaten!$B$5,0),"-") -> 444 | N225: =IFERROR(ROUND(J225*Steuerungsdaten!$B$5,0),"-") -> - | O225: =IF(ISNA(MATCH(A225,Aktiv!$A$6:$A$326,0)),"⚠ nicht im Modell","")
... A232: 5307 | B232: Platte | C232: Schublade | D232: Schublade (980x360) | E232: 980 | F232: 360 | G232: =IFERROR(INDEX(Aktiv!$G$6:$G$326,MATCH(A232,Aktiv!$A$6:$A$326,0)),"") -> 349 | H232: =IFERROR(INDEX(Aktiv!$H$6:$H$326,MATCH(A232,Aktiv!$A$6:$A$326,0)),"") -> 414 | I232: =IFERROR(INDEX(Aktiv!$I$6:$I$326,MATCH(A232,Aktiv!$A$6:$A$326,0)),"") -> 451 | J232: =IFERROR(INDEX(Aktiv!$J$6:$J$326,MATCH(A232,Aktiv!$A$6:$A$326,0)),"") -> - | K232: =IFERROR(ROUND(G232*Steuerungsdaten!$B$5,0),"-") -> 401 | L232: =IFERROR(ROUND(H232*Steuerungsdaten!$B$5,0),"-") -> 476 | M232: =IFERROR(ROUND(I232*Steuerungsdaten!$B$5,0),"-") -> 519 | N232: =IFERROR(ROUND(J232*Steuerungsdaten!$B$5,0),"-") -> - | O232: =IF(ISNA(MATCH(A232,Aktiv!$A$6:$A$326,0)),"⚠ nicht im Modell","")
A233: S_0044 | B233: Platte | C233: Schublade | D233: (780x180) | E233: 780 | F233: 180 | G233: =IFERROR(INDEX(Aktiv!$G$6:$G$326,MATCH(A233,Aktiv!$A$6:$A$326,0)),"") -> 318 | H233: =IFERROR(INDEX(Aktiv!$H$6:$H$326,MATCH(A233,Aktiv!$A$6:$A$326,0)),"") -> 378 | I233: =IFERROR(INDEX(Aktiv!$I$6:$I$326,MATCH(A233,Aktiv!$A$6:$A$326,0)),"") -> 411 | J233: =IFERROR(INDEX(Aktiv!$J$6:$J$326,MATCH(A233,Aktiv!$A$6:$A$326,0)),"") -> - | K233: =IFERROR(ROUND(G233*Steuerungsdaten!$B$5,0),"-") -> 366 | L233: =IFERROR(ROUND(H233*Steuerungsdaten!$B$5,0),"-") -> 435 | M233: =IFERROR(ROUND(I233*Steuerungsdaten!$B$5,0),"-") -> 473 | N233: =IFERROR(ROUND(J233*Steuerungsdaten!$B$5,0),"-") -> - | O233: =IF(ISNA(MATCH(A233,Aktiv!$A$6:$A$326,0)),"⚠ nicht im Modell","")
A234: S_0001 | B234: Platte | C234: Schublade | D234: Schublade (420x134) | E234: 420 | F234: 134 | G234: =IFERROR(INDEX(Aktiv!$G$6:$G$326,MATCH(A234,Aktiv!$A$6:$A$326,0)),"") -> - | H234: =IFERROR(INDEX(Aktiv!$H$6:$H$326,MATCH(A234,Aktiv!$A$6:$A$326,0)),"") -> - | I234: =IFERROR(INDEX(Aktiv!$I$6:$I$326,MATCH(A234,Aktiv!$A$6:$A$326,0)),"") -> - | J234: =IFERROR(INDEX(Aktiv!$J$6:$J$326,MATCH(A234,Aktiv!$A$6:$A$326,0)),"") -> - | K234: =IFERROR(ROUND(G234*Steuerungsdaten!$B$5,0),"-") -> - | L234: =IFERROR(ROUND(H234*Steuerungsdaten!$B$5,0),"-") -> - | M234: =IFERROR(ROUND(I234*Steuerungsdaten!$B$5,0),"-") -> - | N234: =IFERROR(ROUND(J234*Steuerungsdaten!$B$5,0),"-") -> - | O234: ⚠ Größe außerhalb Konfigurator-Standard
A235: S_0002 | B235: Platte | C235: Schublade | D235: Schublade (420x220) | E235: 420 | F235: 220 | G235: =IFERROR(INDEX(Aktiv!$G$6:$G$326,MATCH(A235,Aktiv!$A$6:$A$326,0)),"") -> - | H235: =IFERROR(INDEX(Aktiv!$H$6:$H$326,MATCH(A235,Aktiv!$A$6:$A$326,0)),"") -> - | I235: =IFERROR(INDEX(Aktiv!$I$6:$I$326,MATCH(A235,Aktiv!$A$6:$A$326,0)),"") -> - | J235: =IFERROR(INDEX(Aktiv!$J$6:$J$326,MATCH(A235,Aktiv!$A$6:$A$326,0)),"") -> - | K235: =IFERROR(ROUND(G235*Steuerungsdaten!$B$5,0),"-") -> - | L235: =IFERROR(ROUND(H235*Steuerungsdaten!$B$5,0),"-") -> - | M235: =IFERROR(ROUND(I235*Steuerungsdaten!$B$5,0),"-") -> - | N235: =IFERROR(ROUND(J235*Steuerungsdaten!$B$5,0),"-") -> - | O235: ⚠ Größe außerhalb Konfigurator-Standard
A236: S_0009 | B236: Platte | C236: Schublade | D236: Schublade (412x121) | E236: 412 | F236: 121 | G236: =IFERROR(INDEX(Aktiv!$G$6:$G$326,MATCH(A236,Aktiv!$A$6:$A$326,0)),"") -> - | H236: =IFERROR(INDEX(Aktiv!$H$6:$H$326,MATCH(A236,Aktiv!$A$6:$A$326,0)),"") -> - | I236: =IFERROR(INDEX(Aktiv!$I$6:$I$326,MATCH(A236,Aktiv!$A$6:$A$326,0)),"") -> - | J236: =IFERROR(INDEX(Aktiv!$J$6:$J$326,MATCH(A236,Aktiv!$A$6:$A$326,0)),"") -> - | K236: =IFERROR(ROUND(G236*Steuerungsdaten!$B$5,0),"-") -> - | L236: =IFERROR(ROUND(H236*Steuerungsdaten!$B$5,0),"-") -> - | M236: =IFERROR(ROUND(I236*Steuerungsdaten!$B$5,0),"-") -> - | N236: =IFERROR(ROUND(J236*Steuerungsdaten!$B$5,0),"-") -> - | O236: ⚠ Größe außerhalb Konfigurator-Standard
A237: S_0010 | B237: Platte | C237: Schublade | D237: Schublade (412x400) | E237: 412 | F237: 400 | G237: =IFERROR(INDEX(Aktiv!$G$6:$G$326,MATCH(A237,Aktiv!$A$6:$A$326,0)),"") -> - | H237: =IFERROR(INDEX(Aktiv!$H$6:$H$326,MATCH(A237,Aktiv!$A$6:$A$326,0)),"") -> - | I237: =IFERROR(INDEX(Aktiv!$I$6:$I$326,MATCH(A237,Aktiv!$A$6:$A$326,0)),"") -> - | J237: =IFERROR(INDEX(Aktiv!$J$6:$J$326,MATCH(A237,Aktiv!$A$6:$A$326,0)),"") -> - | K237: =IFERROR(ROUND(G237*Steuerungsdaten!$B$5,0),"-") -> - | L237: =IFERROR(ROUND(H237*Steuerungsdaten!$B$5,0),"-") -> - | M237: =IFERROR(ROUND(I237*Steuerungsdaten!$B$5,0),"-") -> - | N237: =IFERROR(ROUND(J237*Steuerungsdaten!$B$5,0),"-") -> - | O237: ⚠ Größe außerhalb Konfigurator-Standard
A238: S_0017 | B238: Platte | C238: Schublade | D238: Schublade (420x145) | E238: 420 | F238: 145 | G238: =IFERROR(INDEX(Aktiv!$G$6:$G$326,MATCH(A238,Aktiv!$A$6:$A$326,0)),"") -> - | H238: =IFERROR(INDEX(Aktiv!$H$6:$H$326,MATCH(A238,Aktiv!$A$6:$A$326,0)),"") -> - | I238: =IFERROR(INDEX(Aktiv!$I$6:$I$326,MATCH(A238,Aktiv!$A$6:$A$326,0)),"") -> - | J238: =IFERROR(INDEX(Aktiv!$J$6:$J$326,MATCH(A238,Aktiv!$A$6:$A$326,0)),"") -> - | K238: =IFERROR(ROUND(G238*Steuerungsdaten!$B$5,0),"-") -> - | L238: =IFERROR(ROUND(H238*Steuerungsdaten!$B$5,0),"-") -> - | M238: =IFERROR(ROUND(I238*Steuerungsdaten!$B$5,0),"-") -> - | N238: =IFERROR(ROUND(J238*Steuerungsdaten!$B$5,0),"-") -> - | O238: ⚠ Größe außerhalb Konfigurator-Standard
A239: S_0018 | B239: Platte | C239: Schublade | D239: Schublade (420x293) | E239: 420 | F239: 293 | G239: =IFERROR(INDEX(Aktiv!$G$6:$G$326,MATCH(A239,Aktiv!$A$6:$A$326,0)),"") -> - | H239: =IFERROR(INDEX(Aktiv!$H$6:$H$326,MATCH(A239,Aktiv!$A$6:$A$326,0)),"") -> - | I239: =IFERROR(INDEX(Aktiv!$I$6:$I$326,MATCH(A239,Aktiv!$A$6:$A$326,0)),"") -> - | J239: =IFERROR(INDEX(Aktiv!$J$6:$J$326,MATCH(A239,Aktiv!$A$6:$A$326,0)),"") -> - | K239: =IFERROR(ROUND(G239*Steuerungsdaten!$B$5,0),"-") -> - | L239: =IFERROR(ROUND(H239*Steuerungsdaten!$B$5,0),"-") -> - | M239: =IFERROR(ROUND(I239*Steuerungsdaten!$B$5,0),"-") -> - | N239: =IFERROR(ROUND(J239*Steuerungsdaten!$B$5,0),"-") -> - | O239: ⚠ Größe außerhalb Konfigurator-Standard
A240: S_0029 | B240: Platte | C240: Schublade | D240: Schublade (420x67) | E240: 420 | F240: 67 | G240: =IFERROR(INDEX(Aktiv!$G$6:$G$326,MATCH(A240,Aktiv!$A$6:$A$326,0)),"") -> - | H240: =IFERROR(INDEX(Aktiv!$H$6:$H$326,MATCH(A240,Aktiv!$A$6:$A$326,0)),"") -> - | I240: =IFERROR(INDEX(Aktiv!$I$6:$I$326,MATCH(A240,Aktiv!$A$6:$A$326,0)),"") -> - | J240: =IFERROR(INDEX(Aktiv!$J$6:$J$326,MATCH(A240,Aktiv!$A$6:$A$326,0)),"") -> - | K240: =IFERROR(ROUND(G240*Steuerungsdaten!$B$5,0),"-") -> - | L240: =IFERROR(ROUND(H240*Steuerungsdaten!$B$5,0),"-") -> - | M240: =IFERROR(ROUND(I240*Steuerungsdaten!$B$5,0),"-") -> - | N240: =IFERROR(ROUND(J240*Steuerungsdaten!$B$5,0),"-") -> - | O240: ⚠ Größe außerhalb Konfigurator-Standard
A241: S_0033 | B241: Platte | C241: Schublade | D241: Schublade (420x142) | E241: 420 | F241: 142 | G241: =IFERROR(INDEX(Aktiv!$G$6:$G$326,MATCH(A241,Aktiv!$A$6:$A$326,0)),"") -> - | H241: =IFERROR(INDEX(Aktiv!$H$6:$H$326,MATCH(A241,Aktiv!$A$6:$A$326,0)),"") -> - | I241: =IFERROR(INDEX(Aktiv!$I$6:$I$326,MATCH(A241,Aktiv!$A$6:$A$326,0)),"") -> - | J241: =IFERROR(INDEX(Aktiv!$J$6:$J$326,MATCH(A241,Aktiv!$A$6:$A$326,0)),"") -> - | K241: =IFERROR(ROUND(G241*Steuerungsdaten!$B$5,0),"-") -> - | L241: =IFERROR(ROUND(H241*Steuerungsdaten!$B$5,0),"-") -> - | M241: =IFERROR(ROUND(I241*Steuerungsdaten!$B$5,0),"-") -> - | N241: =IFERROR(ROUND(J241*Steuerungsdaten!$B$5,0),"-") -> - | O241: ⚠ Größe außerhalb Konfigurator-Standard
A242: S_0034 | B242: Platte | C242: Schublade | D242: Schublade (420x280) | E242: 420 | F242: 280 | G242: =IFERROR(INDEX(Aktiv!$G$6:$G$326,MATCH(A242,Aktiv!$A$6:$A$326,0)),"") -> - | H242: =IFERROR(INDEX(Aktiv!$H$6:$H$326,MATCH(A242,Aktiv!$A$6:$A$326,0)),"") -> - | I242: =IFERROR(INDEX(Aktiv!$I$6:$I$326,MATCH(A242,Aktiv!$A$6:$A$326,0)),"") -> - | J242: =IFERROR(INDEX(Aktiv!$J$6:$J$326,MATCH(A242,Aktiv!$A$6:$A$326,0)),"") -> - | K242: =IFERROR(ROUND(G242*Steuerungsdaten!$B$5,0),"-") -> - | L242: =IFERROR(ROUND(H242*Steuerungsdaten!$B$5,0),"-") -> - | M242: =IFERROR(ROUND(I242*Steuerungsdaten!$B$5,0),"-") -> - | N242: =IFERROR(ROUND(J242*Steuerungsdaten!$B$5,0),"-") -> - | O242: ⚠ Größe außerhalb Konfigurator-Standard
A243: S_0037 | B243: Platte | C243: Schublade | D243: Schublade (420x141) | E243: 420 | F243: 141 | G243: =IFERROR(INDEX(Aktiv!$G$6:$G$326,MATCH(A243,Aktiv!$A$6:$A$326,0)),"") -> - | H243: =IFERROR(INDEX(Aktiv!$H$6:$H$326,MATCH(A243,Aktiv!$A$6:$A$326,0)),"") -> - | I243: =IFERROR(INDEX(Aktiv!$I$6:$I$326,MATCH(A243,Aktiv!$A$6:$A$326,0)),"") -> - | J243: =IFERROR(INDEX(Aktiv!$J$6:$J$326,MATCH(A243,Aktiv!$A$6:$A$326,0)),"") -> - | K243: =IFERROR(ROUND(G243*Steuerungsdaten!$B$5,0),"-") -> - | L243: =IFERROR(ROUND(H243*Steuerungsdaten!$B$5,0),"-") -> - | M243: =IFERROR(ROUND(I243*Steuerungsdaten!$B$5,0),"-") -> - | N243: =IFERROR(ROUND(J243*Steuerungsdaten!$B$5,0),"-") -> - | O243: ⚠ Größe außerhalb Konfigurator-Standard
A244: 5400 | B244: Platte | C244: Schublade LB 1 | D244: Schublade LB 1 (420x180) | E244: 420 | F244: 180 | G244: =IFERROR(INDEX(Aktiv!$G$6:$G$326,MATCH(A244,Aktiv!$A$6:$A$326,0)),"") -> 299 | H244: =IFERROR(INDEX(Aktiv!$H$6:$H$326,MATCH(A244,Aktiv!$A$6:$A$326,0)),"") -> 355 | I244: =IFERROR(INDEX(Aktiv!$I$6:$I$326,MATCH(A244,Aktiv!$A$6:$A$326,0)),"") -> 386 | J244: =IFERROR(INDEX(Aktiv!$J$6:$J$326,MATCH(A244,Aktiv!$A$6:$A$326,0)),"") -> - | K244: =IFERROR(ROUND(G244*Steuerungsdaten!$B$5,0),"-") -> 344 | L244: =IFERROR(ROUND(H244*Steuerungsdaten!$B$5,0),"-") -> 408 | M244: =IFERROR(ROUND(I244*Steuerungsdaten!$B$5,0),"-") -> 444 | N244: =IFERROR(ROUND(J244*Steuerungsdaten!$B$5,0),"-") -> - | O244: =IF(ISNA(MATCH(A244,Aktiv!$A$6:$A$326,0)),"⚠ nicht im Modell","")
A245: 5401 | B245: Platte | C245: Schublade LB 1 | D245: Schublade LB 1 (420x360) | E245: 420 | F245: 360 | G245: =IFERROR(INDEX(Aktiv!$G$6:$G$326,MATCH(A245,Aktiv!$A$6:$A$326,0)),"") -> 320 | H245: =IFERROR(INDEX(Aktiv!$H$6:$H$326,MATCH(A245,Aktiv!$A$6:$A$326,0)),"") -> 381 | I245: =IFERROR(INDEX(Aktiv!$I$6:$I$326,MATCH(A245,Aktiv!$A$6:$A$326,0)),"") -> 414 | J245: =IFERROR(INDEX(Aktiv!$J$6:$J$326,MATCH(A245,Aktiv!$A$6:$A$326,0)),"") -> - | K245: =IFERROR(ROUND(G245*Steuerungsdaten!$B$5,0),"-") -> 368 | L245: =IFERROR(ROUND(H245*Steuerungsdaten!$B$5,0),"-") -> 438 | M245: =IFERROR(ROUND(I245*Steuerungsdaten!$B$5,0),"-") -> 476 | N245: =IFERROR(ROUND(J245*Steuerungsdaten!$B$5,0),"-") -> - | O245: =IF(ISNA(MATCH(A245,Aktiv!$A$6:$A$326,0)),"⚠ nicht im Modell","")
A246: 5402 | B246: Platte | C246: Schublade LB 1 | D246: Schublade LB 1 (580x180) | E246: 580 | F246: 180 | G246: =IFERROR(INDEX(Aktiv!$G$6:$G$326,MATCH(A246,Aktiv!$A$6:$A$326,0)),"") -> 309 | H246: =IFERROR(INDEX(Aktiv!$H$6:$H$326,MATCH(A246,Aktiv!$A$6:$A$326,0)),"") -> 367 | I246: =IFERROR(INDEX(Aktiv!$I$6:$I$326,MATCH(A246,Aktiv!$A$6:$A$326,0)),"") -> 399 | J246: =IFERROR(INDEX(Aktiv!$J$6:$J$326,MATCH(A246,Aktiv!$A$6:$A$326,0)),"") -> - | K246: =IFERROR(ROUND(G246*Steuerungsdaten!$B$5,0),"-") -> 355 | L246: =IFERROR(ROUND(H246*Steuerungsdaten!$B$5,0),"-") -> 422 | M246: =IFERROR(ROUND(I246*Steuerungsdaten!$B$5,0),"-") -> 459 | N246: =IFERROR(ROUND(J246*Steuerungsdaten!$B$5,0),"-") -> - | O246: =IF(ISNA(MATCH(A246,Aktiv!$A$6:$A$326,0)),"⚠ nicht im Modell","")
A247: 5403 | B247: Platte | C247: Schublade LB 1 | D247: Schublade LB 1 (580x360) | E247: 580 | F247: 360 | G247: =IFERROR(INDEX(Aktiv!$G$6:$G$326,MATCH(A247,Aktiv!$A$6:$A$326,0)),"") -> 331 | H247: =IFERROR(INDEX(Aktiv!$H$6:$H$326,MATCH(A247,Aktiv!$A$6:$A$326,0)),"") -> 393 | I247: =IFERROR(INDEX(Aktiv!$I$6:$I$326,MATCH(A247,Aktiv!$A$6:$A$326,0)),"") -> 428 | J247: =IFERROR(INDEX(Aktiv!$J$6:$J$326,MATCH(A247,Aktiv!$A$6:$A$326,0)),"") -> - | K247: =IFERROR(ROUND(G247*Steuerungsdaten!$B$5,0),"-") -> 381 | L247: =IFERROR(ROUND(H247*Steuerungsdaten!$B$5,0),"-") -> 452 | M247: =IFERROR(ROUND(I247*Steuerungsdaten!$B$5,0),"-") -> 492 | N247: =IFERROR(ROUND(J247*Steuerungsdaten!$B$5,0),"-") -> - | O247: =IF(ISNA(MATCH(A247,Aktiv!$A$6:$A$326,0)),"⚠ nicht im Modell","")
A248: 5404 | B248: Platte | C248: Schublade LB 1 | D248: Schublade LB 1 (780x180) | E248: 780 | F248: 180 | G248: =IFERROR(INDEX(Aktiv!$G$6:$G$326,MATCH(A248,Aktiv!$A$6:$A$326,0)),"") -> 318 | H248: =IFERROR(INDEX(Aktiv!$H$6:$H$326,MATCH(A248,Aktiv!$A$6:$A$326,0)),"") -> 378 | I248: =IFERROR(INDEX(Aktiv!$I$6:$I$326,MATCH(A248,Aktiv!$A$6:$A$326,0)),"") -> 411 | J248: =IFERROR(INDEX(Aktiv!$J$6:$J$326,MATCH(A248,Aktiv!$A$6:$A$326,0)),"") -> - | K248: =IFERROR(ROUND(G248*Steuerungsdaten!$B$5,0),"-") -> 366 | L248: =IFERROR(ROUND(H248*Steuerungsdaten!$B$5,0),"-") -> 435 | M248: =IFERROR(ROUND(I248*Steuerungsdaten!$B$5,0),"-") -> 473 | N248: =IFERROR(ROUND(J248*Steuerungsdaten!$B$5,0),"-") -> - | O248: =IF(ISNA(MATCH(A248,Aktiv!$A$6:$A$326,0)),"⚠ nicht im Modell","")
A249: 5405 | B249: Platte | C249: Schublade LB 1 | D249: Schublade LB 1 (780x360) | E249: 780 | F249: 360 | G249: =IFERROR(INDEX(Aktiv!$G$6:$G$326,MATCH(A249,Aktiv!$A$6:$A$326,0)),"") -> 341 | H249: =IFERROR(INDEX(Aktiv!$H$6:$H$326,MATCH(A249,Aktiv!$A$6:$A$326,0)),"") -> 405 | I249: =IFERROR(INDEX(Aktiv!$I$6:$I$326,MATCH(A249,Aktiv!$A$6:$A$326,0)),"") -> 441 | J249: =IFERROR(INDEX(Aktiv!$J$6:$J$326,MATCH(A249,Aktiv!$A$6:$A$326,0)),"") -> - | K249: =IFERROR(ROUND(G249*Steuerungsdaten!$B$5,0),"-") -> 392 | L249: =IFERROR(ROUND(H249*Steuerungsdaten!$B$5,0),"-") -> 466 | M249: =IFERROR(ROUND(I249*Steuerungsdaten!$B$5,0),"-") -> 507 | N249: =IFERROR(ROUND(J249*Steuerungsdaten!$B$5,0),"-") -> - | O249: =IF(ISNA(MATCH(A249,Aktiv!$A$6:$A$326,0)),"⚠ nicht im Modell","")
A250: 5406 | B250: Platte | C250: Schublade LB 1 | D250: Schublade LB 1 (980x180) | E250: 980 | F250: 180 | G250: =IFERROR(INDEX(Aktiv!$G$6:$G$326,MATCH(A250,Aktiv!$A$6:$A$326,0)),"") -> 325 | H250: =IFERROR(INDEX(Aktiv!$H$6:$H$326,MATCH(A250,Aktiv!$A$6:$A$326,0)),"") -> 386 | I250: =IFERROR(INDEX(Aktiv!$I$6:$I$326,MATCH(A250,Aktiv!$A$6:$A$326,0)),"") -> 421 | J250: =IFERROR(INDEX(Aktiv!$J$6:$J$326,MATCH(A250,Aktiv!$A$6:$A$326,0)),"") -> - | K250: =IFERROR(ROUND(G250*Steuerungsdaten!$B$5,0),"-") -> 374 | L250: =IFERROR(ROUND(H250*Steuerungsdaten!$B$5,0),"-") -> 444 | M250: =IFERROR(ROUND(I250*Steuerungsdaten!$B$5,0),"-") -> 484 | N250: =IFERROR(ROUND(J250*Steuerungsdaten!$B$5,0),"-") -> - | O250: =IF(ISNA(MATCH(A250,Aktiv!$A$6:$A$326,0)),"⚠ nicht im Modell","")
A251: 5407 | B251: Platte | C251: Schublade LB 1 | D251: Schublade LB 1 (980x360) | E251: 980 | F251: 360 | G251: =IFERROR(INDEX(Aktiv!$G$6:$G$326,MATCH(A251,Aktiv!$A$6:$A$326,0)),"") -> 349 | H251: =IFERROR(INDEX(Aktiv!$H$6:$H$326,MATCH(A251,Aktiv!$A$6:$A$326,0)),"") -> 414 | I251: =IFERROR(INDEX(Aktiv!$I$6:$I$326,MATCH(A251,Aktiv!$A$6:$A$326,0)),"") -> 451 | J251: =IFERROR(INDEX(Aktiv!$J$6:$J$326,MATCH(A251,Aktiv!$A$6:$A$326,0)),"") -> - | K251: =IFERROR(ROUND(G251*Steuerungsdaten!$B$5,0),"-") -> 401 | L251: =IFERROR(ROUND(H251*Steuerungsdaten!$B$5,0),"-") -> 476 | M251: =IFERROR(ROUND(I251*Steuerungsdaten!$B$5,0),"-") -> 519 | N251: =IFERROR(ROUND(J251*Steuerungsdaten!$B$5,0),"-") -> - | O251: =IF(ISNA(MATCH(A251,Aktiv!$A$6:$A$326,0)),"⚠ nicht im Modell","")
A252: 5500 | B252: Platte | C252: Schublade LB 2 | D252: Schublade LB 2 (420x180) | E252: 420 | F252: 180 | G252: =IFERROR(INDEX(Aktiv!$G$6:$G$326,MATCH(A252,Aktiv!$A$6:$A$326,0)),"") -> 299 | H252: =IFERROR(INDEX(Aktiv!$H$6:$H$326,MATCH(A252,Aktiv!$A$6:$A$326,0)),"") -> 355 | I252: =IFERROR(INDEX(Aktiv!$I$6:$I$326,MATCH(A252,Aktiv!$A$6:$A$326,0)),"") -> 386 | J252: =IFERROR(INDEX(Aktiv!$J$6:$J$326,MATCH(A252,Aktiv!$A$6:$A$326,0)),"") -> - | K252: =IFERROR(ROUND(G252*Steuerungsdaten!$B$5,0),"-") -> 344 | L252: =IFERROR(ROUND(H252*Steuerungsdaten!$B$5,0),"-") -> 408 | M252: =IFERROR(ROUND(I252*Steuerungsdaten!$B$5,0),"-") -> 444 | N252: =IFERROR(ROUND(J252*Steuerungsdaten!$B$5,0),"-") -> - | O252: =IF(ISNA(MATCH(A252,Aktiv!$A$6:$A$326,0)),"⚠ nicht im Modell","")
A253: 5501 | B253: Platte | C253: Schublade LB 2 | D253: Schublade LB 2 (420x360) | E253: 420 | F253: 360 | G253: =IFERROR(INDEX(Aktiv!$G$6:$G$326,MATCH(A253,Aktiv!$A$6:$A$326,0)),"") -> 320 | H253: =IFERROR(INDEX(Aktiv!$H$6:$H$326,MATCH(A253,Aktiv!$A$6:$A$326,0)),"") -> 381 | I253: =IFERROR(INDEX(Aktiv!$I$6:$I$326,MATCH(A253,Aktiv!$A$6:$A$326,0)),"") -> 414 | J253: =IFERROR(INDEX(Aktiv!$J$6:$J$326,MATCH(A253,Aktiv!$A$6:$A$326,0)),"") -> - | K253: =IFERROR(ROUND(G253*Steuerungsdaten!$B$5,0),"-") -> 368 | L253: =IFERROR(ROUND(H253*Steuerungsdaten!$B$5,0),"-") -> 438 | M253: =IFERROR(ROUND(I253*Steuerungsdaten!$B$5,0),"-") -> 476 | N253: =IFERROR(ROUND(J253*Steuerungsdaten!$B$5,0),"-") -> - | O253: =IF(ISNA(MATCH(A253,Aktiv!$A$6:$A$326,0)),"⚠ nicht im Modell","")
A254: 5502 | B254: Platte | C254: Schublade LB 2 | D254: Schublade LB 2 (580x180) | E254: 580 | F254: 180 | G254: =IFERROR(INDEX(Aktiv!$G$6:$G$326,MATCH(A254,Aktiv!$A$6:$A$326,0)),"") -> 309 | H254: =IFERROR(INDEX(Aktiv!$H$6:$H$326,MATCH(A254,Aktiv!$A$6:$A$326,0)),"") -> 367 | I254: =IFERROR(INDEX(Aktiv!$I$6:$I$326,MATCH(A254,Aktiv!$A$6:$A$326,0)),"") -> 399 | J254: =IFERROR(INDEX(Aktiv!$J$6:$J$326,MATCH(A254,Aktiv!$A$6:$A$326,0)),"") -> - | K254: =IFERROR(ROUND(G254*Steuerungsdaten!$B$5,0),"-") -> 355 | L254: =IFERROR(ROUND(H254*Steuerungsdaten!$B$5,0),"-") -> 422 | M254: =IFERROR(ROUND(I254*Steuerungsdaten!$B$5,0),"-") -> 459 | N254: =IFERROR(ROUND(J254*Steuerungsdaten!$B$5,0),"-") -> - | O254: =IF(ISNA(MATCH(A254,Aktiv!$A$6:$A$326,0)),"⚠ nicht im Modell","")
A255: 5503 | B255: Platte | C255: Schublade LB 2 | D255: Schublade LB 2 (580x360) | E255: 580 | F255: 360 | G255: =IFERROR(INDEX(Aktiv!$G$6:$G$326,MATCH(A255,Aktiv!$A$6:$A$326,0)),"") -> 331 | H255: =IFERROR(INDEX(Aktiv!$H$6:$H$326,MATCH(A255,Aktiv!$A$6:$A$326,0)),"") -> 393 | I255: =IFERROR(INDEX(Aktiv!$I$6:$I$326,MATCH(A255,Aktiv!$A$6:$A$326,0)),"") -> 428 | J255: =IFERROR(INDEX(Aktiv!$J$6:$J$326,MATCH(A255,Aktiv!$A$6:$A$326,0)),"") -> - | K255: =IFERROR(ROUND(G255*Steuerungsdaten!$B$5,0),"-") -> 381 | L255: =IFERROR(ROUND(H255*Steuerungsdaten!$B$5,0),"-") -> 452 | M255: =IFERROR(ROUND(I255*Steuerungsdaten!$B$5,0),"-") -> 492 | N255: =IFERROR(ROUND(J255*Steuerungsdaten!$B$5,0),"-") -> - | O255: =IF(ISNA(MATCH(A255,Aktiv!$A$6:$A$326,0)),"⚠ nicht im Modell","")
... A259: 5507 | B259: Platte | C259: Schublade LB 2 | D259: Schublade LB 2 (980x360) | E259: 980 | F259: 360 | G259: =IFERROR(INDEX(Aktiv!$G$6:$G$326,MATCH(A259,Aktiv!$A$6:$A$326,0)),"") -> 349 | H259: =IFERROR(INDEX(Aktiv!$H$6:$H$326,MATCH(A259,Aktiv!$A$6:$A$326,0)),"") -> 414 | I259: =IFERROR(INDEX(Aktiv!$I$6:$I$326,MATCH(A259,Aktiv!$A$6:$A$326,0)),"") -> 451 | J259: =IFERROR(INDEX(Aktiv!$J$6:$J$326,MATCH(A259,Aktiv!$A$6:$A$326,0)),"") -> - | K259: =IFERROR(ROUND(G259*Steuerungsdaten!$B$5,0),"-") -> 401 | L259: =IFERROR(ROUND(H259*Steuerungsdaten!$B$5,0),"-") -> 476 | M259: =IFERROR(ROUND(I259*Steuerungsdaten!$B$5,0),"-") -> 519 | N259: =IFERROR(ROUND(J259*Steuerungsdaten!$B$5,0),"-") -> - | O259: =IF(ISNA(MATCH(A259,Aktiv!$A$6:$A$326,0)),"⚠ nicht im Modell","")
A260: 1000 | B260: Zubehör | C260: Würfel | D260: Würfel 30mm | G260: =IFERROR(INDEX(Aktiv!$G$6:$G$326,MATCH(A260,Aktiv!$A$6:$A$326,0)),"") -> 6 | H260: =IFERROR(INDEX(Aktiv!$H$6:$H$326,MATCH(A260,Aktiv!$A$6:$A$326,0)),"") -> 6 | I260: =IFERROR(INDEX(Aktiv!$I$6:$I$326,MATCH(A260,Aktiv!$A$6:$A$326,0)),"") -> 6 | J260: =IFERROR(INDEX(Aktiv!$J$6:$J$326,MATCH(A260,Aktiv!$A$6:$A$326,0)),"") -> 6 | K260: =IFERROR(ROUND(G260*Steuerungsdaten!$B$5,0),"-") -> 7 | L260: =IFERROR(ROUND(H260*Steuerungsdaten!$B$5,0),"-") -> 7 | M260: =IFERROR(ROUND(I260*Steuerungsdaten!$B$5,0),"-") -> 7 | N260: =IFERROR(ROUND(J260*Steuerungsdaten!$B$5,0),"-") -> 7 | O260: =IF(ISNA(MATCH(A260,Aktiv!$A$6:$A$326,0)),"⚠ nicht im Modell","")
A261: 1001 | B261: Zubehör | C261: Würfel | D261: Würfel 30mm 1/2 | G261: =IFERROR(INDEX(Aktiv!$G$6:$G$326,MATCH(A261,Aktiv!$A$6:$A$326,0)),"") -> 6 | H261: =IFERROR(INDEX(Aktiv!$H$6:$H$326,MATCH(A261,Aktiv!$A$6:$A$326,0)),"") -> 6 | I261: =IFERROR(INDEX(Aktiv!$I$6:$I$326,MATCH(A261,Aktiv!$A$6:$A$326,0)),"") -> 6 | J261: =IFERROR(INDEX(Aktiv!$J$6:$J$326,MATCH(A261,Aktiv!$A$6:$A$326,0)),"") -> 6 | K261: =IFERROR(ROUND(G261*Steuerungsdaten!$B$5,0),"-") -> 7 | L261: =IFERROR(ROUND(H261*Steuerungsdaten!$B$5,0),"-") -> 7 | M261: =IFERROR(ROUND(I261*Steuerungsdaten!$B$5,0),"-") -> 7 | N261: =IFERROR(ROUND(J261*Steuerungsdaten!$B$5,0),"-") -> 7 | O261: =IF(ISNA(MATCH(A261,Aktiv!$A$6:$A$326,0)),"⚠ nicht im Modell","")
A262: 1002 | B262: Zubehör | C262: Würfel | D262: Würfel 30mm 3/4 | G262: =IFERROR(INDEX(Aktiv!$G$6:$G$326,MATCH(A262,Aktiv!$A$6:$A$326,0)),"") -> 6 | H262: =IFERROR(INDEX(Aktiv!$H$6:$H$326,MATCH(A262,Aktiv!$A$6:$A$326,0)),"") -> 6 | I262: =IFERROR(INDEX(Aktiv!$I$6:$I$326,MATCH(A262,Aktiv!$A$6:$A$326,0)),"") -> 6 | J262: =IFERROR(INDEX(Aktiv!$J$6:$J$326,MATCH(A262,Aktiv!$A$6:$A$326,0)),"") -> 6 | K262: =IFERROR(ROUND(G262*Steuerungsdaten!$B$5,0),"-") -> 7 | L262: =IFERROR(ROUND(H262*Steuerungsdaten!$B$5,0),"-") -> 7 | M262: =IFERROR(ROUND(I262*Steuerungsdaten!$B$5,0),"-") -> 7 | N262: =IFERROR(ROUND(J262*Steuerungsdaten!$B$5,0),"-") -> 7 | O262: =IF(ISNA(MATCH(A262,Aktiv!$A$6:$A$326,0)),"⚠ nicht im Modell","")
A263: 1100 | B263: Zubehör | C263: Würfel | D263: Würfel 46mm | G263: =IFERROR(INDEX(Aktiv!$G$6:$G$326,MATCH(A263,Aktiv!$A$6:$A$326,0)),"") -> 6 | H263: =IFERROR(INDEX(Aktiv!$H$6:$H$326,MATCH(A263,Aktiv!$A$6:$A$326,0)),"") -> 6 | I263: =IFERROR(INDEX(Aktiv!$I$6:$I$326,MATCH(A263,Aktiv!$A$6:$A$326,0)),"") -> 6 | J263: =IFERROR(INDEX(Aktiv!$J$6:$J$326,MATCH(A263,Aktiv!$A$6:$A$326,0)),"") -> 6 | K263: =IFERROR(ROUND(G263*Steuerungsdaten!$B$5,0),"-") -> 7 | L263: =IFERROR(ROUND(H263*Steuerungsdaten!$B$5,0),"-") -> 7 | M263: =IFERROR(ROUND(I263*Steuerungsdaten!$B$5,0),"-") -> 7 | N263: =IFERROR(ROUND(J263*Steuerungsdaten!$B$5,0),"-") -> 7 | O263: =IF(ISNA(MATCH(A263,Aktiv!$A$6:$A$326,0)),"⚠ nicht im Modell","")
A264: 1101 | B264: Zubehör | C264: Würfel | D264: Würfel 46mm 1/2 | G264: =IFERROR(INDEX(Aktiv!$G$6:$G$326,MATCH(A264,Aktiv!$A$6:$A$326,0)),"") -> 6 | H264: =IFERROR(INDEX(Aktiv!$H$6:$H$326,MATCH(A264,Aktiv!$A$6:$A$326,0)),"") -> 6 | I264: =IFERROR(INDEX(Aktiv!$I$6:$I$326,MATCH(A264,Aktiv!$A$6:$A$326,0)),"") -> 6 | J264: =IFERROR(INDEX(Aktiv!$J$6:$J$326,MATCH(A264,Aktiv!$A$6:$A$326,0)),"") -> 6 | K264: =IFERROR(ROUND(G264*Steuerungsdaten!$B$5,0),"-") -> 7 | L264: =IFERROR(ROUND(H264*Steuerungsdaten!$B$5,0),"-") -> 7 | M264: =IFERROR(ROUND(I264*Steuerungsdaten!$B$5,0),"-") -> 7 | N264: =IFERROR(ROUND(J264*Steuerungsdaten!$B$5,0),"-") -> 7 | O264: =IF(ISNA(MATCH(A264,Aktiv!$A$6:$A$326,0)),"⚠ nicht im Modell","")
A265: 1102 | B265: Zubehör | C265: Würfel | D265: Würfel 46mm 3/4 | G265: =IFERROR(INDEX(Aktiv!$G$6:$G$326,MATCH(A265,Aktiv!$A$6:$A$326,0)),"") -> 6 | H265: =IFERROR(INDEX(Aktiv!$H$6:$H$326,MATCH(A265,Aktiv!$A$6:$A$326,0)),"") -> 6 | I265: =IFERROR(INDEX(Aktiv!$I$6:$I$326,MATCH(A265,Aktiv!$A$6:$A$326,0)),"") -> 6 | J265: =IFERROR(INDEX(Aktiv!$J$6:$J$326,MATCH(A265,Aktiv!$A$6:$A$326,0)),"") -> 6 | K265: =IFERROR(ROUND(G265*Steuerungsdaten!$B$5,0),"-") -> 7 | L265: =IFERROR(ROUND(H265*Steuerungsdaten!$B$5,0),"-") -> 7 | M265: =IFERROR(ROUND(I265*Steuerungsdaten!$B$5,0),"-") -> 7 | N265: =IFERROR(ROUND(J265*Steuerungsdaten!$B$5,0),"-") -> 7 | O265: =IF(ISNA(MATCH(A265,Aktiv!$A$6:$A$326,0)),"⚠ nicht im Modell","")
...

Sheet Aktiv
A1: ARTMODUL Preisliste – EUR & CHF
A2: Alle Preise exkl. MwSt. | EUR = Euro | CHF = Schweizer Franken | '-' = nicht verfügbar
A3: Artikel | G3: Preis in EUR (exkl. MwSt.) | K3: Preis in CHF (exkl. MwSt.)
A4: Art.-Nr. | B4: Typ | C4: Kategorie | D4: Bezeichnung | E4: Breite (mm) | F4: Tiefe (mm) | G4: PG 1 EUR | H4: PG 2 EUR | I4: PG 3 EUR | J4: PG 4 EUR | K4: PG 1 CHF | L4: PG 2 CHF | M4: PG 3 CHF | N4: PG 4 CHF | O4: PG1_Basis | P4: PG2_Basis ℹ | Q4: PG3_Basis ℹ | R4: PG4_Basis ℹ
A5: Boden
A6: 3000 | B6: Platte | C6: Boden | D6: Boden (360x360) | E6: 360 | F6: 360 | G6: =IF(VLOOKUP(C6,Steuerungsdaten!$P$17:$T$39,2,0)="","",MAX(ROUND(VLOOKUP(C6,Steuerungsdaten!$P$17:$T$39,2,0)*Steuerungsdaten!$B$4*Steuerungsdaten!$B$7*IFERROR(VLOOKUP(C6,Steuerungsdaten!$B$17:$C$37,2,FALSE),1)*POWER(IF(OR(E6=0,F6=0,E6="",F6=""),1,(E6*F6/1000000)/Steuerungsdaten!$B$6),IFERROR(VLOOKUP(C6,Steuerungsdaten!$B$17:$K$37,10,FALSE),1)-1),0),Steuerungsdaten!$E$4)) -> 25 | H6: =IF(VLOOKUP(C6,Steuerungsdaten!$P$17:$T$39,3,0)="","",MAX(ROUND(VLOOKUP(C6,Steuerungsdaten!$P$17:$T$39,3,0)*Steuerungsdaten!$B$4*Steuerungsdaten!$B$8*IFERROR(VLOOKUP(C6,Steuerungsdaten!$B$17:$E$37,4,FALSE),1)*POWER(IF(OR(E6=0,F6=0,E6="",F6=""),1,(E6*F6/1000000)/Steuerungsdaten!$B$6),IFERROR(VLOOKUP(C6,Steuerungsdaten!$B$17:$L$37,11,FALSE),1)-1),0),Steuerungsdaten!$E$5)) -> 103 | I6: =IF(VLOOKUP(C6,Steuerungsdaten!$P$17:$T$39,4,0)="","",MAX(ROUND(VLOOKUP(C6,Steuerungsdaten!$P$17:$T$39,4,0)*Steuerungsdaten!$B$4*Steuerungsdaten!$B$9*IFERROR(VLOOKUP(C6,Steuerungsdaten!$B$17:$G$37,6,FALSE),1)*POWER(IF(OR(E6=0,F6=0,E6="",F6=""),1,(E6*F6/1000000)/Steuerungsdaten!$B$6),IFERROR(VLOOKUP(C6,Steuerungsdaten!$B$17:$M$37,12,FALSE),1)-1),0),Steuerungsdaten!$E$6)) -> 120 | J6: =IF(VLOOKUP(C6,Steuerungsdaten!$P$17:$T$39,5,0)="","",MAX(ROUND(VLOOKUP(C6,Steuerungsdaten!$P$17:$T$39,5,0)*Steuerungsdaten!$B$4*Steuerungsdaten!$B$10*IFERROR(VLOOKUP(C6,Steuerungsdaten!$B$17:$I$37,8,FALSE),1)*POWER(IF(OR(E6=0,F6=0,E6="",F6=""),1,(E6*F6/1000000)/Steuerungsdaten!$B$6),IFERROR(VLOOKUP(C6,Steuerungsdaten!$B$17:$N$37,13,FALSE),1)-1),0),Steuerungsdaten!$E$7)) -> 145 | K6: =IF(G6="","",ROUND(G6*Steuerungsdaten!$B$5,0)) -> 29 | L6: =IF(H6="","",ROUND(H6*Steuerungsdaten!$B$5,0)) -> 118 | M6: =IF(I6="","",ROUND(I6*Steuerungsdaten!$B$5,0)) -> 138 | N6: =IF(J6="","",ROUND(J6*Steuerungsdaten!$B$5,0)) -> 167 | O6: 34 | P6: =IF(H6="","",ROUND(H6/(Steuerungsdaten!$B$4*Steuerungsdaten!$B$8*IFERROR(VLOOKUP(C6,Steuerungsdaten!$B$17:$E$37,4,FALSE),1)*POWER(IF(OR(E6=0,F6=0,E6="",F6=""),1,(E6*F6/1000000)/Steuerungsdaten!$B$6),IFERROR(VLOOKUP(C6,Steuerungsdaten!$B$17:$L$37,11,FALSE),1)-1)),0)) -> 316 | Q6: =IF(I6="","",ROUND(I6/(Steuerungsdaten!$B$4*Steuerungsdaten!$B$9*IFERROR(VLOOKUP(C6,Steuerungsdaten!$B$17:$G$37,6,FALSE),1)*POWER(IF(OR(E6=0,F6=0,E6="",F6=""),1,(E6*F6/1000000)/Steuerungsdaten!$B$6),IFERROR(VLOOKUP(C6,Steuerungsdaten!$B$17:$M$37,12,FALSE),1)-1)),0)) -> 368 | R6: =IF(J6="","",ROUND(J6/(Steuerungsdaten!$B$4*Steuerungsdaten!$B$10*IFERROR(VLOOKUP(C6,Steuerungsdaten!$B$17:$I$37,8,FALSE),1)*POWER(IF(OR(E6=0,F6=0,E6="",F6=""),1,(E6*F6/1000000)/Steuerungsdaten!$B$6),IFERROR(VLOOKUP(C6,Steuerungsdaten!$B$17:$N$37,13,FALSE),1)-1)),0)) -> 408
A7: 3001 | B7: Platte | C7: Boden | D7: Boden (420x360) | E7: 420 | F7: 360 | G7: =IF(VLOOKUP(C7,Steuerungsdaten!$P$17:$T$39,2,0)="","",MAX(ROUND(VLOOKUP(C7,Steuerungsdaten!$P$17:$T$39,2,0)*Steuerungsdaten!$B$4*Steuerungsdaten!$B$7*IFERROR(VLOOKUP(C7,Steuerungsdaten!$B$17:$C$37,2,FALSE),1)*POWER(IF(OR(E7=0,F7=0,E7="",F7=""),1,(E7*F7/1000000)/Steuerungsdaten!$B$6),IFERROR(VLOOKUP(C7,Steuerungsdaten!$B$17:$K$37,10,FALSE),1)-1),0),Steuerungsdaten!$E$4)) -> 27 | H7: =IF(VLOOKUP(C7,Steuerungsdaten!$P$17:$T$39,3,0)="","",MAX(ROUND(VLOOKUP(C7,Steuerungsdaten!$P$17:$T$39,3,0)*Steuerungsdaten!$B$4*Steuerungsdaten!$B$8*IFERROR(VLOOKUP(C7,Steuerungsdaten!$B$17:$E$37,4,FALSE),1)*POWER(IF(OR(E7=0,F7=0,E7="",F7=""),1,(E7*F7/1000000)/Steuerungsdaten!$B$6),IFERROR(VLOOKUP(C7,Steuerungsdaten!$B$17:$L$37,11,FALSE),1)-1),0),Steuerungsdaten!$E$5)) -> 103 | I7: =IF(VLOOKUP(C7,Steuerungsdaten!$P$17:$T$39,4,0)="","",MAX(ROUND(VLOOKUP(C7,Steuerungsdaten!$P$17:$T$39,4,0)*Steuerungsdaten!$B$4*Steuerungsdaten!$B$9*IFERROR(VLOOKUP(C7,Steuerungsdaten!$B$17:$G$37,6,FALSE),1)*POWER(IF(OR(E7=0,F7=0,E7="",F7=""),1,(E7*F7/1000000)/Steuerungsdaten!$B$6),IFERROR(VLOOKUP(C7,Steuerungsdaten!$B$17:$M$37,12,FALSE),1)-1),0),Steuerungsdaten!$E$6)) -> 120 | J7: =IF(VLOOKUP(C7,Steuerungsdaten!$P$17:$T$39,5,0)="","",MAX(ROUND(VLOOKUP(C7,Steuerungsdaten!$P$17:$T$39,5,0)*Steuerungsdaten!$B$4*Steuerungsdaten!$B$10*IFERROR(VLOOKUP(C7,Steuerungsdaten!$B$17:$I$37,8,FALSE),1)*POWER(IF(OR(E7=0,F7=0,E7="",F7=""),1,(E7*F7/1000000)/Steuerungsdaten!$B$6),IFERROR(VLOOKUP(C7,Steuerungsdaten!$B$17:$N$37,13,FALSE),1)-1),0),Steuerungsdaten!$E$7)) -> 145 | K7: =IF(G7="","",ROUND(G7*Steuerungsdaten!$B$5,0)) -> 31 | L7: =IF(H7="","",ROUND(H7*Steuerungsdaten!$B$5,0)) -> 118 | M7: =IF(I7="","",ROUND(I7*Steuerungsdaten!$B$5,0)) -> 138 | N7: =IF(J7="","",ROUND(J7*Steuerungsdaten!$B$5,0)) -> 167 | O7: 34 | P7: =IF(H7="","",ROUND(H7/(Steuerungsdaten!$B$4*Steuerungsdaten!$B$8*IFERROR(VLOOKUP(C7,Steuerungsdaten!$B$17:$E$37,4,FALSE),1)*POWER(IF(OR(E7=0,F7=0,E7="",F7=""),1,(E7*F7/1000000)/Steuerungsdaten!$B$6),IFERROR(VLOOKUP(C7,Steuerungsdaten!$B$17:$L$37,11,FALSE),1)-1)),0)) -> 271 | Q7: =IF(I7="","",ROUND(I7/(Steuerungsdaten!$B$4*Steuerungsdaten!$B$9*IFERROR(VLOOKUP(C7,Steuerungsdaten!$B$17:$G$37,6,FALSE),1)*POWER(IF(OR(E7=0,F7=0,E7="",F7=""),1,(E7*F7/1000000)/Steuerungsdaten!$B$6),IFERROR(VLOOKUP(C7,Steuerungsdaten!$B$17:$M$37,12,FALSE),1)-1)),0)) -> 316 | R7: =IF(J7="","",ROUND(J7/(Steuerungsdaten!$B$4*Steuerungsdaten!$B$10*IFERROR(VLOOKUP(C7,Steuerungsdaten!$B$17:$I$37,8,FALSE),1)*POWER(IF(OR(E7=0,F7=0,E7="",F7=""),1,(E7*F7/1000000)/Steuerungsdaten!$B$6),IFERROR(VLOOKUP(C7,Steuerungsdaten!$B$17:$N$37,13,FALSE),1)-1)),0)) -> 350
A8: 3002 | B8: Platte | C8: Boden | D8: Boden (580x360) | E8: 580 | F8: 360 | G8: =IF(VLOOKUP(C8,Steuerungsdaten!$P$17:$T$39,2,0)="","",MAX(ROUND(VLOOKUP(C8,Steuerungsdaten!$P$17:$T$39,2,0)*Steuerungsdaten!$B$4*Steuerungsdaten!$B$7*IFERROR(VLOOKUP(C8,Steuerungsdaten!$B$17:$C$37,2,FALSE),1)*POWER(IF(OR(E8=0,F8=0,E8="",F8=""),1,(E8*F8/1000000)/Steuerungsdaten!$B$6),IFERROR(VLOOKUP(C8,Steuerungsdaten!$B$17:$K$37,10,FALSE),1)-1),0),Steuerungsdaten!$E$4)) -> 37 | H8: =IF(VLOOKUP(C8,Steuerungsdaten!$P$17:$T$39,3,0)="","",MAX(ROUND(VLOOKUP(C8,Steuerungsdaten!$P$17:$T$39,3,0)*Steuerungsdaten!$B$4*Steuerungsdaten!$B$8*IFERROR(VLOOKUP(C8,Steuerungsdaten!$B$17:$E$37,4,FALSE),1)*POWER(IF(OR(E8=0,F8=0,E8="",F8=""),1,(E8*F8/1000000)/Steuerungsdaten!$B$6),IFERROR(VLOOKUP(C8,Steuerungsdaten!$B$17:$L$37,11,FALSE),1)-1),0),Steuerungsdaten!$E$5)) -> 126 | I8: =IF(VLOOKUP(C8,Steuerungsdaten!$P$17:$T$39,4,0)="","",MAX(ROUND(VLOOKUP(C8,Steuerungsdaten!$P$17:$T$39,4,0)*Steuerungsdaten!$B$4*Steuerungsdaten!$B$9*IFERROR(VLOOKUP(C8,Steuerungsdaten!$B$17:$G$37,6,FALSE),1)*POWER(IF(OR(E8=0,F8=0,E8="",F8=""),1,(E8*F8/1000000)/Steuerungsdaten!$B$6),IFERROR(VLOOKUP(C8,Steuerungsdaten!$B$17:$M$37,12,FALSE),1)-1),0),Steuerungsdaten!$E$6)) -> 131 | J8: =IF(VLOOKUP(C8,Steuerungsdaten!$P$17:$T$39,5,0)="","",MAX(ROUND(VLOOKUP(C8,Steuerungsdaten!$P$17:$T$39,5,0)*Steuerungsdaten!$B$4*Steuerungsdaten!$B$10*IFERROR(VLOOKUP(C8,Steuerungsdaten!$B$17:$I$37,8,FALSE),1)*POWER(IF(OR(E8=0,F8=0,E8="",F8=""),1,(E8*F8/1000000)/Steuerungsdaten!$B$6),IFERROR(VLOOKUP(C8,Steuerungsdaten!$B$17:$N$37,13,FALSE),1)-1),0),Steuerungsdaten!$E$7)) -> 146 | K8: =IF(G8="","",ROUND(G8*Steuerungsdaten!$B$5,0)) -> 43 | L8: =IF(H8="","",ROUND(H8*Steuerungsdaten!$B$5,0)) -> 145 | M8: =IF(I8="","",ROUND(I8*Steuerungsdaten!$B$5,0)) -> 151 | N8: =IF(J8="","",ROUND(J8*Steuerungsdaten!$B$5,0)) -> 168 | O8: 43 | P8: =IF(H8="","",ROUND(H8/(Steuerungsdaten!$B$4*Steuerungsdaten!$B$8*IFERROR(VLOOKUP(C8,Steuerungsdaten!$B$17:$E$37,4,FALSE),1)*POWER(IF(OR(E8=0,F8=0,E8="",F8=""),1,(E8*F8/1000000)/Steuerungsdaten!$B$6),IFERROR(VLOOKUP(C8,Steuerungsdaten!$B$17:$L$37,11,FALSE),1)-1)),0)) -> 240 | Q8: =IF(I8="","",ROUND(I8/(Steuerungsdaten!$B$4*Steuerungsdaten!$B$9*IFERROR(VLOOKUP(C8,Steuerungsdaten!$B$17:$G$37,6,FALSE),1)*POWER(IF(OR(E8=0,F8=0,E8="",F8=""),1,(E8*F8/1000000)/Steuerungsdaten!$B$6),IFERROR(VLOOKUP(C8,Steuerungsdaten!$B$17:$M$37,12,FALSE),1)-1)),0)) -> 250 | R8: =IF(J8="","",ROUND(J8/(Steuerungsdaten!$B$4*Steuerungsdaten!$B$10*IFERROR(VLOOKUP(C8,Steuerungsdaten!$B$17:$I$37,8,FALSE),1)*POWER(IF(OR(E8=0,F8=0,E8="",F8=""),1,(E8*F8/1000000)/Steuerungsdaten!$B$6),IFERROR(VLOOKUP(C8,Steuerungsdaten!$B$17:$N$37,13,FALSE),1)-1)),0)) -> 255
A9: 3003 | B9: Platte | C9: Boden | D9: Boden (780x360) | E9: 780 | F9: 360 | G9: =IF(VLOOKUP(C9,Steuerungsdaten!$P$17:$T$39,2,0)="","",MAX(ROUND(VLOOKUP(C9,Steuerungsdaten!$P$17:$T$39,2,0)*Steuerungsdaten!$B$4*Steuerungsdaten!$B$7*IFERROR(VLOOKUP(C9,Steuerungsdaten!$B$17:$C$37,2,FALSE),1)*POWER(IF(OR(E9=0,F9=0,E9="",F9=""),1,(E9*F9/1000000)/Steuerungsdaten!$B$6),IFERROR(VLOOKUP(C9,Steuerungsdaten!$B$17:$K$37,10,FALSE),1)-1),0),Steuerungsdaten!$E$4)) -> 49 | H9: =IF(VLOOKUP(C9,Steuerungsdaten!$P$17:$T$39,3,0)="","",MAX(ROUND(VLOOKUP(C9,Steuerungsdaten!$P$17:$T$39,3,0)*Steuerungsdaten!$B$4*Steuerungsdaten!$B$8*IFERROR(VLOOKUP(C9,Steuerungsdaten!$B$17:$E$37,4,FALSE),1)*POWER(IF(OR(E9=0,F9=0,E9="",F9=""),1,(E9*F9/1000000)/Steuerungsdaten!$B$6),IFERROR(VLOOKUP(C9,Steuerungsdaten!$B$17:$L$37,11,FALSE),1)-1),0),Steuerungsdaten!$E$5)) -> 169 | I9: =IF(VLOOKUP(C9,Steuerungsdaten!$P$17:$T$39,4,0)="","",MAX(ROUND(VLOOKUP(C9,Steuerungsdaten!$P$17:$T$39,4,0)*Steuerungsdaten!$B$4*Steuerungsdaten!$B$9*IFERROR(VLOOKUP(C9,Steuerungsdaten!$B$17:$G$37,6,FALSE),1)*POWER(IF(OR(E9=0,F9=0,E9="",F9=""),1,(E9*F9/1000000)/Steuerungsdaten!$B$6),IFERROR(VLOOKUP(C9,Steuerungsdaten!$B$17:$M$37,12,FALSE),1)-1),0),Steuerungsdaten!$E$6)) -> 177 | J9: =IF(VLOOKUP(C9,Steuerungsdaten!$P$17:$T$39,5,0)="","",MAX(ROUND(VLOOKUP(C9,Steuerungsdaten!$P$17:$T$39,5,0)*Steuerungsdaten!$B$4*Steuerungsdaten!$B$10*IFERROR(VLOOKUP(C9,Steuerungsdaten!$B$17:$I$37,8,FALSE),1)*POWER(IF(OR(E9=0,F9=0,E9="",F9=""),1,(E9*F9/1000000)/Steuerungsdaten!$B$6),IFERROR(VLOOKUP(C9,Steuerungsdaten!$B$17:$N$37,13,FALSE),1)-1),0),Steuerungsdaten!$E$7)) -> 196 | K9: =IF(G9="","",ROUND(G9*Steuerungsdaten!$B$5,0)) -> 56 | L9: =IF(H9="","",ROUND(H9*Steuerungsdaten!$B$5,0)) -> 194 | M9: =IF(I9="","",ROUND(I9*Steuerungsdaten!$B$5,0)) -> 204 | N9: =IF(J9="","",ROUND(J9*Steuerungsdaten!$B$5,0)) -> 225 | O9: 56 | P9: =IF(H9="","",ROUND(H9/(Steuerungsdaten!$B$4*Steuerungsdaten!$B$8*IFERROR(VLOOKUP(C9,Steuerungsdaten!$B$17:$E$37,4,FALSE),1)*POWER(IF(OR(E9=0,F9=0,E9="",F9=""),1,(E9*F9/1000000)/Steuerungsdaten!$B$6),IFERROR(VLOOKUP(C9,Steuerungsdaten!$B$17:$L$37,11,FALSE),1)-1)),0)) -> 239 | Q9: =IF(I9="","",ROUND(I9/(Steuerungsdaten!$B$4*Steuerungsdaten!$B$9*IFERROR(VLOOKUP(C9,Steuerungsdaten!$B$17:$G$37,6,FALSE),1)*POWER(IF(OR(E9=0,F9=0,E9="",F9=""),1,(E9*F9/1000000)/Steuerungsdaten!$B$6),IFERROR(VLOOKUP(C9,Steuerungsdaten!$B$17:$M$37,12,FALSE),1)-1)),0)) -> 251 | R9: =IF(J9="","",ROUND(J9/(Steuerungsdaten!$B$4*Steuerungsdaten!$B$10*IFERROR(VLOOKUP(C9,Steuerungsdaten!$B$17:$I$37,8,FALSE),1)*POWER(IF(OR(E9=0,F9=0,E9="",F9=""),1,(E9*F9/1000000)/Steuerungsdaten!$B$6),IFERROR(VLOOKUP(C9,Steuerungsdaten!$B$17:$N$37,13,FALSE),1)-1)),0)) -> 254
